<?xml version='1.0' encoding='UTF-8'?>
<text id="lion_van_bourges">
  <l n="1" tokens="Bi daghe bi nachte" lemmas="bij dag bij nacht">
    <w>
      <form>Bi</form>
      <lemma>bij</lemma>
      <pos>ADP(type=pre)</pos>
    </w>
    <w>
      <form>daghe</form>
      <lemma>dag</lemma>
      <pos>NOU-C(number=sg)</pos>
    </w>
    <w>
      <form>bi</form>
      <lemma>bij</lemma>
      <pos>ADP(type=pre)</pos>
    </w>
    <w>
      <form>nachte</form>
      <lemma>nacht</lemma>
      <pos>NOU-C(number=sg)</pos>
    </w>
  </l>
  <l n="2" tokens="Soe hayde hijt sijt seker das" lemmas="zo haaien hij+het zijn zeker das">
    <w>
      <form>Soe</form>
      <lemma>zo</lemma>
      <pos>ADV(type=reg)</pos>
    </w>
    <w>
      <form>hayde</form>
      <lemma>haaien</lemma>
      <pos>VRB(finiteness=fin,tense=past)</pos>
    </w>
    <w>
      <form>hijt</form>
      <lemma>hij+het</lemma>
      <pos>PD(type=pers,position=free)+PD(type=pers,position=free)</pos>
    </w>
    <w>
      <form>sijt</form>
      <lemma>zijn</lemma>
      <pos>VRB(finiteness=fin,tense=pres)+PD(type=pers,position=free)</pos>
    </w>
    <w>
      <form>seker</form>
      <lemma>zeker</lemma>
      <pos>AA(degree=pos,position=free)</pos>
    </w>
    <w>
      <form>das</form>
      <lemma>das</lemma>
      <pos>CONJ(type=sub)</pos>
    </w>
  </l>
  <l n="3" tokens="Soe ic hebbe verstaen overwaer" lemmas="zo ik hebben verstaan overwaar">
    <w>
      <form>Soe</form>
      <lemma>zo</lemma>
      <pos>CONJ(type=sub)</pos>
    </w>
    <w>
      <form>ic</form>
      <lemma>ik</lemma>
      <pos>PD(type=pers,position=free)</pos>
    </w>
    <w>
      <form>hebbe</form>
      <lemma>hebben</lemma>
      <pos>VRB(finiteness=fin,tense=pres)</pos>
    </w>
    <w>
      <form>verstaen</form>
      <lemma>verstaan</lemma>
      <pos>VRB(finiteness=pastpart)</pos>
    </w>
    <w>
      <form>overwaer</form>
      <lemma>overwaar</lemma>
      <pos>AA(degree=pos,position=free)</pos>
    </w>
  </l>
  <l n="4" tokens="In die martrie VII XII jaer" lemmas="in die martrie zeven twaalf jaar">
    <w>
      <form>In</form>
      <lemma>in</lemma>
      <pos>ADP(type=pre)</pos>
    </w>
    <w>
      <form>die</form>
      <lemma>die</lemma>
      <pos>PD(type=d-p,subtype=art,position=prenom)</pos>
    </w>
    <w>
      <form>martrie</form>
      <lemma>martrie</lemma>
      <pos>NOU-C(number=sg)</pos>
    </w>
    <w>
      <form>VII</form>
      <lemma>zeven</lemma>
      <pos>NUM(type=ord,position=prenom,representation=rom)</pos>
    </w>
    <w>
      <form>XII</form>
      <lemma>twaalf</lemma>
      <pos>NUM(type=ord,position=prenom,representation=rom)</pos>
    </w>
    <w>
      <form>jaer</form>
      <lemma>jaar</lemma>
      <pos>NOU-C(number=sg)</pos>
    </w>
  </l>
  <l n="5" tokens="Die vrouwe en conste weten niet" lemmas="die vrouwe ne kunnen weten niet">
    <w>
      <form>Die</form>
      <lemma>die</lemma>
      <pos>PD(type=d-p,subtype=art,position=prenom)</pos>
    </w>
    <w>
      <form>vrouwe</form>
      <lemma>vrouwe</lemma>
      <pos>NOU-C(number=sg)</pos>
    </w>
    <w>
      <form>en</form>
      <lemma>ne</lemma>
      <pos>ADV(type=reg)</pos>
    </w>
    <w>
      <form>conste</form>
      <lemma>kunnen</lemma>
      <pos>VRB(finiteness=fin,tense=past)</pos>
    </w>
    <w>
      <form>weten</form>
      <lemma>weten</lemma>
      <pos>VRB(finiteness=inf)</pos>
    </w>
    <w>
      <form>niet</form>
      <lemma>niet</lemma>
      <pos>ADV(type=reg)</pos>
    </w>
  </l>
  <l n="6" tokens="Van hem des dogede si verdriet" lemmas="van hij des deugen zij verdriet">
    <w>
      <form>Van</form>
      <lemma>van</lemma>
      <pos>ADP(type=pre)</pos>
    </w>
    <w>
      <form>hem</form>
      <lemma>hij</lemma>
      <pos>PD(type=pers,position=free)</pos>
    </w>
    <w>
      <form>des</form>
      <lemma>des</lemma>
      <pos>ADV(type=reg)</pos>
    </w>
    <w>
      <form>dogede</form>
      <lemma>deugen</lemma>
      <pos>VRB(finiteness=fin,tense=past)</pos>
    </w>
    <w>
      <form>si</form>
      <lemma>zij</lemma>
      <pos>PD(type=pers,position=free)</pos>
    </w>
    <w>
      <form>verdriet</form>
      <lemma>verdriet</lemma>
      <pos>NOU-C(number=sg)</pos>
    </w>
  </l>
  <l n="7" tokens="Weder hi soude behouden tleven" lemmas="weder hij zullen behouden dat+leven">
    <w>
      <form>Weder</form>
      <lemma>weder</lemma>
      <pos>ADV(type=reg)</pos>
    </w>
    <w>
      <form>hi</form>
      <lemma>hij</lemma>
      <pos>PD(type=pers,position=free)</pos>
    </w>
    <w>
      <form>soude</form>
      <lemma>zullen</lemma>
      <pos>VRB(finiteness=fin,tense=past)</pos>
    </w>
    <w>
      <form>behouden</form>
      <lemma>behouden</lemma>
      <pos>VRB(finiteness=inf)</pos>
    </w>
    <w>
      <form>tleven</form>
      <lemma>dat+leven</lemma>
      <pos>PD(type=d-p,subtype=art,position=prenom)+NOU-C(number=sg)</pos>
    </w>
  </l>
  <l n="8" tokens="Oft dat hi doot ware bleven" lemmas="of dat hij dood zijn blijven">
    <w>
      <form>Oft</form>
      <lemma>of</lemma>
      <pos>CONJ(type=coor)</pos>
    </w>
    <w>
      <form>dat</form>
      <lemma>dat</lemma>
      <pos>CONJ(type=sub)</pos>
    </w>
    <w>
      <form>hi</form>
      <lemma>hij</lemma>
      <pos>PD(type=pers,position=free)</pos>
    </w>
    <w>
      <form>doot</form>
      <lemma>dood</lemma>
      <pos>AA(degree=pos,position=free)</pos>
    </w>
    <w>
      <form>ware</form>
      <lemma>zijn</lemma>
      <pos>VRB(finiteness=fin,tense=past)</pos>
    </w>
    <w>
      <form>bleven</form>
      <lemma>blijven</lemma>
      <pos>VRB(finiteness=fin,tense=past)</pos>
    </w>
  </l>
  <l n="9" tokens="Dat en was der vrouwen niet cont" lemmas="dat ne zijn de vrouw niet kond">
    <w>
      <form>Dat</form>
      <lemma>dat</lemma>
      <pos>PD(type=d-p,position=free)</pos>
    </w>
    <w>
      <form>en</form>
      <lemma>ne</lemma>
      <pos>ADV(type=reg)</pos>
    </w>
    <w>
      <form>was</form>
      <lemma>zijn</lemma>
      <pos>VRB(finiteness=fin,tense=past)</pos>
    </w>
    <w>
      <form>der</form>
      <lemma>de</lemma>
      <pos>PD(type=d-p,subtype=art,position=prenom)</pos>
    </w>
    <w>
      <form>vrouwen</form>
      <lemma>vrouw</lemma>
      <pos>NOU-C(number=pl)</pos>
    </w>
    <w>
      <form>niet</form>
      <lemma>niet</lemma>
      <pos>ADV(type=reg)</pos>
    </w>
    <w>
      <form>cont</form>
      <lemma>kond</lemma>
      <pos>AA(degree=pos,position=free)</pos>
    </w>
  </l>
  <l n="10" tokens="Doen geviel up enen stont" lemmas="toen gevallen op een stonde">
    <w>
      <form>Doen</form>
      <lemma>toen</lemma>
      <pos>ADV(type=reg)</pos>
    </w>
    <w>
      <form>geviel</form>
      <lemma>gevallen</lemma>
      <pos>VRB(finiteness=fin,tense=past)</pos>
    </w>
    <w>
      <form>up</form>
      <lemma>op</lemma>
      <pos>ADP(type=pre)</pos>
    </w>
    <w>
      <form>enen</form>
      <lemma>een</lemma>
      <pos>PD(type=indef,subtype=art,position=prenom)</pos>
    </w>
    <w>
      <form>stont</form>
      <lemma>stonde</lemma>
      <pos>NOU-C(number=sg)</pos>
    </w>
  </l>
  <l n="11" tokens="Dat die heyden wijch leiden" lemmas="dat die heide wagen leiden">
    <w>
      <form>Dat</form>
      <lemma>dat</lemma>
      <pos>CONJ(type=sub)</pos>
    </w>
    <w>
      <form>die</form>
      <lemma>die</lemma>
      <pos>PD(type=d-p,subtype=art,position=prenom)</pos>
    </w>
    <w>
      <form>heyden</form>
      <lemma>heide</lemma>
      <pos>NOU-C(number=sg)</pos>
    </w>
    <w>
      <form>wijch</form>
      <lemma>wagen</lemma>
      <pos>VRB(finiteness=fin,tense=past)</pos>
    </w>
    <w>
      <form>leiden</form>
      <lemma>leiden</lemma>
      <pos>VRB(finiteness=inf)</pos>
    </w>
  </l>
  <l n="12" tokens="Jegen die kersten ander heiden" lemmas="jegen die kerst ander heide">
    <w>
      <form>Jegen</form>
      <lemma>jegen</lemma>
      <pos>ADP(type=pre)</pos>
    </w>
    <w>
      <form>die</form>
      <lemma>die</lemma>
      <pos>PD(type=d-p,subtype=art,position=prenom)</pos>
    </w>
    <w>
      <form>kersten</form>
      <lemma>kerst</lemma>
      <pos>NOU-C(number=sg)</pos>
    </w>
    <w>
      <form>ander</form>
      <lemma>ander</lemma>
      <pos>PD(type=indef,subtype=oth,position=prenom)</pos>
    </w>
    <w>
      <form>heiden</form>
      <lemma>heide</lemma>
      <pos>NOU-C(number=sg)</pos>
    </w>
  </l>
  <l n="13" tokens="Te vechten op enen tijt" lemmas="te vechten op een tijd">
    <w>
      <form>Te</form>
      <lemma>te</lemma>
      <pos>ADP(type=pre)</pos>
    </w>
    <w>
      <form>vechten</form>
      <lemma>vechten</lemma>
      <pos>VRB(finiteness=inf)</pos>
    </w>
    <w>
      <form>op</form>
      <lemma>op</lemma>
      <pos>ADP(type=pre)</pos>
    </w>
    <w>
      <form>enen</form>
      <lemma>een</lemma>
      <pos>PD(type=indef,subtype=art,position=prenom)</pos>
    </w>
    <w>
      <form>tijt</form>
      <lemma>tijd</lemma>
      <pos>NOU-C(number=sg)</pos>
    </w>
  </l>
  <l n="14" tokens="Ende als die dach quam dattie strijt" lemmas="en als die dag komen dat+de strijd">
    <w>
      <form>Ende</form>
      <lemma>en</lemma>
      <pos>CONJ(type=coor)</pos>
    </w>
    <w>
      <form>als</form>
      <lemma>als</lemma>
      <pos>CONJ(type=sub)</pos>
    </w>
    <w>
      <form>die</form>
      <lemma>die</lemma>
      <pos>PD(type=d-p,subtype=art,position=prenom)</pos>
    </w>
    <w>
      <form>dach</form>
      <lemma>dag</lemma>
      <pos>NOU-C(number=sg)</pos>
    </w>
    <w>
      <form>quam</form>
      <lemma>komen</lemma>
      <pos>VRB(finiteness=fin,tense=past)</pos>
    </w>
    <w>
      <form>dattie</form>
      <lemma>dat+de</lemma>
      <pos>CONJ(type=sub)+PD(type=d-p,subtype=art,position=prenom)</pos>
    </w>
    <w>
      <form>strijt</form>
      <lemma>strijd</lemma>
      <pos>NOU-C(number=sg)</pos>
    </w>
  </l>
  <l n="15" tokens="Wesen soude na mijn verstaen" lemmas="wezen zullen na mijn verstaan">
    <w>
      <form>Wesen</form>
      <lemma>wezen</lemma>
      <pos>VRB(finiteness=inf)</pos>
    </w>
    <w>
      <form>soude</form>
      <lemma>zullen</lemma>
      <pos>VRB(finiteness=fin,tense=past)</pos>
    </w>
    <w>
      <form>na</form>
      <lemma>na</lemma>
      <pos>ADP(type=pre)</pos>
    </w>
    <w>
      <form>mijn</form>
      <lemma>mijn</lemma>
      <pos>PD(type=poss,position=prenom)</pos>
    </w>
    <w>
      <form>verstaen</form>
      <lemma>verstaan</lemma>
      <pos>NOU-C(number=sg)</pos>
    </w>
  </l>
  <l n="16" tokens="Doen geboet die heyden soudaen" lemmas="toen boeten die heide zoldoen">
    <w>
      <form>Doen</form>
      <lemma>toen</lemma>
      <pos>ADV(type=reg)</pos>
    </w>
    <w>
      <form>geboet</form>
      <lemma>boeten</lemma>
      <pos>VRB(finiteness=pastpart)</pos>
    </w>
    <w>
      <form>die</form>
      <lemma>die</lemma>
      <pos>PD(type=d-p,subtype=art,position=prenom)</pos>
    </w>
    <w>
      <form>heyden</form>
      <lemma>heide</lemma>
      <pos>NOU-C(number=pl)</pos>
    </w>
    <w>
      <form>soudaen</form>
      <lemma>zoldoen</lemma>
      <pos>VRB(finiteness=fin,tense=past)</pos>
    </w>
  </l>
  <l n="17" tokens="Op lijf op goet sinen lieden" lemmas="op lijf op goed zijn lieden">
    <w>
      <form>Op</form>
      <lemma>op</lemma>
      <pos>ADP(type=pre)</pos>
    </w>
    <w>
      <form>lijf</form>
      <lemma>lijf</lemma>
      <pos>NOU-C(number=sg)</pos>
    </w>
    <w>
      <form>op</form>
      <lemma>op</lemma>
      <pos>ADP(type=pre)</pos>
    </w>
    <w>
      <form>goet</form>
      <lemma>goed</lemma>
      <pos>NOU-C(number=sg)</pos>
    </w>
    <w>
      <form>sinen</form>
      <lemma>zijn</lemma>
      <pos>PD(type=poss,position=prenom)</pos>
    </w>
    <w>
      <form>lieden</form>
      <lemma>lieden</lemma>
      <pos>NOU-C(number=pl)</pos>
    </w>
  </l>
  <l n="18" tokens="Dat si alle gader spieden" lemmas="dat zij al gader spieden">
    <w>
      <form>Dat</form>
      <lemma>dat</lemma>
      <pos>CONJ(type=sub)</pos>
    </w>
    <w>
      <form>si</form>
      <lemma>zij</lemma>
      <pos>PD(type=pers,position=free)</pos>
    </w>
    <w>
      <form>alle</form>
      <lemma>al</lemma>
      <pos>ADV(type=reg)</pos>
    </w>
    <w>
      <form>gader</form>
      <lemma>gader</lemma>
      <pos>ADV(type=reg)</pos>
    </w>
    <w>
      <form>spieden</form>
      <lemma>spieden</lemma>
      <pos>VRB(finiteness=fin,tense=past)</pos>
    </w>
  </l>
  <l n="19" tokens="Na den leitsman van den here" lemmas="na de leidsman van de heer">
    <w>
      <form>Na</form>
      <lemma>na</lemma>
      <pos>ADP(type=pre)</pos>
    </w>
    <w>
      <form>den</form>
      <lemma>de</lemma>
      <pos>PD(type=d-p,subtype=art,position=prenom)</pos>
    </w>
    <w>
      <form>leitsman</form>
      <lemma>leidsman</lemma>
      <pos>NOU-C(number=sg)</pos>
    </w>
    <w>
      <form>van</form>
      <lemma>van</lemma>
      <pos>ADP(type=pre)</pos>
    </w>
    <w>
      <form>den</form>
      <lemma>de</lemma>
      <pos>PD(type=d-p,subtype=art,position=prenom)</pos>
    </w>
    <w>
      <form>here</form>
      <lemma>heer</lemma>
      <pos>NOU-C(number=sg)</pos>
    </w>
  </l>
  <l n="20" tokens="Ende dat si pijnden met gere" lemmas="en dat zij pijnen met geer">
    <w>
      <form>Ende</form>
      <lemma>en</lemma>
      <pos>CONJ(type=coor)</pos>
    </w>
    <w>
      <form>dat</form>
      <lemma>dat</lemma>
      <pos>CONJ(type=sub)</pos>
    </w>
    <w>
      <form>si</form>
      <lemma>zij</lemma>
      <pos>PD(type=pers,position=free)</pos>
    </w>
    <w>
      <form>pijnden</form>
      <lemma>pijnen</lemma>
      <pos>VRB(finiteness=fin,tense=past)</pos>
    </w>
    <w>
      <form>met</form>
      <lemma>met</lemma>
      <pos>ADP(type=pre)</pos>
    </w>
    <w>
      <form>gere</form>
      <lemma>geer</lemma>
      <pos>NOU-C(number=sg)</pos>
    </w>
  </l>
  <l n="21" tokens="Dat sine leverden gevaen" lemmas="dat zijn leveren vangen">
    <w>
      <form>Dat</form>
      <lemma>dat</lemma>
      <pos>CONJ(type=sub)</pos>
    </w>
    <w>
      <form>sine</form>
      <lemma>zijn</lemma>
      <pos>PD(type=pers,position=free)+PD(type=pers,position=free)</pos>
    </w>
    <w>
      <form>leverden</form>
      <lemma>leveren</lemma>
      <pos>VRB(finiteness=fin,tense=past)</pos>
    </w>
    <w>
      <form>gevaen</form>
      <lemma>vangen</lemma>
      <pos>VRB(finiteness=pastpart)</pos>
    </w>
  </l>
  <l n="22" tokens="Doe waren sijn consten al gedaen" lemmas="toen zijn zijn kunst al doen">
    <w>
      <form>Doe</form>
      <lemma>toen</lemma>
      <pos>ADV(type=reg)</pos>
    </w>
    <w>
      <form>waren</form>
      <lemma>zijn</lemma>
      <pos>VRB(finiteness=fin,tense=past)</pos>
    </w>
    <w>
      <form>sijn</form>
      <lemma>zijn</lemma>
      <pos>PD(type=poss,position=prenom)</pos>
    </w>
    <w>
      <form>consten</form>
      <lemma>kunst</lemma>
      <pos>NOU-C(number=pl)</pos>
    </w>
    <w>
      <form>al</form>
      <lemma>al</lemma>
      <pos>ADV(type=reg)</pos>
    </w>
    <w>
      <form>gedaen</form>
      <lemma>doen</lemma>
      <pos>VRB(finiteness=pastpart)</pos>
    </w>
  </l>
  <l n="23" tokens="Soe dat sijn here moest faelgeren" lemmas="zo dat zijn heer moeten failleren">
    <w>
      <form>Soe</form>
      <lemma>zo</lemma>
      <pos>CONJ(type=sub)</pos>
    </w>
    <w>
      <form>dat</form>
      <lemma>dat</lemma>
      <pos>CONJ(type=sub)</pos>
    </w>
    <w>
      <form>sijn</form>
      <lemma>zijn</lemma>
      <pos>PD(type=poss,position=prenom)</pos>
    </w>
    <w>
      <form>here</form>
      <lemma>heer</lemma>
      <pos>NOU-C(number=sg)</pos>
    </w>
    <w>
      <form>moest</form>
      <lemma>moeten</lemma>
      <pos>VRB(finiteness=fin,tense=past)</pos>
    </w>
    <w>
      <form>faelgeren</form>
      <lemma>failleren</lemma>
      <pos>VRB(finiteness=inf)</pos>
    </w>
  </l>
  <l n="24" tokens="Ende si vingen se met gewelt" lemmas="en zij vangen zij met geweld">
    <w>
      <form>Ende</form>
      <lemma>en</lemma>
      <pos>CONJ(type=coor)</pos>
    </w>
    <w>
      <form>si</form>
      <lemma>zij</lemma>
      <pos>PD(type=pers,position=free)</pos>
    </w>
    <w>
      <form>vingen</form>
      <lemma>vangen</lemma>
      <pos>VRB(finiteness=fin,tense=past)</pos>
    </w>
    <w>
      <form>se</form>
      <lemma>zij</lemma>
      <pos>PD(type=pers,position=free)</pos>
    </w>
    <w>
      <form>met</form>
      <lemma>met</lemma>
      <pos>ADP(type=pre)</pos>
    </w>
    <w>
      <form>gewelt</form>
      <lemma>geweld</lemma>
      <pos>NOU-C(number=sg)</pos>
    </w>
  </l>
  <l n="25" tokens="Doen bleven die kersten ongestelt ongescelt" lemmas="toen blijven die kerst ongesteld ongescheld">
    <w>
      <form>Doen</form>
      <lemma>toen</lemma>
      <pos>ADV(type=reg)</pos>
    </w>
    <w>
      <form>bleven</form>
      <lemma>blijven</lemma>
      <pos>VRB(finiteness=fin,tense=past)</pos>
    </w>
    <w>
      <form>die</form>
      <lemma>die</lemma>
      <pos>PD(type=d-p,subtype=art,position=prenom)</pos>
    </w>
    <w>
      <form>kersten</form>
      <lemma>kerst</lemma>
      <pos>NOU-C(number=pl)</pos>
    </w>
    <w>
      <form>ongestelt</form>
      <lemma>ongesteld</lemma>
      <pos>AA(degree=pos,position=free)</pos>
    </w>
    <w>
      <form>ongescelt</form>
      <lemma>ongescheld</lemma>
      <pos>AA(degree=pos,position=free)</pos>
    </w>
  </l>
  <l n="26" tokens="Ende herde droeve utermaten" lemmas="en hard droef uitermate">
    <w>
      <form>Ende</form>
      <lemma>en</lemma>
      <pos>CONJ(type=coor)</pos>
    </w>
    <w>
      <form>herde</form>
      <lemma>hard</lemma>
      <pos>ADV(type=reg)</pos>
    </w>
    <w>
      <form>droeve</form>
      <lemma>droef</lemma>
      <pos>NOU-C(number=pl)</pos>
    </w>
    <w>
      <form>utermaten</form>
      <lemma>uitermate</lemma>
      <pos>ADV(type=reg)</pos>
    </w>
  </l>
  <l n="27" tokens="Ende elc vloe wech sijnre straten" lemmas="en elk vlieden wegdoen zijn straat">
    <w>
      <form>Ende</form>
      <lemma>en</lemma>
      <pos>CONJ(type=coor)</pos>
    </w>
    <w>
      <form>elc</form>
      <lemma>elk</lemma>
      <pos>PD(type=indef,position=free)</pos>
    </w>
    <w>
      <form>vloe</form>
      <lemma>vlieden</lemma>
      <pos>VRB(finiteness=fin,tense=past)</pos>
    </w>
    <w>
      <form>wech</form>
      <lemma>wegdoen</lemma>
      <pos>VRB(finiteness=fin,tense=past)</pos>
    </w>
    <w>
      <form>sijnre</form>
      <lemma>zijn</lemma>
      <pos>PD(type=poss,position=prenom)</pos>
    </w>
    <w>
      <form>straten</form>
      <lemma>straat</lemma>
      <pos>NOU-C(number=pl)</pos>
    </w>
  </l>
  <l n="28" tokens="Ende die heyden voerden wech den here" lemmas="en die heide voeren wegdoen de heer">
    <w>
      <form>Ende</form>
      <lemma>en</lemma>
      <pos>CONJ(type=coor)</pos>
    </w>
    <w>
      <form>die</form>
      <lemma>die</lemma>
      <pos>PD(type=d-p,subtype=art,position=prenom)</pos>
    </w>
    <w>
      <form>heyden</form>
      <lemma>heide</lemma>
      <pos>NOU-C(number=pl)</pos>
    </w>
    <w>
      <form>voerden</form>
      <lemma>voeren</lemma>
      <pos>VRB(finiteness=fin,tense=past)</pos>
    </w>
    <w>
      <form>wech</form>
      <lemma>wegdoen</lemma>
      <pos>VRB(finiteness=fin,tense=past)</pos>
    </w>
    <w>
      <form>den</form>
      <lemma>de</lemma>
      <pos>PD(type=d-p,subtype=art,position=prenom)</pos>
    </w>
    <w>
      <form>here</form>
      <lemma>heer</lemma>
      <pos>NOU-C(number=sg)</pos>
    </w>
  </l>
  <l n="29" tokens="Des droefdi uter maten sere" lemmas="des droeven+gij uiter maat zeer">
    <w>
      <form>Des</form>
      <lemma>des</lemma>
      <pos>ADV(type=reg)</pos>
    </w>
    <w>
      <form>droefdi</form>
      <lemma>droeven+gij</lemma>
      <pos>VRB(finiteness=fin,tense=past)+PD(type=pers,position=free)</pos>
    </w>
    <w>
      <form>uter</form>
      <lemma>uiter</lemma>
      <pos>ADV(type=reg)</pos>
    </w>
    <w>
      <form>maten</form>
      <lemma>maat</lemma>
      <pos>NOU-C(number=sg)</pos>
    </w>
    <w>
      <form>sere</form>
      <lemma>zeer</lemma>
      <pos>ADV(type=reg)</pos>
    </w>
  </l>
  <l n="30" tokens="Doe leidemen wech dats waer" lemmas="toen leiden+men wegdoen dat+zijn zijn">
    <w>
      <form>Doe</form>
      <lemma>toen</lemma>
      <pos>ADV(type=reg)</pos>
    </w>
    <w>
      <form>leidemen</form>
      <lemma>leiden+men</lemma>
      <pos>VRB(finiteness=fin,tense=past)+PD(type=pers,position=free)</pos>
    </w>
    <w>
      <form>wech</form>
      <lemma>wegdoen</lemma>
      <pos>VRB(finiteness=fin,tense=past)</pos>
    </w>
    <w>
      <form>dats</form>
      <lemma>dat+zijn</lemma>
      <pos>PD(type=d-p,position=free)+VRB(finiteness=fin,tense=pres)</pos>
    </w>
    <w>
      <form>waer</form>
      <lemma>zijn</lemma>
      <pos>VRB(finiteness=fin,tense=past)</pos>
    </w>
  </l>
  <l n="31" tokens="In enen kerkere waer hi III jaer" lemmas="in een kerker waar hij drie jaar">
    <w>
      <form>In</form>
      <lemma>in</lemma>
      <pos>ADP(type=pre)</pos>
    </w>
    <w>
      <form>enen</form>
      <lemma>een</lemma>
      <pos>PD(type=indef,subtype=art,position=prenom)</pos>
    </w>
    <w>
      <form>kerkere</form>
      <lemma>kerker</lemma>
      <pos>NOU-C(number=sg)</pos>
    </w>
    <w>
      <form>waer</form>
      <lemma>waar</lemma>
      <pos>ADV(type=reg)</pos>
    </w>
    <w>
      <form>hi</form>
      <lemma>hij</lemma>
      <pos>PD(type=pers,position=free)</pos>
    </w>
    <w>
      <form>III</form>
      <lemma>drie</lemma>
      <pos>NUM(type=card,position=prenom,representation=rom)</pos>
    </w>
    <w>
      <form>jaer</form>
      <lemma>jaar</lemma>
      <pos>NOU-C(number=sg)</pos>
    </w>
  </l>
  <l n="32" tokens="In dochde groten noot" lemmas="in deugd groot noot">
    <w>
      <form>In</form>
      <lemma>in</lemma>
      <pos>ADP(type=pre)</pos>
    </w>
    <w>
      <form>dochde</form>
      <lemma>deugd</lemma>
      <pos>NOU-C(number=sg)</pos>
    </w>
    <w>
      <form>groten</form>
      <lemma>groot</lemma>
      <pos>AA(degree=pos,position=prenom)</pos>
    </w>
    <w>
      <form>noot</form>
      <lemma>noot</lemma>
      <pos>NOU-C(number=sg)</pos>
    </w>
  </l>
  <l n="33" tokens="Ende altoos pensdi om die doot" lemmas="en altoos peinzen+du om die dood">
    <w>
      <form>Ende</form>
      <lemma>en</lemma>
      <pos>CONJ(type=coor)</pos>
    </w>
    <w>
      <form>altoos</form>
      <lemma>altoos</lemma>
      <pos>ADV(type=reg)</pos>
    </w>
    <w>
      <form>pensdi</form>
      <lemma>peinzen+du</lemma>
      <pos>VRB(finiteness=fin,tense=past)+PD(type=pers,position=free)</pos>
    </w>
    <w>
      <form>om</form>
      <lemma>om</lemma>
      <pos>ADP(type=pre)</pos>
    </w>
    <w>
      <form>die</form>
      <lemma>die</lemma>
      <pos>PD(type=d-p,subtype=art,position=prenom)</pos>
    </w>
    <w>
      <form>doot</form>
      <lemma>dood</lemma>
      <pos>NOU-C(number=sg)</pos>
    </w>
  </l>
  <l n="34" tokens="Ende om die passie die Christus leet" lemmas="en om die passie die Christus lijden">
    <w>
      <form>Ende</form>
      <lemma>en</lemma>
      <pos>CONJ(type=coor)</pos>
    </w>
    <w>
      <form>om</form>
      <lemma>om</lemma>
      <pos>ADP(type=pre)</pos>
    </w>
    <w>
      <form>die</form>
      <lemma>die</lemma>
      <pos>PD(type=d-p,subtype=art,position=prenom)</pos>
    </w>
    <w>
      <form>passie</form>
      <lemma>passie</lemma>
      <pos>NOU-C(number=sg)</pos>
    </w>
    <w>
      <form>die</form>
      <lemma>die</lemma>
      <pos>PD(type=d-p,position=free)</pos>
    </w>
    <w>
      <form>Christus</form>
      <lemma>Christus</lemma>
      <pos>NOU-P</pos>
    </w>
    <w>
      <form>leet</form>
      <lemma>lijden</lemma>
      <pos>VRB(finiteness=fin,tense=past)</pos>
    </w>
  </l>
  <l n="35" tokens="Doen hi voer hem anden cruce street" lemmas="toen hij voor hij aan+de kruis strijden">
    <w>
      <form>Doen</form>
      <lemma>toen</lemma>
      <pos>CONJ(type=sub)</pos>
    </w>
    <w>
      <form>hi</form>
      <lemma>hij</lemma>
      <pos>PD(type=pers,position=free)</pos>
    </w>
    <w>
      <form>voer</form>
      <lemma>voor</lemma>
      <pos>ADP(type=pre)</pos>
    </w>
    <w>
      <form>hem</form>
      <lemma>hij</lemma>
      <pos>PD(type=pers,position=free)</pos>
    </w>
    <w>
      <form>anden</form>
      <lemma>aan+de</lemma>
      <pos>ADP(type=pre)+PD(type=d-p,subtype=art,position=prenom)</pos>
    </w>
    <w>
      <form>cruce</form>
      <lemma>kruis</lemma>
      <pos>NOU-C(number=sg)</pos>
    </w>
    <w>
      <form>street</form>
      <lemma>strijden</lemma>
      <pos>VRB(finiteness=fin,tense=past)</pos>
    </w>
  </l>
  <l n="36" tokens="Doen hi hadde lange daer" lemmas="toen hij hebben lang daar">
    <w>
      <form>Doen</form>
      <lemma>toen</lemma>
      <pos>CONJ(type=sub)</pos>
    </w>
    <w>
      <form>hi</form>
      <lemma>hij</lemma>
      <pos>PD(type=pers,position=free)</pos>
    </w>
    <w>
      <form>hadde</form>
      <lemma>hebben</lemma>
      <pos>VRB(finiteness=fin,tense=past)</pos>
    </w>
    <w>
      <form>lange</form>
      <lemma>lang</lemma>
      <pos>ADV(type=reg)</pos>
    </w>
    <w>
      <form>daer</form>
      <lemma>daar</lemma>
      <pos>ADV(type=reg)</pos>
    </w>
  </l>
  <l n="37" tokens="Gelegen in den kerker swaer" lemmas="liggen in de kerker zwaar">
    <w>
      <form>Gelegen</form>
      <lemma>liggen</lemma>
      <pos>VRB(finiteness=pastpart)</pos>
    </w>
    <w>
      <form>in</form>
      <lemma>in</lemma>
      <pos>ADP(type=pre)</pos>
    </w>
    <w>
      <form>den</form>
      <lemma>de</lemma>
      <pos>PD(type=d-p,subtype=art,position=prenom)</pos>
    </w>
    <w>
      <form>kerker</form>
      <lemma>kerker</lemma>
      <pos>NOU-C(number=sg)</pos>
    </w>
    <w>
      <form>swaer</form>
      <lemma>zwaar</lemma>
      <pos>AA(degree=pos,position=free)</pos>
    </w>
  </l>
  <l n="38" tokens="Doen was comen die tijt" lemmas="toen zijn komen die tijd">
    <w>
      <form>Doen</form>
      <lemma>toen</lemma>
      <pos>ADV(type=reg)</pos>
    </w>
    <w>
      <form>was</form>
      <lemma>zijn</lemma>
      <pos>VRB(finiteness=fin,tense=past)</pos>
    </w>
    <w>
      <form>comen</form>
      <lemma>komen</lemma>
      <pos>VRB(finiteness=pastpart)</pos>
    </w>
    <w>
      <form>die</form>
      <lemma>die</lemma>
      <pos>PD(type=d-p,subtype=art,position=prenom)</pos>
    </w>
    <w>
      <form>tijt</form>
      <lemma>tijd</lemma>
      <pos>NOU-C(number=sg)</pos>
    </w>
  </l>
  <l n="39" tokens="Dattie soudaen geen respijt" lemmas="dat+de soudaan geen respijt">
    <w>
      <form>Dattie</form>
      <lemma>dat+de</lemma>
      <pos>CONJ(type=sub)+PD(type=d-p,subtype=art,position=prenom)</pos>
    </w>
    <w>
      <form>soudaen</form>
      <lemma>soudaan</lemma>
      <pos>NOU-C(number=sg)</pos>
    </w>
    <w>
      <form>geen</form>
      <lemma>geen</lemma>
      <pos>PD(type=indef,subtype=oth,position=prenom)</pos>
    </w>
    <w>
      <form>respijt</form>
      <lemma>respijt</lemma>
      <pos>NOU-C(number=sg)</pos>
    </w>
  </l>
  <l n="40" tokens="Den here langer wilde geven" lemmas="de heer lang willen geven">
    <w>
      <form>Den</form>
      <lemma>de</lemma>
      <pos>PD(type=d-p,subtype=art,position=prenom)</pos>
    </w>
    <w>
      <form>here</form>
      <lemma>heer</lemma>
      <pos>NOU-C(number=sg)</pos>
    </w>
    <w>
      <form>langer</form>
      <lemma>lang</lemma>
      <pos>AA(degree=comp,position=free)</pos>
    </w>
    <w>
      <form>wilde</form>
      <lemma>willen</lemma>
      <pos>VRB(finiteness=fin,tense=past)</pos>
    </w>
    <w>
      <form>geven</form>
      <lemma>geven</lemma>
      <pos>VRB(finiteness=inf)</pos>
    </w>
  </l>
  <l n="41" tokens="Hine woude hem nemen tleven" lemmas="hij+ne willen hij nemen dat+leven">
    <w>
      <form>Hine</form>
      <lemma>hij+ne</lemma>
      <pos>PD(type=pers,position=free)+ADV(type=reg)</pos>
    </w>
    <w>
      <form>woude</form>
      <lemma>willen</lemma>
      <pos>VRB(finiteness=fin,tense=past)</pos>
    </w>
    <w>
      <form>hem</form>
      <lemma>hij</lemma>
      <pos>PD(type=pers,position=free)</pos>
    </w>
    <w>
      <form>nemen</form>
      <lemma>nemen</lemma>
      <pos>VRB(finiteness=inf)</pos>
    </w>
    <w>
      <form>tleven</form>
      <lemma>dat+leven</lemma>
      <pos>PD(type=d-p,subtype=art,position=prenom)+NOU-C(number=sg)</pos>
    </w>
  </l>
  <l n="42" tokens="Oft hi en geloefde an sinen Mamet" lemmas="of hij ne geloven aan zijn Mamet">
    <w>
      <form>Oft</form>
      <lemma>of</lemma>
      <pos>CONJ(type=sub)</pos>
    </w>
    <w>
      <form>hi</form>
      <lemma>hij</lemma>
      <pos>PD(type=pers,position=free)</pos>
    </w>
    <w>
      <form>en</form>
      <lemma>ne</lemma>
      <pos>ADV(type=reg)</pos>
    </w>
    <w>
      <form>geloefde</form>
      <lemma>geloven</lemma>
      <pos>VRB(finiteness=fin,tense=past)</pos>
    </w>
    <w>
      <form>an</form>
      <lemma>aan</lemma>
      <pos>ADP(type=pre)</pos>
    </w>
    <w>
      <form>sinen</form>
      <lemma>zijn</lemma>
      <pos>PD(type=poss,position=prenom)</pos>
    </w>
    <w>
      <form>Mamet</form>
      <lemma>Mamet</lemma>
      <pos>NOU-C(number=sg)</pos>
    </w>
  </l>
  <l n="43" tokens="Ende liete varen sine wet" lemmas="en laten varen zijn wet">
    <w>
      <form>Ende</form>
      <lemma>en</lemma>
      <pos>CONJ(type=coor)</pos>
    </w>
    <w>
      <form>liete</form>
      <lemma>laten</lemma>
      <pos>VRB(finiteness=fin,tense=past)</pos>
    </w>
    <w>
      <form>varen</form>
      <lemma>varen</lemma>
      <pos>VRB(finiteness=inf)</pos>
    </w>
    <w>
      <form>sine</form>
      <lemma>zijn</lemma>
      <pos>PD(type=poss,position=prenom)</pos>
    </w>
    <w>
      <form>wet</form>
      <lemma>wet</lemma>
      <pos>NOU-C(number=sg)</pos>
    </w>
  </l>
  <l n="44" tokens="Doen dede die here maken" lemmas="toen doen die heer maken">
    <w>
      <form>Doen</form>
      <lemma>toen</lemma>
      <pos>ADV(type=reg)</pos>
    </w>
    <w>
      <form>dede</form>
      <lemma>doen</lemma>
      <pos>VRB(finiteness=fin,tense=past)</pos>
    </w>
    <w>
      <form>die</form>
      <lemma>die</lemma>
      <pos>PD(type=d-p,subtype=art,position=prenom)</pos>
    </w>
    <w>
      <form>here</form>
      <lemma>heer</lemma>
      <pos>NOU-C(number=sg)</pos>
    </w>
    <w>
      <form>maken</form>
      <lemma>maken</lemma>
      <pos>VRB(finiteness=inf)</pos>
    </w>
  </l>
  <l n="45" tokens="Alle tormentelike saken" lemmas="al tormentelijk zaak">
    <w>
      <form>Alle</form>
      <lemma>al</lemma>
      <pos>PD(type=indef,subtype=oth,position=prenom)</pos>
    </w>
    <w>
      <form>tormentelike</form>
      <lemma>tormentelijk</lemma>
      <pos>AA(degree=pos,position=prenom)</pos>
    </w>
    <w>
      <form>saken</form>
      <lemma>zaak</lemma>
      <pos>NOU-C(number=pl)</pos>
    </w>
  </l>
  <l n="46" tokens="Ende laten onsen Mamet" lemmas="en laten ons Mamet">
    <w>
      <form>Ende</form>
      <lemma>en</lemma>
      <pos>CONJ(type=coor)</pos>
    </w>
    <w>
      <form>laten</form>
      <lemma>laten</lemma>
      <pos>VRB(finiteness=inf)</pos>
    </w>
    <w>
      <form>onsen</form>
      <lemma>ons</lemma>
      <pos>PD(type=poss,position=prenom)</pos>
    </w>
    <w>
      <form>Mamet</form>
      <lemma>Mamet</lemma>
      <pos>NOU-C(number=sg)</pos>
    </w>
  </l>
  <l n="47" tokens="Ende volgen uwe wet" lemmas="en volgen uw wet">
    <w>
      <form>Ende</form>
      <lemma>en</lemma>
      <pos>CONJ(type=coor)</pos>
    </w>
    <w>
      <form>volgen</form>
      <lemma>volgen</lemma>
      <pos>VRB(finiteness=inf)</pos>
    </w>
    <w>
      <form>uwe</form>
      <lemma>uw</lemma>
      <pos>PD(type=poss,position=prenom)</pos>
    </w>
    <w>
      <form>wet</form>
      <lemma>wet</lemma>
      <pos>NOU-C(number=sg)</pos>
    </w>
  </l>
  <l n="48" tokens="Heymelijc daer ic mach" lemmas="heimelijk daar ik mogen">
    <w>
      <form>Heymelijc</form>
      <lemma>heimelijk</lemma>
      <pos>AA(degree=pos,position=free)</pos>
    </w>
    <w>
      <form>daer</form>
      <lemma>daar</lemma>
      <pos>ADV(type=reg)</pos>
    </w>
    <w>
      <form>ic</form>
      <lemma>ik</lemma>
      <pos>PD(type=pers,position=free)</pos>
    </w>
    <w>
      <form>mach</form>
      <lemma>mogen</lemma>
      <pos>VRB(finiteness=fin,tense=pres)</pos>
    </w>
  </l>
  <l n="49" tokens="Op dat ghi op desen dach" lemmas="op dat gij op deze dag">
    <w>
      <form>Op</form>
      <lemma>op</lemma>
      <pos>CONJ(type=sub)</pos>
    </w>
    <w>
      <form>dat</form>
      <lemma>dat</lemma>
      <pos>CONJ(type=sub)</pos>
    </w>
    <w>
      <form>ghi</form>
      <lemma>gij</lemma>
      <pos>PD(type=pers,position=free)</pos>
    </w>
    <w>
      <form>op</form>
      <lemma>op</lemma>
      <pos>ADP(type=pre)</pos>
    </w>
    <w>
      <form>desen</form>
      <lemma>deze</lemma>
      <pos>PD(type=d-p,subtype=oth,position=prenom)</pos>
    </w>
    <w>
      <form>dach</form>
      <lemma>dag</lemma>
      <pos>NOU-C(number=sg)</pos>
    </w>
  </l>
  <l n="50" tokens="Uwe wet avegaet" lemmas="uw wet afgaan">
    <w>
      <form>Uwe</form>
      <lemma>uw</lemma>
      <pos>PD(type=poss,position=prenom)</pos>
    </w>
    <w>
      <form>wet</form>
      <lemma>wet</lemma>
      <pos>NOU-C(number=sg)</pos>
    </w>
    <w>
      <form>avegaet</form>
      <lemma>afgaan</lemma>
      <pos>VRB(finiteness=fin,tense=pres)</pos>
    </w>
  </l>
  <l n="51" tokens="Metten monde ende donse ontfaet" lemmas="met+de mond en de+onze ontvangen">
    <w>
      <form>Metten</form>
      <lemma>met+de</lemma>
      <pos>ADP(type=pre)+PD(type=d-p,subtype=art,position=prenom)</pos>
    </w>
    <w>
      <form>monde</form>
      <lemma>mond</lemma>
      <pos>NOU-C(number=sg)</pos>
    </w>
    <w>
      <form>ende</form>
      <lemma>en</lemma>
      <pos>CONJ(type=coor)</pos>
    </w>
    <w>
      <form>donse</form>
      <lemma>de+onze</lemma>
      <pos>PD(type=d-p,subtype=art,position=prenom)+NOU-C(number=sg)</pos>
    </w>
    <w>
      <form>ontfaet</form>
      <lemma>ontvangen</lemma>
      <pos>VRB(finiteness=fin,tense=pres)</pos>
    </w>
  </l>
  <l n="52" tokens="Hi pensde al waert sonde" lemmas="hij peinzen al zijn+het sonde">
    <w>
      <form>Hi</form>
      <lemma>hij</lemma>
      <pos>PD(type=pers,position=free)</pos>
    </w>
    <w>
      <form>pensde</form>
      <lemma>peinzen</lemma>
      <pos>VRB(finiteness=fin,tense=past)</pos>
    </w>
    <w>
      <form>al</form>
      <lemma>al</lemma>
      <pos>CONJ(type=sub)</pos>
    </w>
    <w>
      <form>waert</form>
      <lemma>zijn+het</lemma>
      <pos>VRB(finiteness=fin,tense=past)+PD(type=pers,position=free)</pos>
    </w>
    <w>
      <form>sonde</form>
      <lemma>sonde</lemma>
      <pos>NOU-C(number=sg)</pos>
    </w>
  </l>
  <l n="53" tokens="Hi soude Gods afgaen metten monde" lemmas="hij zullen God afgaan met+de mond">
    <w>
      <form>Hi</form>
      <lemma>hij</lemma>
      <pos>PD(type=pers,position=free)</pos>
    </w>
    <w>
      <form>soude</form>
      <lemma>zullen</lemma>
      <pos>VRB(finiteness=fin,tense=past)</pos>
    </w>
    <w>
      <form>Gods</form>
      <lemma>God</lemma>
      <pos>NOU-P</pos>
    </w>
    <w>
      <form>afgaen</form>
      <lemma>afgaan</lemma>
      <pos>VRB(finiteness=inf)</pos>
    </w>
    <w>
      <form>metten</form>
      <lemma>met+de</lemma>
      <pos>ADP(type=pre)+PD(type=d-p,subtype=art,position=prenom)</pos>
    </w>
    <w>
      <form>monde</form>
      <lemma>mond</lemma>
      <pos>NOU-C(number=sg)</pos>
    </w>
  </l>
  <l n="54" tokens="Maer het soude besloten bliven" lemmas="maar het zullen besluiten blijven">
    <w>
      <form>Maer</form>
      <lemma>maar</lemma>
      <pos>CONJ(type=coor)</pos>
    </w>
    <w>
      <form>het</form>
      <lemma>het</lemma>
      <pos>PD(type=pers,position=free)</pos>
    </w>
    <w>
      <form>soude</form>
      <lemma>zullen</lemma>
      <pos>VRB(finiteness=fin,tense=past)</pos>
    </w>
    <w>
      <form>besloten</form>
      <lemma>besluiten</lemma>
      <pos>VRB(finiteness=pastpart)</pos>
    </w>
    <w>
      <form>bliven</form>
      <lemma>blijven</lemma>
      <pos>VRB(finiteness=inf)</pos>
    </w>
  </l>
  <l n="55" tokens="In sijn herte sonder verdriven" lemmas="in zijn hart zonder verdrijven">
    <w>
      <form>In</form>
      <lemma>in</lemma>
      <pos>ADP(type=pre)</pos>
    </w>
    <w>
      <form>sijn</form>
      <lemma>zijn</lemma>
      <pos>PD(type=poss,position=prenom)</pos>
    </w>
    <w>
      <form>herte</form>
      <lemma>hart</lemma>
      <pos>NOU-C(number=sg)</pos>
    </w>
    <w>
      <form>sonder</form>
      <lemma>zonder</lemma>
      <pos>ADP(type=pre)</pos>
    </w>
    <w>
      <form>verdriven</form>
      <lemma>verdrijven</lemma>
      <pos>NOU-C(number=sg)</pos>
    </w>
  </l>
  <l n="56" tokens="Doen bat hi Gode doer genaden" lemmas="toen bet hij God door genade">
    <w>
      <form>Doen</form>
      <lemma>toen</lemma>
      <pos>ADV(type=reg)</pos>
    </w>
    <w>
      <form>bat</form>
      <lemma>bet</lemma>
      <pos>ADV(type=reg)</pos>
    </w>
    <w>
      <form>hi</form>
      <lemma>hij</lemma>
      <pos>PD(type=pers,position=free)</pos>
    </w>
    <w>
      <form>Gode</form>
      <lemma>God</lemma>
      <pos>NOU-P</pos>
    </w>
    <w>
      <form>doer</form>
      <lemma>door</lemma>
      <pos>ADP(type=pre)</pos>
    </w>
    <w>
      <form>genaden</form>
      <lemma>genade</lemma>
      <pos>NOU-C(number=sg)</pos>
    </w>
  </l>
  <l n="57" tokens="Datti hem vergave die mesdaden" lemmas="dat+gij hij vergeven die misdaad">
    <w>
      <form>Datti</form>
      <lemma>dat+gij</lemma>
      <pos>CONJ(type=sub)+PD(type=pers,position=free)</pos>
    </w>
    <w>
      <form>hem</form>
      <lemma>hij</lemma>
      <pos>PD(type=pers,position=free)</pos>
    </w>
    <w>
      <form>vergave</form>
      <lemma>vergeven</lemma>
      <pos>VRB(finiteness=fin,tense=past)</pos>
    </w>
    <w>
      <form>die</form>
      <lemma>die</lemma>
      <pos>PD(type=d-p,subtype=art,position=prenom)</pos>
    </w>
    <w>
      <form>mesdaden</form>
      <lemma>misdaad</lemma>
      <pos>NOU-C(number=pl)</pos>
    </w>
  </l>
  <l n="58" tokens="Die hi moeste doen doer den noot" lemmas="die hij moeten doen door de noot">
    <w>
      <form>Die</form>
      <lemma>die</lemma>
      <pos>PD(type=d-p,position=free)</pos>
    </w>
    <w>
      <form>hi</form>
      <lemma>hij</lemma>
      <pos>PD(type=pers,position=free)</pos>
    </w>
    <w>
      <form>moeste</form>
      <lemma>moeten</lemma>
      <pos>VRB(finiteness=fin,tense=past)</pos>
    </w>
    <w>
      <form>doen</form>
      <lemma>doen</lemma>
      <pos>VRB(finiteness=inf)</pos>
    </w>
    <w>
      <form>doer</form>
      <lemma>door</lemma>
      <pos>ADP(type=pre)</pos>
    </w>
    <w>
      <form>den</form>
      <lemma>de</lemma>
      <pos>PD(type=d-p,subtype=art,position=prenom)</pos>
    </w>
    <w>
      <form>noot</form>
      <lemma>noot</lemma>
      <pos>NOU-C(number=sg)</pos>
    </w>
  </l>
  <l n="59" tokens="Vander anxteliker doot" lemmas="van+de angstelijk dood">
    <w>
      <form>Vander</form>
      <lemma>van+de</lemma>
      <pos>ADP(type=pre)+PD(type=d-p,subtype=art,position=prenom)</pos>
    </w>
    <w>
      <form>anxteliker</form>
      <lemma>angstelijk</lemma>
      <pos>AA(degree=pos,position=prenom)</pos>
    </w>
    <w>
      <form>doot</form>
      <lemma>dood</lemma>
      <pos>NOU-C(number=sg)</pos>
    </w>
  </l>
  <l n="60" tokens="Doen waert hi daer sarasijn" lemmas="toen worden hij daar Saracijn">
    <w>
      <form>Doen</form>
      <lemma>toen</lemma>
      <pos>ADV(type=reg)</pos>
    </w>
    <w>
      <form>waert</form>
      <lemma>worden</lemma>
      <pos>VRB(finiteness=fin,tense=past)</pos>
    </w>
    <w>
      <form>hi</form>
      <lemma>hij</lemma>
      <pos>PD(type=pers,position=free)</pos>
    </w>
    <w>
      <form>daer</form>
      <lemma>daar</lemma>
      <pos>ADV(type=reg)</pos>
    </w>
    <w>
      <form>sarasijn</form>
      <lemma>Saracijn</lemma>
      <pos>NOU-P</pos>
    </w>
  </l>
  <l n="61" tokens="Inden worde dat was in scine" lemmas="in+de woord dat zijn in schijn">
    <w>
      <form>Inden</form>
      <lemma>in+de</lemma>
      <pos>ADP(type=pre)+PD(type=d-p,subtype=art,position=prenom)</pos>
    </w>
    <w>
      <form>worde</form>
      <lemma>woord</lemma>
      <pos>NOU-C(number=sg)</pos>
    </w>
    <w>
      <form>dat</form>
      <lemma>dat</lemma>
      <pos>PD(type=d-p,position=free)</pos>
    </w>
    <w>
      <form>was</form>
      <lemma>zijn</lemma>
      <pos>VRB(finiteness=fin,tense=past)</pos>
    </w>
    <w>
      <form>in</form>
      <lemma>in</lemma>
      <pos>ADP(type=pre)</pos>
    </w>
    <w>
      <form>scine</form>
      <lemma>schijn</lemma>
      <pos>NOU-C(number=sg)</pos>
    </w>
  </l>
  <l n="62" tokens="Maer int herte was hijs niet" lemmas="maar in+het hart zijn hij+dat niet">
    <w>
      <form>Maer</form>
      <lemma>maar</lemma>
      <pos>CONJ(type=coor)</pos>
    </w>
    <w>
      <form>int</form>
      <lemma>in+het</lemma>
      <pos>ADP(type=pre)+PD(type=d-p,subtype=art,position=prenom)</pos>
    </w>
    <w>
      <form>herte</form>
      <lemma>hart</lemma>
      <pos>NOU-C(number=sg)</pos>
    </w>
    <w>
      <form>was</form>
      <lemma>zijn</lemma>
      <pos>VRB(finiteness=fin,tense=past)</pos>
    </w>
    <w>
      <form>hijs</form>
      <lemma>hij+dat</lemma>
      <pos>PD(type=pers,position=free)+PD(type=d-p,position=free)</pos>
    </w>
    <w>
      <form>niet</form>
      <lemma>niet</lemma>
      <pos>ADV(type=reg)</pos>
    </w>
  </l>
  <l n="63" tokens="Die soudaen beval ende hiet" lemmas="die soudaan bevallen en heten">
    <w>
      <form>Die</form>
      <lemma>die</lemma>
      <pos>PD(type=d-p,subtype=art,position=prenom)</pos>
    </w>
    <w>
      <form>soudaen</form>
      <lemma>soudaan</lemma>
      <pos>NOU-C(number=sg)</pos>
    </w>
    <w>
      <form>beval</form>
      <lemma>bevallen</lemma>
      <pos>VRB(finiteness=fin,tense=past)</pos>
    </w>
    <w>
      <form>ende</form>
      <lemma>en</lemma>
      <pos>CONJ(type=coor)</pos>
    </w>
    <w>
      <form>hiet</form>
      <lemma>heten</lemma>
      <pos>VRB(finiteness=fin,tense=past)</pos>
    </w>
  </l>
  <l n="64" tokens="Sijnre dochter metter vaert" lemmas="zijn dochter met+de vaart">
    <w>
      <form>Sijnre</form>
      <lemma>zijn</lemma>
      <pos>PD(type=poss,position=prenom)</pos>
    </w>
    <w>
      <form>dochter</form>
      <lemma>dochter</lemma>
      <pos>NOU-C(number=sg)</pos>
    </w>
    <w>
      <form>metter</form>
      <lemma>met+de</lemma>
      <pos>ADP(type=pre)+PD(type=d-p,subtype=art,position=prenom)</pos>
    </w>
    <w>
      <form>vaert</form>
      <lemma>vaart</lemma>
      <pos>NOU-C(number=sg)</pos>
    </w>
  </l>
  <l n="65" tokens="Dat sine troude onghespaert" lemmas="dat zijn trouwen ongespaard">
    <w>
      <form>Dat</form>
      <lemma>dat</lemma>
      <pos>CONJ(type=sub)</pos>
    </w>
    <w>
      <form>sine</form>
      <lemma>zijn</lemma>
      <pos>PD(type=poss,position=prenom)</pos>
    </w>
    <w>
      <form>troude</form>
      <lemma>trouwen</lemma>
      <pos>VRB(finiteness=fin,tense=past)</pos>
    </w>
    <w>
      <form>onghespaert</form>
      <lemma>ongespaard</lemma>
      <pos>AA(degree=pos,position=free)</pos>
    </w>
  </l>
  <l n="66" tokens="Na die maniere van der wet" lemmas="na die manier van de wet">
    <w>
      <form>Na</form>
      <lemma>na</lemma>
      <pos>ADP(type=pre)</pos>
    </w>
    <w>
      <form>die</form>
      <lemma>die</lemma>
      <pos>PD(type=d-p,subtype=art,position=prenom)</pos>
    </w>
    <w>
      <form>maniere</form>
      <lemma>manier</lemma>
      <pos>NOU-C(number=sg)</pos>
    </w>
    <w>
      <form>van</form>
      <lemma>van</lemma>
      <pos>ADP(type=pre)</pos>
    </w>
    <w>
      <form>der</form>
      <lemma>de</lemma>
      <pos>PD(type=d-p,subtype=art,position=prenom)</pos>
    </w>
    <w>
      <form>wet</form>
      <lemma>wet</lemma>
      <pos>NOU-C(number=sg)</pos>
    </w>
  </l>
  <l n="67" tokens="In groten stade was hi geset" lemmas="in groot stade zijn hij zetten">
    <w>
      <form>In</form>
      <lemma>in</lemma>
      <pos>ADP(type=pre)</pos>
    </w>
    <w>
      <form>groten</form>
      <lemma>groot</lemma>
      <pos>AA(degree=pos,position=prenom)</pos>
    </w>
    <w>
      <form>stade</form>
      <lemma>stade</lemma>
      <pos>NOU-C(number=sg)</pos>
    </w>
    <w>
      <form>was</form>
      <lemma>zijn</lemma>
      <pos>VRB(finiteness=fin,tense=past)</pos>
    </w>
    <w>
      <form>hi</form>
      <lemma>hij</lemma>
      <pos>PD(type=pers,position=free)</pos>
    </w>
    <w>
      <form>geset</form>
      <lemma>zetten</lemma>
      <pos>VRB(finiteness=pastpart)</pos>
    </w>
  </l>
  <l n="68" tokens="Want hi maecten al te hant" lemmas="want hij maken al te hand">
    <w>
      <form>Want</form>
      <lemma>want</lemma>
      <pos>CONJ(type=coor)</pos>
    </w>
    <w>
      <form>hi</form>
      <lemma>hij</lemma>
      <pos>PD(type=pers,position=free)</pos>
    </w>
    <w>
      <form>maecten</form>
      <lemma>maken</lemma>
      <pos>VRB(finiteness=fin,tense=past)+PD(type=pers,position=free)</pos>
    </w>
    <w>
      <form>al</form>
      <lemma>al</lemma>
      <pos>ADV(type=reg)</pos>
    </w>
    <w>
      <form>te</form>
      <lemma>te</lemma>
      <pos>ADV(type=reg)</pos>
    </w>
    <w>
      <form>hant</form>
      <lemma>hand</lemma>
      <pos>ADV(type=reg)</pos>
    </w>
  </l>
  <l n="69" tokens="Coninc over al sijn lant" lemmas="koning over al zijn land">
    <w>
      <form>Coninc</form>
      <lemma>koning</lemma>
      <pos>NOU-C(number=sg)</pos>
    </w>
    <w>
      <form>over</form>
      <lemma>over</lemma>
      <pos>ADP(type=pre)</pos>
    </w>
    <w>
      <form>al</form>
      <lemma>al</lemma>
      <pos>PD(type=indef,position=free)</pos>
    </w>
    <w>
      <form>sijn</form>
      <lemma>zijn</lemma>
      <pos>PD(type=poss,position=prenom)</pos>
    </w>
    <w>
      <form>lant</form>
      <lemma>land</lemma>
      <pos>NOU-C(number=sg)</pos>
    </w>
  </l>
  <l n="70" tokens="Watti hiet dat dede men saen" lemmas="wat+gij heten dat doen men zaan">
    <w>
      <form>Watti</form>
      <lemma>wat+gij</lemma>
      <pos>ADV(type=reg)+PD(type=pers,position=free)</pos>
    </w>
    <w>
      <form>hiet</form>
      <lemma>heten</lemma>
      <pos>VRB(finiteness=fin,tense=past)</pos>
    </w>
    <w>
      <form>dat</form>
      <lemma>dat</lemma>
      <pos>PD(type=d-p,position=free)</pos>
    </w>
    <w>
      <form>dede</form>
      <lemma>doen</lemma>
      <pos>VRB(finiteness=fin,tense=past)</pos>
    </w>
    <w>
      <form>men</form>
      <lemma>men</lemma>
      <pos>PD(type=pers,position=free)</pos>
    </w>
    <w>
      <form>saen</form>
      <lemma>zaan</lemma>
      <pos>ADV(type=reg)</pos>
    </w>
  </l>
  <l n="71" tokens="Watti verboet dat liet men staen" lemmas="wat+gij verboeten dat laten men staan">
    <w>
      <form>Watti</form>
      <lemma>wat+gij</lemma>
      <pos>PD(type=d-p,position=free)+PD(type=pers,position=free)</pos>
    </w>
    <w>
      <form>verboet</form>
      <lemma>verboeten</lemma>
      <pos>VRB(finiteness=fin,tense=past)</pos>
    </w>
    <w>
      <form>dat</form>
      <lemma>dat</lemma>
      <pos>PD(type=d-p,position=free)</pos>
    </w>
    <w>
      <form>liet</form>
      <lemma>laten</lemma>
      <pos>VRB(finiteness=fin,tense=past)</pos>
    </w>
    <w>
      <form>men</form>
      <lemma>men</lemma>
      <pos>PD(type=pers,position=free)</pos>
    </w>
    <w>
      <form>staen</form>
      <lemma>staan</lemma>
      <pos>VRB(finiteness=inf)</pos>
    </w>
  </l>
  <l n="72" tokens="Hi wert leitsman op de Sarasine" lemmas="hij worden leidsman op de Saracijn">
    <w>
      <form>Hi</form>
      <lemma>hij</lemma>
      <pos>PD(type=pers,position=free)</pos>
    </w>
    <w>
      <form>wert</form>
      <lemma>worden</lemma>
      <pos>VRB(finiteness=fin,tense=past)</pos>
    </w>
    <w>
      <form>leitsman</form>
      <lemma>leidsman</lemma>
      <pos>NOU-C(number=sg)</pos>
    </w>
    <w>
      <form>op</form>
      <lemma>op</lemma>
      <pos>ADP(type=pre)</pos>
    </w>
    <w>
      <form>de</form>
      <lemma>de</lemma>
      <pos>PD(type=d-p,subtype=art,position=prenom)</pos>
    </w>
    <w>
      <form>Sarasine</form>
      <lemma>Saracijn</lemma>
      <pos>NOU-C(number=sg)</pos>
    </w>
  </l>
  <l n="73" tokens="Ende voer vechten op die Kerstine" lemmas="en voeren vechten op die kersten">
    <w>
      <form>Ende</form>
      <lemma>en</lemma>
      <pos>CONJ(type=coor)</pos>
    </w>
    <w>
      <form>voer</form>
      <lemma>voeren</lemma>
      <pos>VRB(finiteness=fin,tense=past)</pos>
    </w>
    <w>
      <form>vechten</form>
      <lemma>vechten</lemma>
      <pos>VRB(finiteness=inf)</pos>
    </w>
    <w>
      <form>op</form>
      <lemma>op</lemma>
      <pos>ADP(type=pre)</pos>
    </w>
    <w>
      <form>die</form>
      <lemma>die</lemma>
      <pos>PD(type=d-p,subtype=art,position=prenom)</pos>
    </w>
    <w>
      <form>Kerstine</form>
      <lemma>kersten</lemma>
      <pos>NOU-C(number=sg)</pos>
    </w>
  </l>
  <l n="74" tokens="Daer hijt met eren mochte laten gaen" lemmas="daar hij+het met eer mogen laten gaan">
    <w>
      <form>Daer</form>
      <lemma>daar</lemma>
      <pos>ADV(type=reg)</pos>
    </w>
    <w>
      <form>hijt</form>
      <lemma>hij+het</lemma>
      <pos>PD(type=pers,position=free)+PD(type=pers,position=free)</pos>
    </w>
    <w>
      <form>met</form>
      <lemma>met</lemma>
      <pos>ADP(type=pre)</pos>
    </w>
    <w>
      <form>eren</form>
      <lemma>eer</lemma>
      <pos>NOU-C(number=sg)</pos>
    </w>
    <w>
      <form>mochte</form>
      <lemma>mogen</lemma>
      <pos>VRB(finiteness=fin,tense=past)</pos>
    </w>
    <w>
      <form>laten</form>
      <lemma>laten</lemma>
      <pos>VRB(finiteness=inf)</pos>
    </w>
    <w>
      <form>gaen</form>
      <lemma>gaan</lemma>
      <pos>VRB(finiteness=inf)</pos>
    </w>
  </l>
  <l n="75" tokens="En dodi niemant maer gevaen" lemmas="ne doden+hij niemand maar vangen">
    <w>
      <form>En</form>
      <lemma>ne</lemma>
      <pos>ADV(type=reg)</pos>
    </w>
    <w>
      <form>dodi</form>
      <lemma>doden+hij</lemma>
      <pos>VRB(finiteness=fin,tense=past)+PD(type=pers,position=free)</pos>
    </w>
    <w>
      <form>niemant</form>
      <lemma>niemand</lemma>
      <pos>PD(type=indef,position=free)</pos>
    </w>
    <w>
      <form>maer</form>
      <lemma>maar</lemma>
      <pos>CONJ(type=coor)</pos>
    </w>
    <w>
      <form>gevaen</form>
      <lemma>vangen</lemma>
      <pos>VRB(finiteness=pastpart)</pos>
    </w>
  </l>
  <l n="76" tokens="Nochtan dede hise tot meniger stont" lemmas="nochtan doen hij+zij tot menig stonde">
    <w>
      <form>Nochtan</form>
      <lemma>nochtan</lemma>
      <pos>ADV(type=reg)</pos>
    </w>
    <w>
      <form>dede</form>
      <lemma>doen</lemma>
      <pos>VRB(finiteness=fin,tense=past)</pos>
    </w>
    <w>
      <form>hise</form>
      <lemma>hij+zij</lemma>
      <pos>PD(type=pers,position=free)+PD(type=pers,position=free)</pos>
    </w>
    <w>
      <form>tot</form>
      <lemma>tot</lemma>
      <pos>ADP(type=pre)</pos>
    </w>
    <w>
      <form>meniger</form>
      <lemma>menig</lemma>
      <pos>PD(type=indef,subtype=oth,position=prenom)</pos>
    </w>
    <w>
      <form>stont</form>
      <lemma>stonde</lemma>
      <pos>NOU-C(number=sg)</pos>
    </w>
  </l>
  <l n="77" tokens="Om te stoppene den mont" lemmas="om te stoppen de mond">
    <w>
      <form>Om</form>
      <lemma>om</lemma>
      <pos>ADP(type=pre)</pos>
    </w>
    <w>
      <form>te</form>
      <lemma>te</lemma>
      <pos>ADP(type=pre)</pos>
    </w>
    <w>
      <form>stoppene</form>
      <lemma>stoppen</lemma>
      <pos>VRB(finiteness=inf)</pos>
    </w>
    <w>
      <form>den</form>
      <lemma>de</lemma>
      <pos>PD(type=d-p,subtype=art,position=prenom)</pos>
    </w>
    <w>
      <form>mont</form>
      <lemma>mond</lemma>
      <pos>NOU-C(number=sg)</pos>
    </w>
  </l>
  <l n="78" tokens="Der heyden daer hi clene trouwe" lemmas="de heide daar hij klein trouw">
    <w>
      <form>Der</form>
      <lemma>de</lemma>
      <pos>PD(type=d-p,subtype=art,position=prenom)</pos>
    </w>
    <w>
      <form>heyden</form>
      <lemma>heide</lemma>
      <pos>NOU-C(number=sg)</pos>
    </w>
    <w>
      <form>daer</form>
      <lemma>daar</lemma>
      <pos>ADV(type=pron)</pos>
    </w>
    <w>
      <form>hi</form>
      <lemma>hij</lemma>
      <pos>PD(type=pers,position=free)</pos>
    </w>
    <w>
      <form>clene</form>
      <lemma>klein</lemma>
      <pos>AA(degree=pos,position=prenom)</pos>
    </w>
    <w>
      <form>trouwe</form>
      <lemma>trouw</lemma>
      <pos>NOU-C(number=sg)</pos>
    </w>
  </l>
  <l n="79" tokens="In hadde maer die scone vrouwe" lemmas="in hebben maar die schoon vrouwe">
    <w>
      <form>In</form>
      <lemma>in</lemma>
      <pos>ADV(type=pron)</pos>
    </w>
    <w>
      <form>hadde</form>
      <lemma>hebben</lemma>
      <pos>VRB(finiteness=fin,tense=past)</pos>
    </w>
    <w>
      <form>maer</form>
      <lemma>maar</lemma>
      <pos>CONJ(type=coor)</pos>
    </w>
    <w>
      <form>die</form>
      <lemma>die</lemma>
      <pos>PD(type=d-p,subtype=art,position=prenom)</pos>
    </w>
    <w>
      <form>scone</form>
      <lemma>schoon</lemma>
      <pos>AA(degree=pos,position=prenom)</pos>
    </w>
    <w>
      <form>vrouwe</form>
      <lemma>vrouwe</lemma>
      <pos>NOU-C(number=sg)</pos>
    </w>
  </l>
  <l n="80" tokens="Mindi utermaten sere" lemmas="minnen+gij uitermate zeer">
    <w>
      <form>Mindi</form>
      <lemma>minnen+gij</lemma>
      <pos>VRB(finiteness=fin,tense=past)+PD(type=pers,position=free)</pos>
    </w>
    <w>
      <form>utermaten</form>
      <lemma>uitermate</lemma>
      <pos>ADV(type=reg)</pos>
    </w>
    <w>
      <form>sere</form>
      <lemma>zeer</lemma>
      <pos>ADV(type=reg)</pos>
    </w>
  </l>
  <l n="81" tokens="Al die liefde ende die ere" lemmas="al die liefde en die eer">
    <w>
      <form>Al</form>
      <lemma>al</lemma>
      <pos>PD(type=indef,position=free)</pos>
    </w>
    <w>
      <form>die</form>
      <lemma>die</lemma>
      <pos>PD(type=d-p,subtype=art,position=prenom)</pos>
    </w>
    <w>
      <form>liefde</form>
      <lemma>liefde</lemma>
      <pos>NOU-C(number=sg)</pos>
    </w>
    <w>
      <form>ende</form>
      <lemma>en</lemma>
      <pos>CONJ(type=coor)</pos>
    </w>
    <w>
      <form>die</form>
      <lemma>die</lemma>
      <pos>PD(type=d-p,subtype=art,position=prenom)</pos>
    </w>
    <w>
      <form>ere</form>
      <lemma>eer</lemma>
      <pos>NOU-C(number=sg)</pos>
    </w>
  </l>
  <l n="82" tokens="Die si hem gedoen conde" lemmas="die zij hij gedoen kunnen">
    <w>
      <form>Die</form>
      <lemma>die</lemma>
      <pos>PD(type=d-p,position=free)</pos>
    </w>
    <w>
      <form>si</form>
      <lemma>zij</lemma>
      <pos>PD(type=pers,position=free)</pos>
    </w>
    <w>
      <form>hem</form>
      <lemma>hij</lemma>
      <pos>PD(type=pers,position=free)</pos>
    </w>
    <w>
      <form>gedoen</form>
      <lemma>gedoen</lemma>
      <pos>VRB(finiteness=inf)</pos>
    </w>
    <w>
      <form>conde</form>
      <lemma>kunnen</lemma>
      <pos>VRB(finiteness=fin,tense=past)</pos>
    </w>
  </l>
  <l n="83" tokens="Deedse hem met goeden gronde" lemmas="doen+zij hij met goed grond">
    <w>
      <form>Deedse</form>
      <lemma>doen+zij</lemma>
      <pos>VRB(finiteness=fin,tense=past)+PD(type=pers,position=free)</pos>
    </w>
    <w>
      <form>hem</form>
      <lemma>hij</lemma>
      <pos>PD(type=pers,position=free)</pos>
    </w>
    <w>
      <form>met</form>
      <lemma>met</lemma>
      <pos>ADP(type=pre)</pos>
    </w>
    <w>
      <form>goeden</form>
      <lemma>goed</lemma>
      <pos>AA(degree=pos,position=prenom)</pos>
    </w>
    <w>
      <form>gronde</form>
      <lemma>grond</lemma>
      <pos>NOU-C(number=sg)</pos>
    </w>
  </l>
  <l n="84" tokens="Elc was anderen gerne bi" lemmas="elk zijn ander gaarne bij">
    <w>
      <form>Elc</form>
      <lemma>elk</lemma>
      <pos>PD(type=indef,position=free)</pos>
    </w>
    <w>
      <form>was</form>
      <lemma>zijn</lemma>
      <pos>VRB(finiteness=fin,tense=past)</pos>
    </w>
    <w>
      <form>anderen</form>
      <lemma>ander</lemma>
      <pos>PD(type=indef,position=free)</pos>
    </w>
    <w>
      <form>gerne</form>
      <lemma>gaarne</lemma>
      <pos>ADV(type=reg)</pos>
    </w>
    <w>
      <form>bi</form>
      <lemma>bij</lemma>
      <pos>ADV(type=reg)</pos>
    </w>
  </l>
  <l n="85" tokens="Dat si woude dat woude hi" lemmas="dat zij willen dat willen hij">
    <w>
      <form>Dat</form>
      <lemma>dat</lemma>
      <pos>CONJ(type=sub)</pos>
    </w>
    <w>
      <form>si</form>
      <lemma>zij</lemma>
      <pos>PD(type=pers,position=free)</pos>
    </w>
    <w>
      <form>woude</form>
      <lemma>willen</lemma>
      <pos>VRB(finiteness=fin,tense=past)</pos>
    </w>
    <w>
      <form>dat</form>
      <lemma>dat</lemma>
      <pos>PD(type=d-p,position=free)</pos>
    </w>
    <w>
      <form>woude</form>
      <lemma>willen</lemma>
      <pos>VRB(finiteness=fin,tense=past)</pos>
    </w>
    <w>
      <form>hi</form>
      <lemma>hij</lemma>
      <pos>PD(type=pers,position=free)</pos>
    </w>
  </l>
  <l n="86" tokens="Maer si helt haer gebet" lemmas="maar zij hellen haar gebed">
    <w>
      <form>Maer</form>
      <lemma>maar</lemma>
      <pos>CONJ(type=coor)</pos>
    </w>
    <w>
      <form>si</form>
      <lemma>zij</lemma>
      <pos>PD(type=pers,position=free)</pos>
    </w>
    <w>
      <form>helt</form>
      <lemma>hellen</lemma>
      <pos>VRB(finiteness=fin,tense=pres)</pos>
    </w>
    <w>
      <form>haer</form>
      <lemma>haar</lemma>
      <pos>PD(type=poss,position=prenom)</pos>
    </w>
    <w>
      <form>gebet</form>
      <lemma>gebed</lemma>
      <pos>NOU-C(number=sg)</pos>
    </w>
  </l>
  <l n="87" tokens="Altoes na die heyden wet" lemmas="altoos na die heide wet">
    <w>
      <form>Altoes</form>
      <lemma>altoos</lemma>
      <pos>ADV(type=reg)</pos>
    </w>
    <w>
      <form>na</form>
      <lemma>na</lemma>
      <pos>ADP(type=pre)</pos>
    </w>
    <w>
      <form>die</form>
      <lemma>die</lemma>
      <pos>PD(type=d-p,subtype=art,position=prenom)</pos>
    </w>
    <w>
      <form>heyden</form>
      <lemma>heide</lemma>
      <pos>NOU-C(number=pl)</pos>
    </w>
    <w>
      <form>wet</form>
      <lemma>wet</lemma>
      <pos>NOU-C(number=sg)</pos>
    </w>
  </l>
  <l n="88" tokens="Ende heymelijc hilt hi tsine" lemmas="en heimelijk houden hij dat+zijn">
    <w>
      <form>Ende</form>
      <lemma>en</lemma>
      <pos>CONJ(type=coor)</pos>
    </w>
    <w>
      <form>heymelijc</form>
      <lemma>heimelijk</lemma>
      <pos>ADV(type=reg)</pos>
    </w>
    <w>
      <form>hilt</form>
      <lemma>houden</lemma>
      <pos>VRB(finiteness=fin,tense=past)</pos>
    </w>
    <w>
      <form>hi</form>
      <lemma>hij</lemma>
      <pos>PD(type=pers,position=free)</pos>
    </w>
    <w>
      <form>tsine</form>
      <lemma>dat+zijn</lemma>
      <pos>PD(type=d-p,subtype=art,position=prenom)+NOU-C(number=sg)</pos>
    </w>
  </l>
  <l n="89" tokens="Als een goet Kerstine" lemmas="als een goed kersten">
    <w>
      <form>Als</form>
      <lemma>als</lemma>
      <pos>CONJ(type=sub)</pos>
    </w>
    <w>
      <form>een</form>
      <lemma>een</lemma>
      <pos>PD(type=indef,subtype=art,position=prenom)</pos>
    </w>
    <w>
      <form>goet</form>
      <lemma>goed</lemma>
      <pos>AA(degree=pos,position=prenom)</pos>
    </w>
    <w>
      <form>Kerstine</form>
      <lemma>kersten</lemma>
      <pos>NOU-C(number=sg)</pos>
    </w>
  </l>
  <l n="90" tokens="Sendi Gode sijn gebede" lemmas="zenden+gij God zijn gebed">
    <w>
      <form>Sendi</form>
      <lemma>zenden+gij</lemma>
      <pos>VRB(finiteness=fin,tense=pres)+PD(type=pers,position=free)</pos>
    </w>
    <w>
      <form>Gode</form>
      <lemma>God</lemma>
      <pos>NOU-P</pos>
    </w>
    <w>
      <form>sijn</form>
      <lemma>zijn</lemma>
      <pos>PD(type=poss,position=prenom)</pos>
    </w>
    <w>
      <form>gebede</form>
      <lemma>gebed</lemma>
      <pos>NOU-C(number=sg)</pos>
    </w>
  </l>
  <l n="91" tokens="Dagelijcs in heymelijchede" lemmas="dagelijks in heimelijkheid">
    <w>
      <form>Dagelijcs</form>
      <lemma>dagelijks</lemma>
      <pos>ADV(type=reg)</pos>
    </w>
    <w>
      <form>in</form>
      <lemma>in</lemma>
      <pos>ADP(type=pre)</pos>
    </w>
    <w>
      <form>heymelijchede</form>
      <lemma>heimelijkheid</lemma>
      <pos>NOU-C(number=sg)</pos>
    </w>
  </l>
  <l n="92" tokens="Nu soe willic laten varen" lemmas="nu zo willen+ik laten varen">
    <w>
      <form>Nu</form>
      <lemma>nu</lemma>
      <pos>ADV(type=reg)</pos>
    </w>
    <w>
      <form>soe</form>
      <lemma>zo</lemma>
      <pos>ADV(type=reg)</pos>
    </w>
    <w>
      <form>willic</form>
      <lemma>willen+ik</lemma>
      <pos>VRB(finiteness=fin,tense=pres)+PD(type=pers,position=free)</pos>
    </w>
    <w>
      <form>laten</form>
      <lemma>laten</lemma>
      <pos>VRB(finiteness=inf)</pos>
    </w>
    <w>
      <form>varen</form>
      <lemma>varen</lemma>
      <pos>VRB(finiteness=inf)</pos>
    </w>
  </l>
  <l n="93" tokens="Van den here mer te verclaren" lemmas="van de heer maar te verklaren">
    <w>
      <form>Van</form>
      <lemma>van</lemma>
      <pos>ADP(type=pre)</pos>
    </w>
    <w>
      <form>den</form>
      <lemma>de</lemma>
      <pos>PD(type=d-p,subtype=art,position=prenom)</pos>
    </w>
    <w>
      <form>here</form>
      <lemma>heer</lemma>
      <pos>NOU-C(number=sg)</pos>
    </w>
    <w>
      <form>mer</form>
      <lemma>maar</lemma>
      <pos>CONJ(type=coor)</pos>
    </w>
    <w>
      <form>te</form>
      <lemma>te</lemma>
      <pos>ADP(type=pre)</pos>
    </w>
    <w>
      <form>verclaren</form>
      <lemma>verklaren</lemma>
      <pos>VRB(finiteness=inf)</pos>
    </w>
  </l>
  <l n="94" tokens="Van II kinderen die hi achter liet" lemmas="van twee kind die hij achten laten">
    <w>
      <form>Van</form>
      <lemma>van</lemma>
      <pos>ADP(type=pre)</pos>
    </w>
    <w>
      <form>II</form>
      <lemma>twee</lemma>
      <pos>NUM(type=card,position=prenom,representation=rom)</pos>
    </w>
    <w>
      <form>kinderen</form>
      <lemma>kind</lemma>
      <pos>NOU-C(number=pl)</pos>
    </w>
    <w>
      <form>die</form>
      <lemma>die</lemma>
      <pos>PD(type=d-p,position=free)</pos>
    </w>
    <w>
      <form>hi</form>
      <lemma>hij</lemma>
      <pos>PD(type=pers,position=free)</pos>
    </w>
    <w>
      <form>achter</form>
      <lemma>achten</lemma>
      <pos>VRB(finiteness=fin,tense=past)</pos>
    </w>
    <w>
      <form>liet</form>
      <lemma>laten</lemma>
      <pos>VRB(finiteness=fin,tense=past)</pos>
    </w>
  </l>
  <l n="95" tokens="Des hi selve en wiste niet" lemmas="de hij zelf ne wissen niet">
    <w>
      <form>Des</form>
      <lemma>de</lemma>
      <pos>PD(type=d-p,position=free)</pos>
    </w>
    <w>
      <form>hi</form>
      <lemma>hij</lemma>
      <pos>PD(type=pers,position=free)</pos>
    </w>
    <w>
      <form>selve</form>
      <lemma>zelf</lemma>
      <pos>PD(type=d-p,position=free)</pos>
    </w>
    <w>
      <form>en</form>
      <lemma>ne</lemma>
      <pos>ADV(type=reg)</pos>
    </w>
    <w>
      <form>wiste</form>
      <lemma>wissen</lemma>
      <pos>VRB(finiteness=fin,tense=past)</pos>
    </w>
    <w>
      <form>niet</form>
      <lemma>niet</lemma>
      <pos>ADV(type=reg)</pos>
    </w>
  </l>
  <l n="96" tokens="Die hi hadde bi der vrouwen" lemmas="die hij hebben bij de vrouw">
    <w>
      <form>Die</form>
      <lemma>die</lemma>
      <pos>PD(type=d-p,position=free)</pos>
    </w>
    <w>
      <form>hi</form>
      <lemma>hij</lemma>
      <pos>PD(type=pers,position=free)</pos>
    </w>
    <w>
      <form>hadde</form>
      <lemma>hebben</lemma>
      <pos>VRB(finiteness=fin,tense=past)</pos>
    </w>
    <w>
      <form>bi</form>
      <lemma>bij</lemma>
      <pos>ADP(type=pre)</pos>
    </w>
    <w>
      <form>der</form>
      <lemma>de</lemma>
      <pos>PD(type=d-p,subtype=art,position=prenom)</pos>
    </w>
    <w>
      <form>vrouwen</form>
      <lemma>vrouw</lemma>
      <pos>NOU-C(number=sg)</pos>
    </w>
  </l>
  <l n="97" tokens="Wies herte hi liet in rouwen" lemmas="wassen hart hij laten in rouw">
    <w>
      <form>Wies</form>
      <lemma>wassen</lemma>
      <pos>VRB(finiteness=fin,tense=past)</pos>
    </w>
    <w>
      <form>herte</form>
      <lemma>hart</lemma>
      <pos>NOU-C(number=sg)</pos>
    </w>
    <w>
      <form>hi</form>
      <lemma>hij</lemma>
      <pos>PD(type=pers,position=free)</pos>
    </w>
    <w>
      <form>liet</form>
      <lemma>laten</lemma>
      <pos>VRB(finiteness=fin,tense=past)</pos>
    </w>
    <w>
      <form>in</form>
      <lemma>in</lemma>
      <pos>ADP(type=pre)</pos>
    </w>
    <w>
      <form>rouwen</form>
      <lemma>rouw</lemma>
      <pos>NOU-C(number=sg)</pos>
    </w>
  </l>
  <l n="98" tokens="Al mocht hijs gebeteren niet" lemmas="al mogen hij+dat gebeteren niet">
    <w>
      <form>Al</form>
      <lemma>al</lemma>
      <pos>CONJ(type=sub)</pos>
    </w>
    <w>
      <form>mocht</form>
      <lemma>mogen</lemma>
      <pos>VRB(finiteness=fin,tense=past)</pos>
    </w>
    <w>
      <form>hijs</form>
      <lemma>hij+dat</lemma>
      <pos>PD(type=pers,position=free)+PD(type=d-p,position=free)</pos>
    </w>
    <w>
      <form>gebeteren</form>
      <lemma>gebeteren</lemma>
      <pos>VRB(finiteness=inf)</pos>
    </w>
    <w>
      <form>niet</form>
      <lemma>niet</lemma>
      <pos>ADV(type=reg)</pos>
    </w>
  </l>
  <l n="99" tokens="Die kinder waren worden groot" lemmas="die kind zijn worden groot">
    <w>
      <form>Die</form>
      <lemma>die</lemma>
      <pos>PD(type=d-p,subtype=art,position=prenom)</pos>
    </w>
    <w>
      <form>kinder</form>
      <lemma>kind</lemma>
      <pos>NOU-C(number=pl)</pos>
    </w>
    <w>
      <form>waren</form>
      <lemma>zijn</lemma>
      <pos>VRB(finiteness=fin,tense=past)</pos>
    </w>
    <w>
      <form>worden</form>
      <lemma>worden</lemma>
      <pos>VRB(finiteness=inf)</pos>
    </w>
    <w>
      <form>groot</form>
      <lemma>groot</lemma>
      <pos>AA(degree=pos,position=free)</pos>
    </w>
  </l>
  <l n="100" tokens="Si waenden dat haer vader doot" lemmas="zij wanen dat haar vader dood">
    <w>
      <form>Si</form>
      <lemma>zij</lemma>
      <pos>PD(type=pers,position=free)</pos>
    </w>
    <w>
      <form>waenden</form>
      <lemma>wanen</lemma>
      <pos>VRB(finiteness=fin,tense=past)</pos>
    </w>
    <w>
      <form>dat</form>
      <lemma>dat</lemma>
      <pos>CONJ(type=sub)</pos>
    </w>
    <w>
      <form>haer</form>
      <lemma>haar</lemma>
      <pos>PD(type=poss,position=prenom)</pos>
    </w>
    <w>
      <form>vader</form>
      <lemma>vader</lemma>
      <pos>NOU-C(number=sg)</pos>
    </w>
    <w>
      <form>doot</form>
      <lemma>dood</lemma>
      <pos>AA(degree=pos,position=free)</pos>
    </w>
  </l>
</text>
