<?xml version='1.0' encoding='UTF-8'?>
<text id="madelgijs_fragm_le4">
  <l n="1" tokens="Scone ioncvrauwe doe mi verstaen" lemmas="schoon jonkvrouw doen ik verstaan">
    <w>
      <form>Scone</form>
      <lemma>schoon</lemma>
      <pos>AA(degree=pos,position=prenom)</pos>
    </w>
    <w>
      <form>ioncvrauwe</form>
      <lemma>jonkvrouw</lemma>
      <pos>NOU-C(number=sg)</pos>
    </w>
    <w>
      <form>doe</form>
      <lemma>doen</lemma>
      <pos>VRB(finiteness=fin,tense=pres)</pos>
    </w>
    <w>
      <form>mi</form>
      <lemma>ik</lemma>
      <pos>PD(type=pers,position=free)</pos>
    </w>
    <w>
      <form>verstaen</form>
      <lemma>verstaan</lemma>
      <pos>VRB(finiteness=inf)</pos>
    </w>
  </l>
  <l n="2" tokens="Ende lucifeer andworde saen" lemmas="en lucifeer antwoorden zaan">
    <w>
      <form>Ende</form>
      <lemma>en</lemma>
      <pos>CONJ(type=coor)</pos>
    </w>
    <w>
      <form>lucifeer</form>
      <lemma>lucifeer</lemma>
      <pos>PD(type=d-p,subtype=art,position=prenom)+NOU-C(number=sg)</pos>
    </w>
    <w>
      <form>andworde</form>
      <lemma>antwoorden</lemma>
      <pos>VRB(finiteness=fin,tense=pres)</pos>
    </w>
    <w>
      <form>saen</form>
      <lemma>zaan</lemma>
      <pos>ADV(type=reg)</pos>
    </w>
  </l>
  <l n="3" tokens="Urauwe ic bem een edel wijf" lemmas="urouw ik zijn een edel wijf">
    <w>
      <form>Urauwe</form>
      <lemma>urouw</lemma>
      <pos>NOU-C(number=sg)</pos>
    </w>
    <w>
      <form>ic</form>
      <lemma>ik</lemma>
      <pos>PD(type=pers,position=free)</pos>
    </w>
    <w>
      <form>bem</form>
      <lemma>zijn</lemma>
      <pos>VRB(finiteness=fin,tense=pres)</pos>
    </w>
    <w>
      <form>een</form>
      <lemma>een</lemma>
      <pos>PD(type=indef,subtype=art,position=prenom)</pos>
    </w>
    <w>
      <form>edel</form>
      <lemma>edel</lemma>
      <pos>AA(degree=pos,position=prenom)</pos>
    </w>
    <w>
      <form>wijf</form>
      <lemma>wijf</lemma>
      <pos>NOU-C(number=sg)</pos>
    </w>
  </l>
  <l n="4" tokens="Gaet met mi sonder blijf" lemmas="gaan met ik zonder blijf">
    <w>
      <form>Gaet</form>
      <lemma>gaan</lemma>
      <pos>VRB(finiteness=fin,tense=pres)</pos>
    </w>
    <w>
      <form>met</form>
      <lemma>met</lemma>
      <pos>ADP(type=pre)</pos>
    </w>
    <w>
      <form>mi</form>
      <lemma>ik</lemma>
      <pos>PD(type=pers,position=free)</pos>
    </w>
    <w>
      <form>sonder</form>
      <lemma>zonder</lemma>
      <pos>ADP(type=pre)</pos>
    </w>
    <w>
      <form>blijf</form>
      <lemma>blijf</lemma>
      <pos>NOU-C(number=sg)</pos>
    </w>
  </l>
  <l n="5" tokens="Ghi sult wel te ghemake wesen" lemmas="gij zullen wel te gemak wezen">
    <w>
      <form>Ghi</form>
      <lemma>gij</lemma>
      <pos>PD(type=pers,position=free)</pos>
    </w>
    <w>
      <form>sult</form>
      <lemma>zullen</lemma>
      <pos>VRB(finiteness=fin,tense=pres)</pos>
    </w>
    <w>
      <form>wel</form>
      <lemma>wel</lemma>
      <pos>ADV(type=reg)</pos>
    </w>
    <w>
      <form>te</form>
      <lemma>te</lemma>
      <pos>ADP(type=pre)</pos>
    </w>
    <w>
      <form>ghemake</form>
      <lemma>gemak</lemma>
      <pos>NOU-C(number=sg)</pos>
    </w>
    <w>
      <form>wesen</form>
      <lemma>wezen</lemma>
      <pos>VRB(finiteness=inf)</pos>
    </w>
  </l>
  <l n="6" tokens="Doe sach oriande met desen" lemmas="toen zien Oriande met deze">
    <w>
      <form>Doe</form>
      <lemma>toen</lemma>
      <pos>ADV(type=reg)</pos>
    </w>
    <w>
      <form>sach</form>
      <lemma>zien</lemma>
      <pos>VRB(finiteness=fin,tense=past)</pos>
    </w>
    <w>
      <form>oriande</form>
      <lemma>Oriande</lemma>
      <pos>NOU-P</pos>
    </w>
    <w>
      <form>met</form>
      <lemma>met</lemma>
      <pos>ADP(type=pre)</pos>
    </w>
    <w>
      <form>desen</form>
      <lemma>deze</lemma>
      <pos>PD(type=d-p,position=free)</pos>
    </w>
  </l>
  <l n="7" tokens="Op die ioncvrauwe des ghelooft" lemmas="op die jonkvrouw de geloofd">
    <w>
      <form>Op</form>
      <lemma>op</lemma>
      <pos>ADP(type=pre)</pos>
    </w>
    <w>
      <form>die</form>
      <lemma>die</lemma>
      <pos>PD(type=d-p,subtype=art,position=prenom)</pos>
    </w>
    <w>
      <form>ioncvrauwe</form>
      <lemma>jonkvrouw</lemma>
      <pos>NOU-C(number=sg)</pos>
    </w>
    <w>
      <form>des</form>
      <lemma>de</lemma>
      <pos>PD(type=d-p,subtype=art,position=prenom)</pos>
    </w>
    <w>
      <form>ghelooft</form>
      <lemma>geloofd</lemma>
      <pos>NOU-C(number=sg)</pos>
    </w>
  </l>
  <l n="8" tokens="Daer sach soe bliken an haer hoeft" lemmas="daar zien zij blijken aan haar hoofd">
    <w>
      <form>Daer</form>
      <lemma>daar</lemma>
      <pos>ADV(type=reg)</pos>
    </w>
    <w>
      <form>sach</form>
      <lemma>zien</lemma>
      <pos>VRB(finiteness=fin,tense=past)</pos>
    </w>
    <w>
      <form>soe</form>
      <lemma>zij</lemma>
      <pos>PD(type=pers,position=free)</pos>
    </w>
    <w>
      <form>bliken</form>
      <lemma>blijken</lemma>
      <pos>VRB(finiteness=inf)</pos>
    </w>
    <w>
      <form>an</form>
      <lemma>aan</lemma>
      <pos>ADP(type=pre)</pos>
    </w>
    <w>
      <form>haer</form>
      <lemma>haar</lemma>
      <pos>PD(type=poss,position=prenom)</pos>
    </w>
    <w>
      <form>hoeft</form>
      <lemma>hoofd</lemma>
      <pos>NOU-C(number=sg)</pos>
    </w>
  </l>
  <l n="9" tokens="Dat het was die helsche geest" lemmas="dat het zijn die hels geest">
    <w>
      <form>Dat</form>
      <lemma>dat</lemma>
      <pos>CONJ(type=sub)</pos>
    </w>
    <w>
      <form>het</form>
      <lemma>het</lemma>
      <pos>PD(type=pers,position=free)</pos>
    </w>
    <w>
      <form>was</form>
      <lemma>zijn</lemma>
      <pos>VRB(finiteness=fin,tense=past)</pos>
    </w>
    <w>
      <form>die</form>
      <lemma>die</lemma>
      <pos>PD(type=d-p,subtype=art,position=prenom)</pos>
    </w>
    <w>
      <form>helsche</form>
      <lemma>hels</lemma>
      <pos>AA(degree=pos,position=prenom)</pos>
    </w>
    <w>
      <form>geest</form>
      <lemma>geest</lemma>
      <pos>NOU-C(number=sg)</pos>
    </w>
  </l>
  <l n="10" tokens="Joncvrouwe na dien dat ghi" lemmas="jonkvrouw na die dat gij">
    <w>
      <form>Joncvrouwe</form>
      <lemma>jonkvrouw</lemma>
      <pos>NOU-C(number=sg)</pos>
    </w>
    <w>
      <form>na</form>
      <lemma>na</lemma>
      <pos>ADV(type=reg)</pos>
    </w>
    <w>
      <form>dien</form>
      <lemma>die</lemma>
      <pos>ADV(type=reg)</pos>
    </w>
    <w>
      <form>dat</form>
      <lemma>dat</lemma>
      <pos>CONJ(type=sub)</pos>
    </w>
    <w>
      <form>ghi</form>
      <lemma>gij</lemma>
      <pos>PD(type=pers,position=free)</pos>
    </w>
  </l>
  <l n="11" tokens="So edel sijt ende so vri" lemmas="zo edel zijn en zo vrij">
    <w>
      <form>So</form>
      <lemma>zo</lemma>
      <pos>ADV(type=reg)</pos>
    </w>
    <w>
      <form>edel</form>
      <lemma>edel</lemma>
      <pos>AA(degree=pos,position=free)</pos>
    </w>
    <w>
      <form>sijt</form>
      <lemma>zijn</lemma>
      <pos>VRB(finiteness=fin,tense=pres)</pos>
    </w>
    <w>
      <form>ende</form>
      <lemma>en</lemma>
      <pos>CONJ(type=coor)</pos>
    </w>
    <w>
      <form>so</form>
      <lemma>zo</lemma>
      <pos>ADV(type=reg)</pos>
    </w>
    <w>
      <form>vri</form>
      <lemma>vrij</lemma>
      <pos>AA(degree=pos,position=free)</pos>
    </w>
  </l>
  <l n="12" tokens="So willic nv met v gaen" lemmas="zo willen+ik nu met u gaan">
    <w>
      <form>So</form>
      <lemma>zo</lemma>
      <pos>ADV(type=reg)</pos>
    </w>
    <w>
      <form>willic</form>
      <lemma>willen+ik</lemma>
      <pos>VRB(finiteness=fin,tense=pres)+PD(type=pers,position=free)</pos>
    </w>
    <w>
      <form>nv</form>
      <lemma>nu</lemma>
      <pos>ADV(type=reg)</pos>
    </w>
    <w>
      <form>met</form>
      <lemma>met</lemma>
      <pos>ADP(type=pre)</pos>
    </w>
    <w>
      <form>v</form>
      <lemma>u</lemma>
      <pos>PD(type=pers,position=free)</pos>
    </w>
    <w>
      <form>gaen</form>
      <lemma>gaan</lemma>
      <pos>VRB(finiteness=inf)</pos>
    </w>
  </l>
  <l n="13" tokens="Jn de maniere dat hem god liet slaen" lemmas="in de manier dat hij God laten slaan">
    <w>
      <form>Jn</form>
      <lemma>in</lemma>
      <pos>ADP(type=pre)</pos>
    </w>
    <w>
      <form>de</form>
      <lemma>de</lemma>
      <pos>PD(type=d-p,subtype=art,position=prenom)</pos>
    </w>
    <w>
      <form>maniere</form>
      <lemma>manier</lemma>
      <pos>NOU-C(number=sg)</pos>
    </w>
    <w>
      <form>dat</form>
      <lemma>dat</lemma>
      <pos>CONJ(type=sub)</pos>
    </w>
    <w>
      <form>hem</form>
      <lemma>hij</lemma>
      <pos>PD(type=pers,position=free)</pos>
    </w>
    <w>
      <form>god</form>
      <lemma>God</lemma>
      <pos>NOU-P</pos>
    </w>
    <w>
      <form>liet</form>
      <lemma>laten</lemma>
      <pos>VRB(finiteness=fin,tense=past)</pos>
    </w>
    <w>
      <form>slaen</form>
      <lemma>slaan</lemma>
      <pos>VRB(finiteness=inf)</pos>
    </w>
  </l>
  <l n="14" tokens="An een cruus alst es ghescreuen" lemmas="aan een kruis als+het zijn schrijven">
    <w>
      <form>An</form>
      <lemma>aan</lemma>
      <pos>ADP(type=pre)</pos>
    </w>
    <w>
      <form>een</form>
      <lemma>een</lemma>
      <pos>PD(type=indef,subtype=art,position=prenom)</pos>
    </w>
    <w>
      <form>cruus</form>
      <lemma>kruis</lemma>
      <pos>NOU-C(number=sg)</pos>
    </w>
    <w>
      <form>alst</form>
      <lemma>als+het</lemma>
      <pos>CONJ(type=sub)+PD(type=pers,position=free)</pos>
    </w>
    <w>
      <form>es</form>
      <lemma>zijn</lemma>
      <pos>VRB(finiteness=fin,tense=pres)</pos>
    </w>
    <w>
      <form>ghescreuen</form>
      <lemma>schrijven</lemma>
      <pos>VRB(finiteness=pastpart)</pos>
    </w>
  </l>
  <l n="15" tokens="Doe began die viant beuen" lemmas="toen beginnen die vijand beven">
    <w>
      <form>Doe</form>
      <lemma>toen</lemma>
      <pos>ADV(type=reg)</pos>
    </w>
    <w>
      <form>began</form>
      <lemma>beginnen</lemma>
      <pos>VRB(finiteness=fin,tense=past)</pos>
    </w>
    <w>
      <form>die</form>
      <lemma>die</lemma>
      <pos>PD(type=d-p,subtype=art,position=prenom)</pos>
    </w>
    <w>
      <form>viant</form>
      <lemma>vijand</lemma>
      <pos>NOU-C(number=sg)</pos>
    </w>
    <w>
      <form>beuen</form>
      <lemma>beven</lemma>
      <pos>VRB(finiteness=inf)</pos>
    </w>
  </l>
  <l n="16" tokens="Die daer stont in ioncvrauwen wise" lemmas="die daar staan in jonkvrouw wijze">
    <w>
      <form>Die</form>
      <lemma>die</lemma>
      <pos>PD(type=d-p,position=free)</pos>
    </w>
    <w>
      <form>daer</form>
      <lemma>daar</lemma>
      <pos>ADV(type=reg)</pos>
    </w>
    <w>
      <form>stont</form>
      <lemma>staan</lemma>
      <pos>VRB(finiteness=fin,tense=past)</pos>
    </w>
    <w>
      <form>in</form>
      <lemma>in</lemma>
      <pos>ADP(type=pre)</pos>
    </w>
    <w>
      <form>ioncvrauwen</form>
      <lemma>jonkvrouw</lemma>
      <pos>NOU-C(number=sg)</pos>
    </w>
    <w>
      <form>wise</form>
      <lemma>wijze</lemma>
      <pos>NOU-C(number=sg)</pos>
    </w>
  </l>
  <l n="17" tokens="Hi sede edele vrouwe van prise" lemmas="hij zeggen edel vrouwe van prijs">
    <w>
      <form>Hi</form>
      <lemma>hij</lemma>
      <pos>PD(type=pers,position=free)</pos>
    </w>
    <w>
      <form>sede</form>
      <lemma>zeggen</lemma>
      <pos>VRB(finiteness=fin,tense=past)</pos>
    </w>
    <w>
      <form>edele</form>
      <lemma>edel</lemma>
      <pos>AA(degree=pos,position=prenom)</pos>
    </w>
    <w>
      <form>vrouwe</form>
      <lemma>vrouwe</lemma>
      <pos>NOU-C(number=sg)</pos>
    </w>
    <w>
      <form>van</form>
      <lemma>van</lemma>
      <pos>ADP(type=pre)</pos>
    </w>
    <w>
      <form>prise</form>
      <lemma>prijs</lemma>
      <pos>NOU-C(number=sg)</pos>
    </w>
  </l>
  <l n="18" tokens="Ende of ghi wilt dat beste doen" lemmas="en of gij willen dat best doen">
    <w>
      <form>Ende</form>
      <lemma>en</lemma>
      <pos>CONJ(type=coor)</pos>
    </w>
    <w>
      <form>of</form>
      <lemma>of</lemma>
      <pos>CONJ(type=sub)</pos>
    </w>
    <w>
      <form>ghi</form>
      <lemma>gij</lemma>
      <pos>PD(type=pers,position=free)</pos>
    </w>
    <w>
      <form>wilt</form>
      <lemma>willen</lemma>
      <pos>VRB(finiteness=fin,tense=pres)</pos>
    </w>
    <w>
      <form>dat</form>
      <lemma>dat</lemma>
      <pos>PD(type=d-p,subtype=oth,position=prenom)</pos>
    </w>
    <w>
      <form>beste</form>
      <lemma>best</lemma>
      <pos>NOU-C(number=sg)</pos>
    </w>
    <w>
      <form>doen</form>
      <lemma>doen</lemma>
      <pos>VRB(finiteness=inf)</pos>
    </w>
  </l>
  <l n="19" tokens="Sone sect nemmeer dat orisoen" lemmas="zo+ne sek nimmer dat orisoen">
    <w>
      <form>Sone</form>
      <lemma>zo+ne</lemma>
      <pos>PD(type=pers,position=free)+ADV(type=reg)</pos>
    </w>
    <w>
      <form>sect</form>
      <lemma>sek</lemma>
      <pos>NOU-C(number=sg)</pos>
    </w>
    <w>
      <form>nemmeer</form>
      <lemma>nimmer</lemma>
      <pos>ADV(type=reg)</pos>
    </w>
    <w>
      <form>dat</form>
      <lemma>dat</lemma>
      <pos>PD(type=d-p,subtype=art,position=prenom)</pos>
    </w>
    <w>
      <form>orisoen</form>
      <lemma>orisoen</lemma>
      <pos>NOU-C(number=sg)</pos>
    </w>
  </l>
  <l n="20" tokens="Want bedi dat nes niet goet" lemmas="want bedie dat ne+zijn niet goed">
    <w>
      <form>Want</form>
      <lemma>want</lemma>
      <pos>CONJ(type=coor)</pos>
    </w>
    <w>
      <form>bedi</form>
      <lemma>bedie</lemma>
      <pos>CONJ(type=sub)</pos>
    </w>
    <w>
      <form>dat</form>
      <lemma>dat</lemma>
      <pos>PD(type=d-p,position=free)</pos>
    </w>
    <w>
      <form>nes</form>
      <lemma>ne+zijn</lemma>
      <pos>ADV(type=reg)+VRB(finiteness=fin,tense=pres)</pos>
    </w>
    <w>
      <form>niet</form>
      <lemma>niet</lemma>
      <pos>PD(type=indef,position=free)</pos>
    </w>
    <w>
      <form>goet</form>
      <lemma>goed</lemma>
      <pos>AA(degree=pos,position=free)</pos>
    </w>
  </l>
  <l n="21" tokens="Doe sede soe daer soe stoet" lemmas="toen zeggen zij daar zo staan">
    <w>
      <form>Doe</form>
      <lemma>toen</lemma>
      <pos>ADV(type=reg)</pos>
    </w>
    <w>
      <form>sede</form>
      <lemma>zeggen</lemma>
      <pos>VRB(finiteness=fin,tense=past)</pos>
    </w>
    <w>
      <form>soe</form>
      <lemma>zij</lemma>
      <pos>PD(type=pers,position=free)</pos>
    </w>
    <w>
      <form>daer</form>
      <lemma>daar</lemma>
      <pos>ADV(type=reg)</pos>
    </w>
    <w>
      <form>soe</form>
      <lemma>zo</lemma>
      <pos>ADV(type=reg)</pos>
    </w>
    <w>
      <form>stoet</form>
      <lemma>staan</lemma>
      <pos>VRB(finiteness=fin,tense=past)</pos>
    </w>
  </l>
  <l n="22" tokens="AY euel geest ende waenstu mie" lemmas="ai evel geest en wanen+du ik">
    <w>
      <form>AY</form>
      <lemma>ai</lemma>
      <pos>INT</pos>
    </w>
    <w>
      <form>euel</form>
      <lemma>evel</lemma>
      <pos>AA(degree=pos,position=prenom)</pos>
    </w>
    <w>
      <form>geest</form>
      <lemma>geest</lemma>
      <pos>NOU-C(number=sg)</pos>
    </w>
    <w>
      <form>ende</form>
      <lemma>en</lemma>
      <pos>CONJ(type=coor)</pos>
    </w>
    <w>
      <form>waenstu</form>
      <lemma>wanen+du</lemma>
      <pos>VRB(finiteness=fin,tense=pres)+PD(type=pers,position=free)</pos>
    </w>
    <w>
      <form>mie</form>
      <lemma>ik</lemma>
      <pos>PD(type=pers,position=free)</pos>
    </w>
  </l>
  <l n="23" tokens="Tempteren ic ne sal die" lemmas="tempteren ik ne zullen die">
    <w>
      <form>Tempteren</form>
      <lemma>tempteren</lemma>
      <pos>VRB(finiteness=inf)</pos>
    </w>
    <w>
      <form>ic</form>
      <lemma>ik</lemma>
      <pos>PD(type=pers,position=free)</pos>
    </w>
    <w>
      <form>ne</form>
      <lemma>ne</lemma>
      <pos>ADV(type=reg)</pos>
    </w>
    <w>
      <form>sal</form>
      <lemma>zullen</lemma>
      <pos>VRB(finiteness=fin,tense=pres)</pos>
    </w>
    <w>
      <form>die</form>
      <lemma>die</lemma>
      <pos>PD(type=d-p,position=free)</pos>
    </w>
  </l>
  <l n="24" tokens="Vraghen bider gods cracht" lemmas="vragen bij+de God kracht">
    <w>
      <form>Vraghen</form>
      <lemma>vragen</lemma>
      <pos>VRB(finiteness=inf)</pos>
    </w>
    <w>
      <form>bider</form>
      <lemma>bij+de</lemma>
      <pos>ADP(type=pre)+PD(type=d-p,subtype=art,position=prenom)</pos>
    </w>
    <w>
      <form>gods</form>
      <lemma>God</lemma>
      <pos>NOU-P</pos>
    </w>
    <w>
      <form>cracht</form>
      <lemma>kracht</lemma>
      <pos>NOU-C(number=sg)</pos>
    </w>
  </l>
  <l n="25" tokens="Doe god verrees in paessch daghe" lemmas="toen God verrijzen in Pas Dage">
    <w>
      <form>Doe</form>
      <lemma>toen</lemma>
      <pos>CONJ(type=sub)</pos>
    </w>
    <w>
      <form>god</form>
      <lemma>God</lemma>
      <pos>NOU-P</pos>
    </w>
    <w>
      <form>verrees</form>
      <lemma>verrijzen</lemma>
      <pos>VRB(finiteness=fin,tense=past)</pos>
    </w>
    <w>
      <form>in</form>
      <lemma>in</lemma>
      <pos>ADP(type=pre)</pos>
    </w>
    <w>
      <form>paessch</form>
      <lemma>Pas</lemma>
      <pos>NOU-P</pos>
    </w>
    <w>
      <form>daghe</form>
      <lemma>Dage</lemma>
      <pos>NOU-P</pos>
    </w>
  </l>
  <l n="26" tokens="Om te verlossene vriende ende maghe" lemmas="om te verlossen vriend en maag">
    <w>
      <form>Om</form>
      <lemma>om</lemma>
      <pos>ADP(type=pre)</pos>
    </w>
    <w>
      <form>te</form>
      <lemma>te</lemma>
      <pos>ADP(type=pre)</pos>
    </w>
    <w>
      <form>verlossene</form>
      <lemma>verlossen</lemma>
      <pos>VRB(finiteness=inf)</pos>
    </w>
    <w>
      <form>vriende</form>
      <lemma>vriend</lemma>
      <pos>NOU-C(number=pl)</pos>
    </w>
    <w>
      <form>ende</form>
      <lemma>en</lemma>
      <pos>CONJ(type=coor)</pos>
    </w>
    <w>
      <form>maghe</form>
      <lemma>maag</lemma>
      <pos>NOU-C(number=sg)</pos>
    </w>
  </l>
  <l n="27" tokens="Ende vlooch wech siere veerde" lemmas="en vliegen wegdoen zijn vaart">
    <w>
      <form>Ende</form>
      <lemma>en</lemma>
      <pos>CONJ(type=coor)</pos>
    </w>
    <w>
      <form>vlooch</form>
      <lemma>vliegen</lemma>
      <pos>VRB(finiteness=fin,tense=past)</pos>
    </w>
    <w>
      <form>wech</form>
      <lemma>wegdoen</lemma>
      <pos>VRB(finiteness=fin,tense=past)</pos>
    </w>
    <w>
      <form>siere</form>
      <lemma>zijn</lemma>
      <pos>PD(type=poss,position=prenom)</pos>
    </w>
    <w>
      <form>veerde</form>
      <lemma>vaart</lemma>
      <pos>NOU-C(number=sg)</pos>
    </w>
  </l>
  <l n="28" tokens="Die gode dancte met goeder trouwen" lemmas="die God danken met goed trouw">
    <w>
      <form>Die</form>
      <lemma>die</lemma>
      <pos>PD(type=d-p,position=free)</pos>
    </w>
    <w>
      <form>gode</form>
      <lemma>God</lemma>
      <pos>NOU-P</pos>
    </w>
    <w>
      <form>dancte</form>
      <lemma>danken</lemma>
      <pos>VRB(finiteness=fin,tense=past)</pos>
    </w>
    <w>
      <form>met</form>
      <lemma>met</lemma>
      <pos>ADP(type=pre)</pos>
    </w>
    <w>
      <form>goeder</form>
      <lemma>goed</lemma>
      <pos>AA(degree=pos,position=prenom)</pos>
    </w>
    <w>
      <form>trouwen</form>
      <lemma>trouw</lemma>
      <pos>NOU-C(number=sg)</pos>
    </w>
  </l>
  <l n="29" tokens="Dat hi haer die ere dede" lemmas="dat hij zij die eer doen">
    <w>
      <form>Dat</form>
      <lemma>dat</lemma>
      <pos>CONJ(type=sub)</pos>
    </w>
    <w>
      <form>hi</form>
      <lemma>hij</lemma>
      <pos>PD(type=pers,position=free)</pos>
    </w>
    <w>
      <form>haer</form>
      <lemma>zij</lemma>
      <pos>PD(type=pers,position=free)</pos>
    </w>
    <w>
      <form>die</form>
      <lemma>die</lemma>
      <pos>PD(type=d-p,subtype=art,position=prenom)</pos>
    </w>
    <w>
      <form>ere</form>
      <lemma>eer</lemma>
      <pos>NOU-C(number=sg)</pos>
    </w>
    <w>
      <form>dede</form>
      <lemma>doen</lemma>
      <pos>VRB(finiteness=fin,tense=past)</pos>
    </w>
  </l>
  <l n="30" tokens="Doe ghinc soe voert sonder bede" lemmas="toen gaan zij voeren zonder bede">
    <w>
      <form>Doe</form>
      <lemma>toen</lemma>
      <pos>ADV(type=reg)</pos>
    </w>
    <w>
      <form>ghinc</form>
      <lemma>gaan</lemma>
      <pos>VRB(finiteness=fin,tense=past)</pos>
    </w>
    <w>
      <form>soe</form>
      <lemma>zij</lemma>
      <pos>PD(type=pers,position=free)</pos>
    </w>
    <w>
      <form>voert</form>
      <lemma>voeren</lemma>
      <pos>VRB(finiteness=fin,tense=past)</pos>
    </w>
    <w>
      <form>sonder</form>
      <lemma>zonder</lemma>
      <pos>ADP(type=pre)</pos>
    </w>
    <w>
      <form>bede</form>
      <lemma>bede</lemma>
      <pos>NOU-C(number=sg)</pos>
    </w>
  </l>
  <l n="31" tokens="An den slach van ere mile" lemmas="aan de slag van een mijl">
    <w>
      <form>An</form>
      <lemma>aan</lemma>
      <pos>ADP(type=pre)</pos>
    </w>
    <w>
      <form>den</form>
      <lemma>de</lemma>
      <pos>PD(type=d-p,subtype=art,position=prenom)</pos>
    </w>
    <w>
      <form>slach</form>
      <lemma>slag</lemma>
      <pos>NOU-C(number=sg)</pos>
    </w>
    <w>
      <form>van</form>
      <lemma>van</lemma>
      <pos>ADP(type=pre)</pos>
    </w>
    <w>
      <form>ere</form>
      <lemma>een</lemma>
      <pos>PD(type=indef,subtype=art,position=prenom)</pos>
    </w>
    <w>
      <form>mile</form>
      <lemma>mijl</lemma>
      <pos>NOU-C(number=sg)</pos>
    </w>
  </l>
  <l n="32" tokens="Daer sach soe in corter wile" lemmas="daar zien zij in kort wijl">
    <w>
      <form>Daer</form>
      <lemma>daar</lemma>
      <pos>ADV(type=reg)</pos>
    </w>
    <w>
      <form>sach</form>
      <lemma>zien</lemma>
      <pos>VRB(finiteness=fin,tense=past)</pos>
    </w>
    <w>
      <form>soe</form>
      <lemma>zij</lemma>
      <pos>PD(type=pers,position=free)</pos>
    </w>
    <w>
      <form>in</form>
      <lemma>in</lemma>
      <pos>ADP(type=pre)</pos>
    </w>
    <w>
      <form>corter</form>
      <lemma>kort</lemma>
      <pos>AA(degree=pos,position=prenom)</pos>
    </w>
    <w>
      <form>wile</form>
      <lemma>wijl</lemma>
      <pos>NOU-C(number=sg)</pos>
    </w>
  </l>
  <l n="33" tokens="Ene poorte harde rene" lemmas="een poort hard rijn">
    <w>
      <form>Ene</form>
      <lemma>een</lemma>
      <pos>PD(type=indef,subtype=art,position=prenom)</pos>
    </w>
    <w>
      <form>poorte</form>
      <lemma>poort</lemma>
      <pos>NOU-C(number=sg)</pos>
    </w>
    <w>
      <form>harde</form>
      <lemma>hard</lemma>
      <pos>ADV(type=reg)</pos>
    </w>
    <w>
      <form>rene</form>
      <lemma>rijn</lemma>
      <pos>NOU-C(number=sg)</pos>
    </w>
  </l>
  <l n="34" tokens="Ghemaect van precieusen stene" lemmas="maken van precieus steen">
    <w>
      <form>Ghemaect</form>
      <lemma>maken</lemma>
      <pos>VRB(finiteness=pastpart)</pos>
    </w>
    <w>
      <form>van</form>
      <lemma>van</lemma>
      <pos>ADP(type=pre)</pos>
    </w>
    <w>
      <form>precieusen</form>
      <lemma>precieus</lemma>
      <pos>AA(degree=pos,position=prenom)</pos>
    </w>
    <w>
      <form>stene</form>
      <lemma>steen</lemma>
      <pos>NOU-C(number=sg)</pos>
    </w>
  </l>
  <l n="35" tokens="Ende van goude sijt des wijs" lemmas="en van goud zijn des wijs">
    <w>
      <form>Ende</form>
      <lemma>en</lemma>
      <pos>CONJ(type=coor)</pos>
    </w>
    <w>
      <form>van</form>
      <lemma>van</lemma>
      <pos>ADP(type=pre)</pos>
    </w>
    <w>
      <form>goude</form>
      <lemma>goud</lemma>
      <pos>NOU-C(number=sg)</pos>
    </w>
    <w>
      <form>sijt</form>
      <lemma>zijn</lemma>
      <pos>VRB(finiteness=fin,tense=pres)+PD(type=pers,position=free)</pos>
    </w>
    <w>
      <form>des</form>
      <lemma>des</lemma>
      <pos>ADV(type=reg)</pos>
    </w>
    <w>
      <form>wijs</form>
      <lemma>wijs</lemma>
      <pos>AA(degree=pos,position=free)</pos>
    </w>
  </l>
  <l n="36" tokens="Doe quamen II moneke iolijs" lemmas="toen komen twee monnik Jolius">
    <w>
      <form>Doe</form>
      <lemma>toen</lemma>
      <pos>ADV(type=reg)</pos>
    </w>
    <w>
      <form>quamen</form>
      <lemma>komen</lemma>
      <pos>VRB(finiteness=fin,tense=past)</pos>
    </w>
    <w>
      <form>II</form>
      <lemma>twee</lemma>
      <pos>NUM(type=card,position=prenom,representation=rom)</pos>
    </w>
    <w>
      <form>moneke</form>
      <lemma>monnik</lemma>
      <pos>NOU-C(number=pl)</pos>
    </w>
    <w>
      <form>iolijs</form>
      <lemma>Jolius</lemma>
      <pos>NOU-P</pos>
    </w>
  </l>
  <l n="37" tokens="Jeghen haer met feesten groot" lemmas="jegen zij met feest groot">
    <w>
      <form>Jeghen</form>
      <lemma>jegen</lemma>
      <pos>ADP(type=pre)</pos>
    </w>
    <w>
      <form>haer</form>
      <lemma>zij</lemma>
      <pos>PD(type=pers,position=free)</pos>
    </w>
    <w>
      <form>met</form>
      <lemma>met</lemma>
      <pos>ADP(type=pre)</pos>
    </w>
    <w>
      <form>feesten</form>
      <lemma>feest</lemma>
      <pos>NOU-C(number=pl)</pos>
    </w>
    <w>
      <form>groot</form>
      <lemma>groot</lemma>
      <pos>AA(degree=pos,position=postnom)</pos>
    </w>
  </l>
  <l n="38" tokens="Elc brochte een cruus root" lemmas="elk brengen een kruis rood">
    <w>
      <form>Elc</form>
      <lemma>elk</lemma>
      <pos>PD(type=indef,position=free)</pos>
    </w>
    <w>
      <form>brochte</form>
      <lemma>brengen</lemma>
      <pos>VRB(finiteness=fin,tense=past)</pos>
    </w>
    <w>
      <form>een</form>
      <lemma>een</lemma>
      <pos>PD(type=indef,subtype=art,position=prenom)</pos>
    </w>
    <w>
      <form>cruus</form>
      <lemma>kruis</lemma>
      <pos>NOU-C(number=sg)</pos>
    </w>
    <w>
      <form>root</form>
      <lemma>rood</lemma>
      <pos>AA(degree=pos,position=postnom)</pos>
    </w>
  </l>
  <l n="39" tokens="Voer sinen boesem wel gheprent" lemmas="voor zijn boezem wel prenten">
    <w>
      <form>Voer</form>
      <lemma>voor</lemma>
      <pos>ADP(type=pre)</pos>
    </w>
    <w>
      <form>sinen</form>
      <lemma>zijn</lemma>
      <pos>PD(type=poss,position=prenom)</pos>
    </w>
    <w>
      <form>boesem</form>
      <lemma>boezem</lemma>
      <pos>NOU-C(number=sg)</pos>
    </w>
    <w>
      <form>wel</form>
      <lemma>wel</lemma>
      <pos>ADV(type=reg)</pos>
    </w>
    <w>
      <form>gheprent</form>
      <lemma>prenten</lemma>
      <pos>VRB(finiteness=pastpart)</pos>
    </w>
  </l>
  <l n="40" tokens="Si brochten an wit uestiment" lemmas="zij brengen aan wit ustiment">
    <w>
      <form>Si</form>
      <lemma>zij</lemma>
      <pos>PD(type=pers,position=free)</pos>
    </w>
    <w>
      <form>brochten</form>
      <lemma>brengen</lemma>
      <pos>VRB(finiteness=fin,tense=past)</pos>
    </w>
    <w>
      <form>an</form>
      <lemma>aan</lemma>
      <pos>ADP(type=pre)</pos>
    </w>
    <w>
      <form>wit</form>
      <lemma>wit</lemma>
      <pos>AA(degree=pos,position=prenom)</pos>
    </w>
    <w>
      <form>uestiment</form>
      <lemma>ustiment</lemma>
      <pos>NOU-C(number=sg)</pos>
    </w>
  </l>
  <l n="41" tokens="Si quamen al singhende bi hande" lemmas="zij komen al zingen bij hand">
    <w>
      <form>Si</form>
      <lemma>zij</lemma>
      <pos>PD(type=pers,position=free)</pos>
    </w>
    <w>
      <form>quamen</form>
      <lemma>komen</lemma>
      <pos>VRB(finiteness=fin,tense=past)</pos>
    </w>
    <w>
      <form>al</form>
      <lemma>al</lemma>
      <pos>ADV(type=reg)</pos>
    </w>
    <w>
      <form>singhende</form>
      <lemma>zingen</lemma>
      <pos>VRB(finiteness=prespart)</pos>
    </w>
    <w>
      <form>bi</form>
      <lemma>bij</lemma>
      <pos>ADP(type=pre)</pos>
    </w>
    <w>
      <form>hande</form>
      <lemma>hand</lemma>
      <pos>NOU-C(number=pl)</pos>
    </w>
  </l>
  <l n="42" tokens="Si reden dus o oriande" lemmas="zij reden dus o Oriande">
    <w>
      <form>Si</form>
      <lemma>zij</lemma>
      <pos>PD(type=pers,position=free)</pos>
    </w>
    <w>
      <form>reden</form>
      <lemma>reden</lemma>
      <pos>VRB(finiteness=fin,tense=past)</pos>
    </w>
    <w>
      <form>dus</form>
      <lemma>dus</lemma>
      <pos>ADV(type=reg)</pos>
    </w>
    <w>
      <form>o</form>
      <lemma>o</lemma>
      <pos>INT</pos>
    </w>
    <w>
      <form>oriande</form>
      <lemma>Oriande</lemma>
      <pos>NOU-P</pos>
    </w>
  </l>
  <l n="43" tokens="Bin deser poorten die es claer" lemmas="bin deze poort die zijn klaar">
    <w>
      <form>Bin</form>
      <lemma>bin</lemma>
      <pos>ADP(type=pre)</pos>
    </w>
    <w>
      <form>deser</form>
      <lemma>deze</lemma>
      <pos>PD(type=d-p,subtype=oth,position=prenom)</pos>
    </w>
    <w>
      <form>poorten</form>
      <lemma>poort</lemma>
      <pos>NOU-C(number=sg)</pos>
    </w>
    <w>
      <form>die</form>
      <lemma>die</lemma>
      <pos>PD(type=d-p,position=free)</pos>
    </w>
    <w>
      <form>es</form>
      <lemma>zijn</lemma>
      <pos>VRB(finiteness=fin,tense=pres)</pos>
    </w>
    <w>
      <form>claer</form>
      <lemma>klaar</lemma>
      <pos>AA(degree=pos,position=free)</pos>
    </w>
  </l>
  <l n="44" tokens="Sullen wi v leden sijt sonder vaer" lemmas="zullen wij uw lid zijn zonder vaar">
    <w>
      <form>Sullen</form>
      <lemma>zullen</lemma>
      <pos>VRB(finiteness=fin,tense=pres)</pos>
    </w>
    <w>
      <form>wi</form>
      <lemma>wij</lemma>
      <pos>PD(type=pers,position=free)</pos>
    </w>
    <w>
      <form>v</form>
      <lemma>uw</lemma>
      <pos>PD(type=poss,position=prenom)</pos>
    </w>
    <w>
      <form>leden</form>
      <lemma>lid</lemma>
      <pos>NOU-C(number=pl)</pos>
    </w>
    <w>
      <form>sijt</form>
      <lemma>zijn</lemma>
      <pos>VRB(finiteness=fin,tense=pres)</pos>
    </w>
    <w>
      <form>sonder</form>
      <lemma>zonder</lemma>
      <pos>ADP(type=pre)</pos>
    </w>
    <w>
      <form>vaer</form>
      <lemma>vaar</lemma>
      <pos>NOU-C(number=sg)</pos>
    </w>
  </l>
  <l n="45" tokens="Daer ghi sult sien sinte patrike" lemmas="daar gij zullen zien Sint Patrijk">
    <w>
      <form>Daer</form>
      <lemma>daar</lemma>
      <pos>ADV(type=reg)</pos>
    </w>
    <w>
      <form>ghi</form>
      <lemma>gij</lemma>
      <pos>PD(type=pers,position=free)</pos>
    </w>
    <w>
      <form>sult</form>
      <lemma>zullen</lemma>
      <pos>VRB(finiteness=fin,tense=pres)</pos>
    </w>
    <w>
      <form>sien</form>
      <lemma>zien</lemma>
      <pos>VRB(finiteness=inf)</pos>
    </w>
    <w>
      <form>sinte</form>
      <lemma>Sint</lemma>
      <pos>NOU-P</pos>
    </w>
    <w>
      <form>patrike</form>
      <lemma>Patrijk</lemma>
      <pos>NOU-P</pos>
    </w>
  </l>
  <l n="46" tokens="Om v oriande antwoerde gheeft" lemmas="om uw oriande antwoorden geven">
    <w>
      <form>Om</form>
      <lemma>om</lemma>
      <pos>ADP(type=pre)</pos>
    </w>
    <w>
      <form>v</form>
      <lemma>uw</lemma>
      <pos>PD(type=poss,position=prenom)</pos>
    </w>
    <w>
      <form>oriande</form>
      <lemma>oriande</lemma>
      <pos>NOU-C(number=sg)</pos>
    </w>
    <w>
      <form>antwoerde</form>
      <lemma>antwoorden</lemma>
      <pos>VRB(finiteness=fin,tense=past)</pos>
    </w>
    <w>
      <form>gheeft</form>
      <lemma>geven</lemma>
      <pos>VRB(finiteness=pastpart)</pos>
    </w>
  </l>
  <l n="47" tokens="Dies moete god ghedanct sijn" lemmas="dies moeten God danken zijn">
    <w>
      <form>Dies</form>
      <lemma>dies</lemma>
      <pos>ADV(type=reg)</pos>
    </w>
    <w>
      <form>moete</form>
      <lemma>moeten</lemma>
      <pos>VRB(finiteness=fin,tense=pres)</pos>
    </w>
    <w>
      <form>god</form>
      <lemma>God</lemma>
      <pos>NOU-P</pos>
    </w>
    <w>
      <form>ghedanct</form>
      <lemma>danken</lemma>
      <pos>VRB(finiteness=pastpart)</pos>
    </w>
    <w>
      <form>sijn</form>
      <lemma>zijn</lemma>
      <pos>VRB(finiteness=inf)</pos>
    </w>
  </l>
  <l n="48" tokens="Die van watre maecte wijn" lemmas="die van wat maken wijn">
    <w>
      <form>Die</form>
      <lemma>die</lemma>
      <pos>PD(type=d-p,position=free)</pos>
    </w>
    <w>
      <form>van</form>
      <lemma>van</lemma>
      <pos>ADP(type=pre)</pos>
    </w>
    <w>
      <form>watre</form>
      <lemma>wat</lemma>
      <pos>PD(type=indef,position=free)</pos>
    </w>
    <w>
      <form>maecte</form>
      <lemma>maken</lemma>
      <pos>VRB(finiteness=fin,tense=past)</pos>
    </w>
    <w>
      <form>wijn</form>
      <lemma>wijn</lemma>
      <pos>NOU-C(number=sg)</pos>
    </w>
  </l>
  <l n="49" tokens="Dat hi mi hier toe heeft vercoren" lemmas="dat hij ik hier toe hebben verkiezen">
    <w>
      <form>Dat</form>
      <lemma>dat</lemma>
      <pos>CONJ(type=sub)</pos>
    </w>
    <w>
      <form>hi</form>
      <lemma>hij</lemma>
      <pos>PD(type=pers,position=free)</pos>
    </w>
    <w>
      <form>mi</form>
      <lemma>ik</lemma>
      <pos>PD(type=pers,position=free)</pos>
    </w>
    <w>
      <form>hier</form>
      <lemma>hier</lemma>
      <pos>ADV(type=pron)</pos>
    </w>
    <w>
      <form>toe</form>
      <lemma>toe</lemma>
      <pos>ADV(type=pron)</pos>
    </w>
    <w>
      <form>heeft</form>
      <lemma>hebben</lemma>
      <pos>VRB(finiteness=fin,tense=pres)</pos>
    </w>
    <w>
      <form>vercoren</form>
      <lemma>verkiezen</lemma>
      <pos>VRB(finiteness=pastpart)</pos>
    </w>
  </l>
  <l n="50" tokens="Soe seinde haer bachten ende voren" lemmas="zo seinen haar bacht en voren">
    <w>
      <form>Soe</form>
      <lemma>zo</lemma>
      <pos>ADV(type=reg)</pos>
    </w>
    <w>
      <form>seinde</form>
      <lemma>seinen</lemma>
      <pos>VRB(finiteness=fin,tense=past)</pos>
    </w>
    <w>
      <form>haer</form>
      <lemma>haar</lemma>
      <pos>PD(type=poss,position=prenom)</pos>
    </w>
    <w>
      <form>bachten</form>
      <lemma>bacht</lemma>
      <pos>NOU-C(number=pl)</pos>
    </w>
    <w>
      <form>ende</form>
      <lemma>en</lemma>
      <pos>CONJ(type=coor)</pos>
    </w>
    <w>
      <form>voren</form>
      <lemma>voren</lemma>
      <pos>ADV(type=reg)</pos>
    </w>
  </l>
  <l n="51" tokens="Ende ghinc men in die poorten" lemmas="en gaan men in die poort">
    <w>
      <form>Ende</form>
      <lemma>en</lemma>
      <pos>CONJ(type=coor)</pos>
    </w>
    <w>
      <form>ghinc</form>
      <lemma>gaan</lemma>
      <pos>VRB(finiteness=fin,tense=past)</pos>
    </w>
    <w>
      <form>men</form>
      <lemma>men</lemma>
      <pos>PD(type=pers,position=free)</pos>
    </w>
    <w>
      <form>in</form>
      <lemma>in</lemma>
      <pos>ADP(type=pre)</pos>
    </w>
    <w>
      <form>die</form>
      <lemma>die</lemma>
      <pos>PD(type=d-p,subtype=art,position=prenom)</pos>
    </w>
    <w>
      <form>poorten</form>
      <lemma>poort</lemma>
      <pos>NOU-C(number=pl)</pos>
    </w>
  </l>
  <l n="52" tokens="Die bede waren van gods soorte" lemmas="die bede zijn van God soort">
    <w>
      <form>Die</form>
      <lemma>die</lemma>
      <pos>PD(type=d-p,position=free)</pos>
    </w>
    <w>
      <form>bede</form>
      <lemma>bede</lemma>
      <pos>NOU-C(number=sg)</pos>
    </w>
    <w>
      <form>waren</form>
      <lemma>zijn</lemma>
      <pos>VRB(finiteness=fin,tense=past)</pos>
    </w>
    <w>
      <form>van</form>
      <lemma>van</lemma>
      <pos>ADP(type=pre)</pos>
    </w>
    <w>
      <form>gods</form>
      <lemma>God</lemma>
      <pos>NOU-P</pos>
    </w>
    <w>
      <form>soorte</form>
      <lemma>soort</lemma>
      <pos>NOU-C(number=sg)</pos>
    </w>
  </l>
  <l n="53" tokens="Entie bede waren verchiert" lemmas="en+de bede zijn versieren">
    <w>
      <form>Entie</form>
      <lemma>en+de</lemma>
      <pos>CONJ(type=coor)+PD(type=d-p,subtype=art,position=prenom)</pos>
    </w>
    <w>
      <form>bede</form>
      <lemma>bede</lemma>
      <pos>NOU-C(number=sg)</pos>
    </w>
    <w>
      <form>waren</form>
      <lemma>zijn</lemma>
      <pos>VRB(finiteness=fin,tense=past)</pos>
    </w>
    <w>
      <form>verchiert</form>
      <lemma>versieren</lemma>
      <pos>VRB(finiteness=pastpart)</pos>
    </w>
  </l>
  <l n="54" tokens="Met groten lichte ende ghepuergiert" lemmas="met groot licht en purgeren">
    <w>
      <form>Met</form>
      <lemma>met</lemma>
      <pos>ADP(type=pre)</pos>
    </w>
    <w>
      <form>groten</form>
      <lemma>groot</lemma>
      <pos>AA(degree=pos,position=prenom)</pos>
    </w>
    <w>
      <form>lichte</form>
      <lemma>licht</lemma>
      <pos>NOU-C(number=sg)</pos>
    </w>
    <w>
      <form>ende</form>
      <lemma>en</lemma>
      <pos>CONJ(type=coor)</pos>
    </w>
    <w>
      <form>ghepuergiert</form>
      <lemma>purgeren</lemma>
      <pos>VRB(finiteness=pastpart)</pos>
    </w>
  </l>
  <l n="55" tokens="Van allen smetten van allen sonden" lemmas="van al smet van al zonde">
    <w>
      <form>Van</form>
      <lemma>van</lemma>
      <pos>ADP(type=pre)</pos>
    </w>
    <w>
      <form>allen</form>
      <lemma>al</lemma>
      <pos>PD(type=indef,subtype=oth,position=prenom)</pos>
    </w>
    <w>
      <form>smetten</form>
      <lemma>smet</lemma>
      <pos>NOU-C(number=pl)</pos>
    </w>
    <w>
      <form>van</form>
      <lemma>van</lemma>
      <pos>ADP(type=pre)</pos>
    </w>
    <w>
      <form>allen</form>
      <lemma>al</lemma>
      <pos>PD(type=indef,subtype=oth,position=prenom)</pos>
    </w>
    <w>
      <form>sonden</form>
      <lemma>zonde</lemma>
      <pos>NOU-C(number=pl)</pos>
    </w>
  </l>
  <l n="56" tokens="Dus ghinc die vrouwe te dien stonden" lemmas="dus gaan die vrouwe te dat stond">
    <w>
      <form>Dus</form>
      <lemma>dus</lemma>
      <pos>ADV(type=reg)</pos>
    </w>
    <w>
      <form>ghinc</form>
      <lemma>gaan</lemma>
      <pos>VRB(finiteness=fin,tense=past)</pos>
    </w>
    <w>
      <form>die</form>
      <lemma>die</lemma>
      <pos>PD(type=d-p,subtype=art,position=prenom)</pos>
    </w>
    <w>
      <form>vrouwe</form>
      <lemma>vrouwe</lemma>
      <pos>NOU-C(number=sg)</pos>
    </w>
    <w>
      <form>te</form>
      <lemma>te</lemma>
      <pos>ADP(type=pre)</pos>
    </w>
    <w>
      <form>dien</form>
      <lemma>dat</lemma>
      <pos>PD(type=d-p,subtype=oth,position=prenom)</pos>
    </w>
    <w>
      <form>stonden</form>
      <lemma>stond</lemma>
      <pos>NOU-C(number=sg)</pos>
    </w>
  </l>
  <l n="57" tokens="Daer soe selue wilde sijn" lemmas="daar zij zelf willen zijn">
    <w>
      <form>Daer</form>
      <lemma>daar</lemma>
      <pos>ADV(type=reg)</pos>
    </w>
    <w>
      <form>soe</form>
      <lemma>zij</lemma>
      <pos>PD(type=pers,position=free)</pos>
    </w>
    <w>
      <form>selue</form>
      <lemma>zelf</lemma>
      <pos>PD(type=d-p,position=free)</pos>
    </w>
    <w>
      <form>wilde</form>
      <lemma>willen</lemma>
      <pos>VRB(finiteness=fin,tense=past)</pos>
    </w>
    <w>
      <form>sijn</form>
      <lemma>zijn</lemma>
      <pos>VRB(finiteness=inf)</pos>
    </w>
  </l>
  <l n="58" tokens="Die III pylaren van goude fijn" lemmas="die drie pilaar van goud fijn">
    <w>
      <form>Die</form>
      <lemma>die</lemma>
      <pos>PD(type=d-p,subtype=art,position=prenom)</pos>
    </w>
    <w>
      <form>III</form>
      <lemma>drie</lemma>
      <pos>NUM(type=card,position=prenom,representation=rom)</pos>
    </w>
    <w>
      <form>pylaren</form>
      <lemma>pilaar</lemma>
      <pos>NOU-C(number=pl)</pos>
    </w>
    <w>
      <form>van</form>
      <lemma>van</lemma>
      <pos>ADP(type=pre)</pos>
    </w>
    <w>
      <form>goude</form>
      <lemma>goud</lemma>
      <pos>NOU-C(number=sg)</pos>
    </w>
    <w>
      <form>fijn</form>
      <lemma>fijn</lemma>
      <pos>AA(degree=pos,position=postnom)</pos>
    </w>
  </l>
  <l n="59" tokens="Ende van seluere ende van cristale" lemmas="en van zelf en van Christale">
    <w>
      <form>Ende</form>
      <lemma>en</lemma>
      <pos>CONJ(type=coor)</pos>
    </w>
    <w>
      <form>van</form>
      <lemma>van</lemma>
      <pos>ADP(type=pre)</pos>
    </w>
    <w>
      <form>seluere</form>
      <lemma>zelf</lemma>
      <pos>PD(type=d-p,position=free)</pos>
    </w>
    <w>
      <form>ende</form>
      <lemma>en</lemma>
      <pos>CONJ(type=coor)</pos>
    </w>
    <w>
      <form>van</form>
      <lemma>van</lemma>
      <pos>ADP(type=pre)</pos>
    </w>
    <w>
      <form>cristale</form>
      <lemma>Christale</lemma>
      <pos>NOU-P</pos>
    </w>
  </l>
  <l n="60" tokens="Sach soe staan daer die sale" lemmas="zien zij staan daar die sale">
    <w>
      <form>Sach</form>
      <lemma>zien</lemma>
      <pos>VRB(finiteness=fin,tense=past)</pos>
    </w>
    <w>
      <form>soe</form>
      <lemma>zij</lemma>
      <pos>PD(type=pers,position=free)</pos>
    </w>
    <w>
      <form>staan</form>
      <lemma>staan</lemma>
      <pos>VRB(finiteness=inf)</pos>
    </w>
    <w>
      <form>daer</form>
      <lemma>daar</lemma>
      <pos>ADV(type=pron)</pos>
    </w>
    <w>
      <form>die</form>
      <lemma>die</lemma>
      <pos>PD(type=d-p,subtype=art,position=prenom)</pos>
    </w>
    <w>
      <form>sale</form>
      <lemma>sale</lemma>
      <pos>NOU-C(number=sg)</pos>
    </w>
  </l>
  <l n="61" tokens="Op ruste ende die woninghe" lemmas="op rust en die woning">
    <w>
      <form>Op</form>
      <lemma>op</lemma>
      <pos>ADP(type=pre)</pos>
    </w>
    <w>
      <form>ruste</form>
      <lemma>rust</lemma>
      <pos>NOU-C(number=sg)</pos>
    </w>
    <w>
      <form>ende</form>
      <lemma>en</lemma>
      <pos>CONJ(type=coor)</pos>
    </w>
    <w>
      <form>die</form>
      <lemma>die</lemma>
      <pos>PD(type=d-p,subtype=art,position=prenom)</pos>
    </w>
    <w>
      <form>woninghe</form>
      <lemma>woning</lemma>
      <pos>NOU-C(number=sg)</pos>
    </w>
  </l>
  <l n="62" tokens="Noit mensche sach scoonre dinghe" lemmas="nooit mens zien schoon ding">
    <w>
      <form>Noit</form>
      <lemma>nooit</lemma>
      <pos>ADV(type=reg)</pos>
    </w>
    <w>
      <form>mensche</form>
      <lemma>mens</lemma>
      <pos>NOU-C(number=sg)</pos>
    </w>
    <w>
      <form>sach</form>
      <lemma>zien</lemma>
      <pos>VRB(finiteness=fin,tense=past)</pos>
    </w>
    <w>
      <form>scoonre</form>
      <lemma>schoon</lemma>
      <pos>AA(degree=comp,position=prenom)</pos>
    </w>
    <w>
      <form>dinghe</form>
      <lemma>ding</lemma>
      <pos>NOU-C(number=pl)</pos>
    </w>
  </l>
  <l n="63" tokens="Dan oriande daer mochte sien" lemmas="dan Oriande daar mogen zien">
    <w>
      <form>Dan</form>
      <lemma>dan</lemma>
      <pos>CONJ(type=sub)</pos>
    </w>
    <w>
      <form>oriande</form>
      <lemma>Oriande</lemma>
      <pos>NOU-P</pos>
    </w>
    <w>
      <form>daer</form>
      <lemma>daar</lemma>
      <pos>ADV(type=reg)</pos>
    </w>
    <w>
      <form>mochte</form>
      <lemma>mogen</lemma>
      <pos>VRB(finiteness=fin,tense=past)</pos>
    </w>
    <w>
      <form>sien</form>
      <lemma>zien</lemma>
      <pos>VRB(finiteness=inf)</pos>
    </w>
  </l>
  <l n="64" tokens="Die XII moneke sach soe mettien" lemmas="die twaalf monnik zien zo mettien">
    <w>
      <form>Die</form>
      <lemma>die</lemma>
      <pos>PD(type=d-p,subtype=art,position=prenom)</pos>
    </w>
    <w>
      <form>XII</form>
      <lemma>twaalf</lemma>
      <pos>NUM(type=ord,position=prenom,representation=rom)</pos>
    </w>
    <w>
      <form>moneke</form>
      <lemma>monnik</lemma>
      <pos>NOU-C(number=sg)</pos>
    </w>
    <w>
      <form>sach</form>
      <lemma>zien</lemma>
      <pos>VRB(finiteness=fin,tense=past)</pos>
    </w>
    <w>
      <form>soe</form>
      <lemma>zo</lemma>
      <pos>ADV(type=reg)</pos>
    </w>
    <w>
      <form>mettien</form>
      <lemma>mettien</lemma>
      <pos>ADV(type=reg)</pos>
    </w>
  </l>
  <l n="65" tokens="Al eens ghecleet met witten abite" lemmas="al eens kleden met wit habijt">
    <w>
      <form>Al</form>
      <lemma>al</lemma>
      <pos>ADV(type=reg)</pos>
    </w>
    <w>
      <form>eens</form>
      <lemma>eens</lemma>
      <pos>ADV(type=reg)</pos>
    </w>
    <w>
      <form>ghecleet</form>
      <lemma>kleden</lemma>
      <pos>VRB(finiteness=pastpart)</pos>
    </w>
    <w>
      <form>met</form>
      <lemma>met</lemma>
      <pos>ADP(type=pre)</pos>
    </w>
    <w>
      <form>witten</form>
      <lemma>wit</lemma>
      <pos>AA(degree=pos,position=prenom)</pos>
    </w>
    <w>
      <form>abite</form>
      <lemma>habijt</lemma>
      <pos>NOU-C(number=sg)</pos>
    </w>
  </l>
  <l n="66" tokens="Si songhen lude met iolite" lemmas="zij zingen luid met joliet">
    <w>
      <form>Si</form>
      <lemma>zij</lemma>
      <pos>PD(type=pers,position=free)</pos>
    </w>
    <w>
      <form>songhen</form>
      <lemma>zingen</lemma>
      <pos>VRB(finiteness=fin,tense=past)</pos>
    </w>
    <w>
      <form>lude</form>
      <lemma>luid</lemma>
      <pos>NOU-C(number=pl)</pos>
    </w>
    <w>
      <form>met</form>
      <lemma>met</lemma>
      <pos>ADP(type=pre)</pos>
    </w>
    <w>
      <form>iolite</form>
      <lemma>joliet</lemma>
      <pos>NOU-C(number=sg)</pos>
    </w>
  </l>
  <l n="67" tokens="Gode te loue ende dreuen spel" lemmas="God te loven en dreven spel">
    <w>
      <form>Gode</form>
      <lemma>God</lemma>
      <pos>NOU-P</pos>
    </w>
    <w>
      <form>te</form>
      <lemma>te</lemma>
      <pos>ADP(type=pre)</pos>
    </w>
    <w>
      <form>loue</form>
      <lemma>loven</lemma>
      <pos>VRB(finiteness=inf)</pos>
    </w>
    <w>
      <form>ende</form>
      <lemma>en</lemma>
      <pos>CONJ(type=coor)</pos>
    </w>
    <w>
      <form>dreuen</form>
      <lemma>dreven</lemma>
      <pos>VRB(finiteness=fin,tense=pres)</pos>
    </w>
    <w>
      <form>spel</form>
      <lemma>spel</lemma>
      <pos>NOU-C(number=sg)</pos>
    </w>
  </l>
  <l n="68" tokens="Benedictus dominus deus israel" lemmas="benedictus dominus deus Israël">
    <w>
      <form>Benedictus</form>
      <lemma>benedictus</lemma>
      <pos>RES(type=for)</pos>
    </w>
    <w>
      <form>dominus</form>
      <lemma>dominus</lemma>
      <pos>RES(type=for)</pos>
    </w>
    <w>
      <form>deus</form>
      <lemma>deus</lemma>
      <pos>RES(type=for)</pos>
    </w>
    <w>
      <form>israel</form>
      <lemma>Israël</lemma>
      <pos>NOU-P</pos>
    </w>
  </l>
  <l n="69" tokens="Oriande gheliet haer blidelike" lemmas="Oriande gelaten haar blijdelijk">
    <w>
      <form>Oriande</form>
      <lemma>Oriande</lemma>
      <pos>NOU-P</pos>
    </w>
    <w>
      <form>gheliet</form>
      <lemma>gelaten</lemma>
      <pos>VRB(finiteness=fin,tense=pres)</pos>
    </w>
    <w>
      <form>haer</form>
      <lemma>haar</lemma>
      <pos>PD(type=poss,position=prenom)</pos>
    </w>
    <w>
      <form>blidelike</form>
      <lemma>blijdelijk</lemma>
      <pos>ADV(type=reg)</pos>
    </w>
  </l>
  <l n="70" tokens="Om dat soe sach sinte patrike" lemmas="om dat zij zien Sint Patrijk">
    <w>
      <form>Om</form>
      <lemma>om</lemma>
      <pos>CONJ(type=sub)</pos>
    </w>
    <w>
      <form>dat</form>
      <lemma>dat</lemma>
      <pos>CONJ(type=sub)</pos>
    </w>
    <w>
      <form>soe</form>
      <lemma>zij</lemma>
      <pos>PD(type=pers,position=free)</pos>
    </w>
    <w>
      <form>sach</form>
      <lemma>zien</lemma>
      <pos>VRB(finiteness=fin,tense=past)</pos>
    </w>
    <w>
      <form>sinte</form>
      <lemma>Sint</lemma>
      <pos>NOU-P</pos>
    </w>
    <w>
      <form>patrike</form>
      <lemma>Patrijk</lemma>
      <pos>NOU-P</pos>
    </w>
  </l>
  <l n="71" tokens="Die tote haer sede vriendelike kint" lemmas="die tot zij zeggen vriendelijk kind">
    <w>
      <form>Die</form>
      <lemma>die</lemma>
      <pos>PD(type=d-p,position=free)</pos>
    </w>
    <w>
      <form>tote</form>
      <lemma>tot</lemma>
      <pos>ADP(type=pre)</pos>
    </w>
    <w>
      <form>haer</form>
      <lemma>zij</lemma>
      <pos>PD(type=pers,position=free)</pos>
    </w>
    <w>
      <form>sede</form>
      <lemma>zeggen</lemma>
      <pos>VRB(finiteness=fin,tense=past)</pos>
    </w>
    <w>
      <form>vriendelike</form>
      <lemma>vriendelijk</lemma>
      <pos>AA(degree=pos,position=prenom)</pos>
    </w>
    <w>
      <form>kint</form>
      <lemma>kind</lemma>
      <pos>NOU-C(number=sg)</pos>
    </w>
  </l>
  <l n="72" tokens="Jc rade vdat ghi gode mint" lemmas="ik raden uitdat gij God minnen">
    <w>
      <form>Jc</form>
      <lemma>ik</lemma>
      <pos>PD(type=pers,position=free)</pos>
    </w>
    <w>
      <form>rade</form>
      <lemma>raden</lemma>
      <pos>VRB(finiteness=fin,tense=pres)</pos>
    </w>
    <w>
      <form>vdat</form>
      <lemma>uitdat</lemma>
      <pos>PD(type=w-p,position=free)</pos>
    </w>
    <w>
      <form>ghi</form>
      <lemma>gij</lemma>
      <pos>PD(type=pers,position=free)</pos>
    </w>
    <w>
      <form>gode</form>
      <lemma>God</lemma>
      <pos>NOU-P</pos>
    </w>
    <w>
      <form>mint</form>
      <lemma>minnen</lemma>
      <pos>VRB(finiteness=fin,tense=pres)</pos>
    </w>
  </l>
  <l n="73" tokens="Van rochefloer dochter mijn" lemmas="van Rochefloer dochter mijn">
    <w>
      <form>Van</form>
      <lemma>van</lemma>
      <pos>ADP(type=pre)</pos>
    </w>
    <w>
      <form>rochefloer</form>
      <lemma>Rochefloer</lemma>
      <pos>NOU-P</pos>
    </w>
    <w>
      <form>dochter</form>
      <lemma>dochter</lemma>
      <pos>NOU-C(number=sg)</pos>
    </w>
    <w>
      <form>mijn</form>
      <lemma>mijn</lemma>
      <pos>PD(type=poss,position=postnom)</pos>
    </w>
  </l>
  <l n="74" tokens="Dinen sonden al vergheuen sijn" lemmas="dijn zonde al vergeven zijn">
    <w>
      <form>Dinen</form>
      <lemma>dijn</lemma>
      <pos>PD(type=poss,position=prenom)</pos>
    </w>
    <w>
      <form>sonden</form>
      <lemma>zonde</lemma>
      <pos>NOU-C(number=pl)</pos>
    </w>
    <w>
      <form>al</form>
      <lemma>al</lemma>
      <pos>ADV(type=reg)</pos>
    </w>
    <w>
      <form>vergheuen</form>
      <lemma>vergeven</lemma>
      <pos>VRB(finiteness=pastpart)</pos>
    </w>
    <w>
      <form>sijn</form>
      <lemma>zijn</lemma>
      <pos>VRB(finiteness=fin,tense=pres)</pos>
    </w>
  </l>
  <l n="75" tokens="Om dattu spraecs biechte waerachtich" lemmas="om+hij dat+du spreken biecht waarachtig">
    <w>
      <form>Om</form>
      <lemma>om+hij</lemma>
      <pos>CONJ(type=sub)+PD(type=pers,position=free)</pos>
    </w>
    <w>
      <form>dattu</form>
      <lemma>dat+du</lemma>
      <pos>CONJ(type=sub)+PD(type=pers,position=free)</pos>
    </w>
    <w>
      <form>spraecs</form>
      <lemma>spreken</lemma>
      <pos>VRB(finiteness=fin,tense=past)</pos>
    </w>
    <w>
      <form>biechte</form>
      <lemma>biecht</lemma>
      <pos>NOU-C(number=sg)</pos>
    </w>
    <w>
      <form>waerachtich</form>
      <lemma>waarachtig</lemma>
      <pos>AA(degree=pos,position=free)</pos>
    </w>
  </l>
  <l n="76" tokens="Tote minen abdt ende du crachtich" lemmas="tot mijn abt en du krachtig">
    <w>
      <form>Tote</form>
      <lemma>tot</lemma>
      <pos>ADP(type=pre)</pos>
    </w>
    <w>
      <form>minen</form>
      <lemma>mijn</lemma>
      <pos>PD(type=poss,position=prenom)</pos>
    </w>
    <w>
      <form>abdt</form>
      <lemma>abt</lemma>
      <pos>NOU-C(number=sg)</pos>
    </w>
    <w>
      <form>ende</form>
      <lemma>en</lemma>
      <pos>CONJ(type=coor)</pos>
    </w>
    <w>
      <form>du</form>
      <lemma>du</lemma>
      <pos>PD(type=pers,position=free)</pos>
    </w>
    <w>
      <form>crachtich</form>
      <lemma>krachtig</lemma>
      <pos>AA(degree=pos,position=free)</pos>
    </w>
  </l>
  <l n="77" tokens="Met goeden gheloue weder stonts" lemmas="met goed geloof weder stonds">
    <w>
      <form>Met</form>
      <lemma>met</lemma>
      <pos>ADP(type=pre)</pos>
    </w>
    <w>
      <form>goeden</form>
      <lemma>goed</lemma>
      <pos>AA(degree=pos,position=prenom)</pos>
    </w>
    <w>
      <form>gheloue</form>
      <lemma>geloof</lemma>
      <pos>NOU-C(number=sg)</pos>
    </w>
    <w>
      <form>weder</form>
      <lemma>weder</lemma>
      <pos>ADV(type=reg)</pos>
    </w>
    <w>
      <form>stonts</form>
      <lemma>stonds</lemma>
      <pos>ADV(type=reg)</pos>
    </w>
  </l>
  <l n="78" tokens="Die opti wrochten hare temptacie" lemmas="die opti werken haar temptatie">
    <w>
      <form>Die</form>
      <lemma>die</lemma>
      <pos>PD(type=d-p,position=free)</pos>
    </w>
    <w>
      <form>opti</form>
      <lemma>opti</lemma>
      <pos>NOU-C(number=sg)</pos>
    </w>
    <w>
      <form>wrochten</form>
      <lemma>werken</lemma>
      <pos>VRB(finiteness=fin,tense=past)</pos>
    </w>
    <w>
      <form>hare</form>
      <lemma>haar</lemma>
      <pos>PD(type=poss,position=prenom)</pos>
    </w>
    <w>
      <form>temptacie</form>
      <lemma>temptatie</lemma>
      <pos>NOU-C(number=sg)</pos>
    </w>
  </l>
  <l n="79" tokens="Lieue kint gods gracie" lemmas="lief kind God gratie">
    <w>
      <form>Lieue</form>
      <lemma>lief</lemma>
      <pos>AA(degree=pos,position=prenom)</pos>
    </w>
    <w>
      <form>kint</form>
      <lemma>kind</lemma>
      <pos>NOU-C(number=sg)</pos>
    </w>
    <w>
      <form>gods</form>
      <lemma>God</lemma>
      <pos>NOU-P</pos>
    </w>
    <w>
      <form>gracie</form>
      <lemma>gratie</lemma>
      <pos>NOU-C(number=sg)</pos>
    </w>
  </l>
  <l n="80" tokens="Daer dede haer sinte patrijc mettesen" lemmas="daar doen zij Sint Patrijc mettezen">
    <w>
      <form>Daer</form>
      <lemma>daar</lemma>
      <pos>ADV(type=reg)</pos>
    </w>
    <w>
      <form>dede</form>
      <lemma>doen</lemma>
      <pos>VRB(finiteness=fin,tense=past)</pos>
    </w>
    <w>
      <form>haer</form>
      <lemma>zij</lemma>
      <pos>PD(type=pers,position=free)</pos>
    </w>
    <w>
      <form>sinte</form>
      <lemma>Sint</lemma>
      <pos>NOU-P</pos>
    </w>
    <w>
      <form>patrijc</form>
      <lemma>Patrijc</lemma>
      <pos>NOU-P</pos>
    </w>
    <w>
      <form>mettesen</form>
      <lemma>mettezen</lemma>
      <pos>ADV(type=reg)</pos>
    </w>
  </l>
  <l n="81" tokens="Dancte sere der auenture" lemmas="danken zeer de avontuur">
    <w>
      <form>Dancte</form>
      <lemma>danken</lemma>
      <pos>VRB(finiteness=fin,tense=past)</pos>
    </w>
    <w>
      <form>sere</form>
      <lemma>zeer</lemma>
      <pos>ADV(type=reg)</pos>
    </w>
    <w>
      <form>der</form>
      <lemma>de</lemma>
      <pos>PD(type=d-p,subtype=art,position=prenom)</pos>
    </w>
    <w>
      <form>auenture</form>
      <lemma>avontuur</lemma>
      <pos>NOU-C(number=sg)</pos>
    </w>
  </l>
  <l n="82" tokens="Ende gode noch toe was open die dure" lemmas="en God nog toe zijn open die deur">
    <w>
      <form>Ende</form>
      <lemma>en</lemma>
      <pos>CONJ(type=coor)</pos>
    </w>
    <w>
      <form>gode</form>
      <lemma>God</lemma>
      <pos>NOU-P</pos>
    </w>
    <w>
      <form>noch</form>
      <lemma>nog</lemma>
      <pos>ADV(type=reg)</pos>
    </w>
    <w>
      <form>toe</form>
      <lemma>toe</lemma>
      <pos>ADV(type=reg)</pos>
    </w>
    <w>
      <form>was</form>
      <lemma>zijn</lemma>
      <pos>VRB(finiteness=fin,tense=past)</pos>
    </w>
    <w>
      <form>open</form>
      <lemma>open</lemma>
      <pos>AA(degree=pos,position=free)</pos>
    </w>
    <w>
      <form>die</form>
      <lemma>die</lemma>
      <pos>PD(type=d-p,subtype=art,position=prenom)</pos>
    </w>
    <w>
      <form>dure</form>
      <lemma>deur</lemma>
      <pos>NOU-C(number=sg)</pos>
    </w>
  </l>
  <l n="83" tokens="Maer nigrieel voren lach" lemmas="maar Nigrieel voren lachen">
    <w>
      <form>Maer</form>
      <lemma>maar</lemma>
      <pos>CONJ(type=coor)</pos>
    </w>
    <w>
      <form>nigrieel</form>
      <lemma>Nigrieel</lemma>
      <pos>NOU-P</pos>
    </w>
    <w>
      <form>voren</form>
      <lemma>voren</lemma>
      <pos>ADV(type=reg)</pos>
    </w>
    <w>
      <form>lach</form>
      <lemma>lachen</lemma>
      <pos>VRB(finiteness=fin,tense=past)</pos>
    </w>
  </l>
  <l n="84" tokens="Ende teerst hi siere vrouwen sach" lemmas="en teerst hij zijn vrouw zien">
    <w>
      <form>Ende</form>
      <lemma>en</lemma>
      <pos>CONJ(type=coor)</pos>
    </w>
    <w>
      <form>teerst</form>
      <lemma>teerst</lemma>
      <pos>CONJ(type=sub)</pos>
    </w>
    <w>
      <form>hi</form>
      <lemma>hij</lemma>
      <pos>PD(type=pers,position=free)</pos>
    </w>
    <w>
      <form>siere</form>
      <lemma>zijn</lemma>
      <pos>PD(type=poss,position=prenom)</pos>
    </w>
    <w>
      <form>vrouwen</form>
      <lemma>vrouw</lemma>
      <pos>NOU-C(number=pl)</pos>
    </w>
    <w>
      <form>sach</form>
      <lemma>zien</lemma>
      <pos>VRB(finiteness=fin,tense=past)</pos>
    </w>
  </l>
  <l n="85" tokens="Was hi die alre blijtste man" lemmas="zijn hij die al blij man">
    <w>
      <form>Was</form>
      <lemma>zijn</lemma>
      <pos>VRB(finiteness=fin,tense=past)</pos>
    </w>
    <w>
      <form>hi</form>
      <lemma>hij</lemma>
      <pos>PD(type=pers,position=free)</pos>
    </w>
    <w>
      <form>die</form>
      <lemma>die</lemma>
      <pos>PD(type=d-p,subtype=art,position=prenom)</pos>
    </w>
    <w>
      <form>alre</form>
      <lemma>al</lemma>
      <pos>AA(degree=sup,position=prenom)</pos>
    </w>
    <w>
      <form>blijtste</form>
      <lemma>blij</lemma>
      <pos>AA(degree=sup,position=prenom)</pos>
    </w>
    <w>
      <form>man</form>
      <lemma>man</lemma>
      <pos>NOU-C(number=sg)</pos>
    </w>
  </l>
  <l n="86" tokens="Die noit der werelt lijf ghewan" lemmas="die nooit de wereld lijf gewinnen">
    <w>
      <form>Die</form>
      <lemma>die</lemma>
      <pos>PD(type=d-p,position=free)</pos>
    </w>
    <w>
      <form>noit</form>
      <lemma>nooit</lemma>
      <pos>ADV(type=reg)</pos>
    </w>
    <w>
      <form>der</form>
      <lemma>de</lemma>
      <pos>PD(type=d-p,subtype=art,position=prenom)</pos>
    </w>
    <w>
      <form>werelt</form>
      <lemma>wereld</lemma>
      <pos>NOU-C(number=sg)</pos>
    </w>
    <w>
      <form>lijf</form>
      <lemma>lijf</lemma>
      <pos>NOU-C(number=sg)</pos>
    </w>
    <w>
      <form>ghewan</form>
      <lemma>gewinnen</lemma>
      <pos>VRB(finiteness=fin,tense=past)</pos>
    </w>
  </l>
  <l n="87" tokens="Hi cussetse al omtrent" lemmas="hij kussen+zij al omtrent">
    <w>
      <form>Hi</form>
      <lemma>hij</lemma>
      <pos>PD(type=pers,position=free)</pos>
    </w>
    <w>
      <form>cussetse</form>
      <lemma>kussen+zij</lemma>
      <pos>VRB(finiteness=fin,tense=past)+PD(type=pers,position=free)</pos>
    </w>
    <w>
      <form>al</form>
      <lemma>al</lemma>
      <pos>ADV(type=reg)</pos>
    </w>
    <w>
      <form>omtrent</form>
      <lemma>omtrent</lemma>
      <pos>ADV(type=reg)</pos>
    </w>
  </l>
  <l n="88" tokens="Die abt ende sijn couent" lemmas="die abt en zijn kovende">
    <w>
      <form>Die</form>
      <lemma>die</lemma>
      <pos>PD(type=d-p,subtype=art,position=prenom)</pos>
    </w>
    <w>
      <form>abt</form>
      <lemma>abt</lemma>
      <pos>NOU-C(number=sg)</pos>
    </w>
    <w>
      <form>ende</form>
      <lemma>en</lemma>
      <pos>CONJ(type=coor)</pos>
    </w>
    <w>
      <form>sijn</form>
      <lemma>zijn</lemma>
      <pos>PD(type=poss,position=prenom)</pos>
    </w>
    <w>
      <form>couent</form>
      <lemma>kovende</lemma>
      <pos>NOU-C(number=sg)</pos>
    </w>
  </l>
  <l n="89" tokens="Verhoerden dat die vrouwe was comen" lemmas="verhoren dat die vrouwe zijn komen">
    <w>
      <form>Verhoerden</form>
      <lemma>verhoren</lemma>
      <pos>VRB(finiteness=fin,tense=past)</pos>
    </w>
    <w>
      <form>dat</form>
      <lemma>dat</lemma>
      <pos>CONJ(type=sub)</pos>
    </w>
    <w>
      <form>die</form>
      <lemma>die</lemma>
      <pos>PD(type=d-p,subtype=art,position=prenom)</pos>
    </w>
    <w>
      <form>vrouwe</form>
      <lemma>vrouwe</lemma>
      <pos>NOU-C(number=sg)</pos>
    </w>
    <w>
      <form>was</form>
      <lemma>zijn</lemma>
      <pos>VRB(finiteness=fin,tense=past)</pos>
    </w>
    <w>
      <form>comen</form>
      <lemma>komen</lemma>
      <pos>VRB(finiteness=pastpart)</pos>
    </w>
  </l>
  <l n="90" tokens="Niement soude v connen ghenomen" lemmas="niemand zullen u kunnen nemen">
    <w>
      <form>Niement</form>
      <lemma>niemand</lemma>
      <pos>PD(type=indef,position=free)</pos>
    </w>
    <w>
      <form>soude</form>
      <lemma>zullen</lemma>
      <pos>VRB(finiteness=fin,tense=past)</pos>
    </w>
    <w>
      <form>v</form>
      <lemma>u</lemma>
      <pos>PD(type=pers,position=free)</pos>
    </w>
    <w>
      <form>connen</form>
      <lemma>kunnen</lemma>
      <pos>VRB(finiteness=inf)</pos>
    </w>
    <w>
      <form>ghenomen</form>
      <lemma>nemen</lemma>
      <pos>VRB(finiteness=inf)</pos>
    </w>
  </l>
  <l n="91" tokens="Die grote feeste die ghonder was" lemmas="die groot feest die gunder zijn">
    <w>
      <form>Die</form>
      <lemma>die</lemma>
      <pos>PD(type=d-p,subtype=art,position=prenom)</pos>
    </w>
    <w>
      <form>grote</form>
      <lemma>groot</lemma>
      <pos>AA(degree=pos,position=prenom)</pos>
    </w>
    <w>
      <form>feeste</form>
      <lemma>feest</lemma>
      <pos>NOU-C(number=sg)</pos>
    </w>
    <w>
      <form>die</form>
      <lemma>die</lemma>
      <pos>PD(type=d-p,position=free)</pos>
    </w>
    <w>
      <form>ghonder</form>
      <lemma>gunder</lemma>
      <pos>AA(degree=pos,position=free)</pos>
    </w>
    <w>
      <form>was</form>
      <lemma>zijn</lemma>
      <pos>VRB(finiteness=fin,tense=past)</pos>
    </w>
  </l>
  <l n="92" tokens="Die abt leedese in sijn palas" lemmas="die abt leiden+zij in zijn paleis">
    <w>
      <form>Die</form>
      <lemma>die</lemma>
      <pos>PD(type=d-p,subtype=art,position=prenom)</pos>
    </w>
    <w>
      <form>abt</form>
      <lemma>abt</lemma>
      <pos>NOU-C(number=sg)</pos>
    </w>
    <w>
      <form>leedese</form>
      <lemma>leiden+zij</lemma>
      <pos>VRB(finiteness=fin,tense=past)+PD(type=pers,position=free)</pos>
    </w>
    <w>
      <form>in</form>
      <lemma>in</lemma>
      <pos>ADP(type=pre)</pos>
    </w>
    <w>
      <form>sijn</form>
      <lemma>zijn</lemma>
      <pos>PD(type=poss,position=prenom)</pos>
    </w>
    <w>
      <form>palas</form>
      <lemma>paleis</lemma>
      <pos>NOU-C(number=sg)</pos>
    </w>
  </l>
  <l n="93" tokens="Ende vraechde hoe soe hadde gheuaren" lemmas="en vragen hoe zij hebben varen">
    <w>
      <form>Ende</form>
      <lemma>en</lemma>
      <pos>CONJ(type=coor)</pos>
    </w>
    <w>
      <form>vraechde</form>
      <lemma>vragen</lemma>
      <pos>VRB(finiteness=fin,tense=past)</pos>
    </w>
    <w>
      <form>hoe</form>
      <lemma>hoe</lemma>
      <pos>ADV(type=reg)</pos>
    </w>
    <w>
      <form>soe</form>
      <lemma>zij</lemma>
      <pos>PD(type=pers,position=free)</pos>
    </w>
    <w>
      <form>hadde</form>
      <lemma>hebben</lemma>
      <pos>VRB(finiteness=fin,tense=past)</pos>
    </w>
    <w>
      <form>gheuaren</form>
      <lemma>varen</lemma>
      <pos>VRB(finiteness=pastpart)</pos>
    </w>
  </l>
  <l n="94" tokens="Daer vertracset hem sonder sparen" lemmas="daar vertraksen+het hij zonder sparen">
    <w>
      <form>Daer</form>
      <lemma>daar</lemma>
      <pos>ADV(type=reg)</pos>
    </w>
    <w>
      <form>vertracset</form>
      <lemma>vertraksen+het</lemma>
      <pos>VRB(finiteness=fin,tense=pres)+PD(type=pers,position=free)</pos>
    </w>
    <w>
      <form>hem</form>
      <lemma>hij</lemma>
      <pos>PD(type=pers,position=free)</pos>
    </w>
    <w>
      <form>sonder</form>
      <lemma>zonder</lemma>
      <pos>ADP(type=pre)</pos>
    </w>
    <w>
      <form>sparen</form>
      <lemma>sparen</lemma>
      <pos>NOU-C(number=sg)</pos>
    </w>
  </l>
  <l n="95" tokens="Hare auenture dits waer" lemmas="haar avontuur dit+zijn waar">
    <w>
      <form>Hare</form>
      <lemma>haar</lemma>
      <pos>PD(type=poss,position=prenom)</pos>
    </w>
    <w>
      <form>auenture</form>
      <lemma>avontuur</lemma>
      <pos>NOU-C(number=sg)</pos>
    </w>
    <w>
      <form>dits</form>
      <lemma>dit+zijn</lemma>
      <pos>PD(type=d-p,position=free)+VRB(finiteness=fin,tense=pres)</pos>
    </w>
    <w>
      <form>waer</form>
      <lemma>waar</lemma>
      <pos>AA(degree=pos,position=free)</pos>
    </w>
  </l>
  <l n="96" tokens="Doe rochte soe vut die lettren daer" lemmas="toen roeken zij uit die letter daar">
    <w>
      <form>Doe</form>
      <lemma>toen</lemma>
      <pos>ADV(type=reg)</pos>
    </w>
    <w>
      <form>rochte</form>
      <lemma>roeken</lemma>
      <pos>VRB(finiteness=fin,tense=past)</pos>
    </w>
    <w>
      <form>soe</form>
      <lemma>zij</lemma>
      <pos>PD(type=pers,position=free)</pos>
    </w>
    <w>
      <form>vut</form>
      <lemma>uit</lemma>
      <pos>ADP(type=pre)</pos>
    </w>
    <w>
      <form>die</form>
      <lemma>die</lemma>
      <pos>PD(type=d-p,subtype=art,position=prenom)</pos>
    </w>
    <w>
      <form>lettren</form>
      <lemma>letter</lemma>
      <pos>NOU-C(number=pl)</pos>
    </w>
    <w>
      <form>daer</form>
      <lemma>daar</lemma>
      <pos>ADV(type=reg)</pos>
    </w>
  </l>
  <l n="97" tokens="Die haer dede gheuen sinte patrijc de here" lemmas="die zij doen geven Sint Patrijc de heer">
    <w>
      <form>Die</form>
      <lemma>die</lemma>
      <pos>PD(type=d-p,position=free)</pos>
    </w>
    <w>
      <form>haer</form>
      <lemma>zij</lemma>
      <pos>PD(type=pers,position=free)</pos>
    </w>
    <w>
      <form>dede</form>
      <lemma>doen</lemma>
      <pos>VRB(finiteness=fin,tense=past)</pos>
    </w>
    <w>
      <form>gheuen</form>
      <lemma>geven</lemma>
      <pos>VRB(finiteness=inf)</pos>
    </w>
    <w>
      <form>sinte</form>
      <lemma>Sint</lemma>
      <pos>NOU-P</pos>
    </w>
    <w>
      <form>patrijc</form>
      <lemma>Patrijc</lemma>
      <pos>NOU-P</pos>
    </w>
    <w>
      <form>de</form>
      <lemma>de</lemma>
      <pos>PD(type=d-p,subtype=art,position=prenom)</pos>
    </w>
    <w>
      <form>here</form>
      <lemma>heer</lemma>
      <pos>NOU-C(number=sg)</pos>
    </w>
  </l>
  <l n="98" tokens="Doe benedietse die abt sere" lemmas="toen benedien+zij die abt zeer">
    <w>
      <form>Doe</form>
      <lemma>toen</lemma>
      <pos>ADV(type=reg)</pos>
    </w>
    <w>
      <form>benedietse</form>
      <lemma>benedien+zij</lemma>
      <pos>VRB(finiteness=fin,tense=past)+PD(type=pers,position=free)</pos>
    </w>
    <w>
      <form>die</form>
      <lemma>die</lemma>
      <pos>PD(type=d-p,subtype=art,position=prenom)</pos>
    </w>
    <w>
      <form>abt</form>
      <lemma>abt</lemma>
      <pos>NOU-C(number=sg)</pos>
    </w>
    <w>
      <form>sere</form>
      <lemma>zeer</lemma>
      <pos>ADV(type=reg)</pos>
    </w>
  </l>
  <l n="99" tokens="Dat si balcaerde vernamen" lemmas="dat zij Balkaerd vernemen">
    <w>
      <form>Dat</form>
      <lemma>dat</lemma>
      <pos>CONJ(type=sub)</pos>
    </w>
    <w>
      <form>si</form>
      <lemma>zij</lemma>
      <pos>PD(type=pers,position=free)</pos>
    </w>
    <w>
      <form>balcaerde</form>
      <lemma>Balkaerd</lemma>
      <pos>NOU-P</pos>
    </w>
    <w>
      <form>vernamen</form>
      <lemma>vernemen</lemma>
      <pos>VRB(finiteness=fin,tense=past)</pos>
    </w>
  </l>
  <l n="100" tokens="Jn mi also ic spreke" lemmas="in ik alzo ik spreken">
    <w>
      <form>Jn</form>
      <lemma>in</lemma>
      <pos>ADP(type=pre)</pos>
    </w>
    <w>
      <form>mi</form>
      <lemma>ik</lemma>
      <pos>PD(type=pers,position=free)</pos>
    </w>
    <w>
      <form>also</form>
      <lemma>alzo</lemma>
      <pos>CONJ(type=sub)</pos>
    </w>
    <w>
      <form>ic</form>
      <lemma>ik</lemma>
      <pos>PD(type=pers,position=free)</pos>
    </w>
    <w>
      <form>spreke</form>
      <lemma>spreken</lemma>
      <pos>VRB(finiteness=fin,tense=pres)</pos>
    </w>
  </l>
  <l n="101" tokens="Nerghent of hebbic breke" lemmas="nergen of hebben+ik breek">
    <w>
      <form>Nerghent</form>
      <lemma>nergen</lemma>
      <pos>ADV(type=reg)</pos>
    </w>
    <w>
      <form>of</form>
      <lemma>of</lemma>
      <pos>CONJ(type=coor)</pos>
    </w>
    <w>
      <form>hebbic</form>
      <lemma>hebben+ik</lemma>
      <pos>VRB(finiteness=fin,tense=pres)+PD(type=pers,position=free)</pos>
    </w>
    <w>
      <form>breke</form>
      <lemma>breek</lemma>
      <pos>NOU-C(number=sg)</pos>
    </w>
  </l>
  <l n="102" tokens="Sonder dat ic niet en mach" lemmas="zonder dat ik niet ne mogen">
    <w>
      <form>Sonder</form>
      <lemma>zonder</lemma>
      <pos>ADP(type=pre)</pos>
    </w>
    <w>
      <form>dat</form>
      <lemma>dat</lemma>
      <pos>CONJ(type=sub)</pos>
    </w>
    <w>
      <form>ic</form>
      <lemma>ik</lemma>
      <pos>PD(type=pers,position=free)</pos>
    </w>
    <w>
      <form>niet</form>
      <lemma>niet</lemma>
      <pos>ADV(type=reg)</pos>
    </w>
    <w>
      <form>en</form>
      <lemma>ne</lemma>
      <pos>ADV(type=reg)</pos>
    </w>
    <w>
      <form>mach</form>
      <lemma>mogen</lemma>
      <pos>VRB(finiteness=fin,tense=pres)</pos>
    </w>
  </l>
  <l n="103" tokens="Bi v wesen nacht ende dach" lemmas="bij u wezen nacht en dag">
    <w>
      <form>Bi</form>
      <lemma>bij</lemma>
      <pos>ADP(type=pre)</pos>
    </w>
    <w>
      <form>v</form>
      <lemma>u</lemma>
      <pos>PD(type=pers,position=free)</pos>
    </w>
    <w>
      <form>wesen</form>
      <lemma>wezen</lemma>
      <pos>VRB(finiteness=inf)</pos>
    </w>
    <w>
      <form>nacht</form>
      <lemma>nacht</lemma>
      <pos>NOU-C(number=sg)</pos>
    </w>
    <w>
      <form>ende</form>
      <lemma>en</lemma>
      <pos>CONJ(type=coor)</pos>
    </w>
    <w>
      <form>dach</form>
      <lemma>dag</lemma>
      <pos>NOU-C(number=sg)</pos>
    </w>
  </l>
  <l n="104" tokens="Houesch lief madelghijs" lemmas="Hovees lief Magdalgijs">
    <w>
      <form>Houesch</form>
      <lemma>Hovees</lemma>
      <pos>AA(degree=pos,position=prenom)</pos>
    </w>
    <w>
      <form>lief</form>
      <lemma>lief</lemma>
      <pos>NOU-C(number=sg)</pos>
    </w>
    <w>
      <form>madelghijs</form>
      <lemma>Magdalgijs</lemma>
      <pos>NOU-P</pos>
    </w>
  </l>
  <l n="105" tokens="Jn deser claghe in deser wijs" lemmas="in deze klaag in deze wijs">
    <w>
      <form>Jn</form>
      <lemma>in</lemma>
      <pos>ADP(type=pre)</pos>
    </w>
    <w>
      <form>deser</form>
      <lemma>deze</lemma>
      <pos>PD(type=d-p,subtype=oth,position=prenom)</pos>
    </w>
    <w>
      <form>claghe</form>
      <lemma>klaag</lemma>
      <pos>NOU-C(number=sg)</pos>
    </w>
    <w>
      <form>in</form>
      <lemma>in</lemma>
      <pos>ADP(type=pre)</pos>
    </w>
    <w>
      <form>deser</form>
      <lemma>deze</lemma>
      <pos>PD(type=d-p,subtype=oth,position=prenom)</pos>
    </w>
    <w>
      <form>wijs</form>
      <lemma>wijs</lemma>
      <pos>NOU-C(number=sg)</pos>
    </w>
  </l>
  <l n="106" tokens="Lach die vrouwe oriande" lemmas="lachen die vrouwe Oriande">
    <w>
      <form>Lach</form>
      <lemma>lachen</lemma>
      <pos>VRB(finiteness=fin,tense=past)</pos>
    </w>
    <w>
      <form>die</form>
      <lemma>die</lemma>
      <pos>PD(type=d-p,subtype=art,position=prenom)</pos>
    </w>
    <w>
      <form>vrouwe</form>
      <lemma>vrouwe</lemma>
      <pos>NOU-C(number=sg)</pos>
    </w>
    <w>
      <form>oriande</form>
      <lemma>Oriande</lemma>
      <pos>NOU-P</pos>
    </w>
  </l>
  <l n="107" tokens="Die zee dreef van den eylande" lemmas="die zee drijven van de eiland">
    <w>
      <form>Die</form>
      <lemma>die</lemma>
      <pos>PD(type=d-p,subtype=art,position=prenom)</pos>
    </w>
    <w>
      <form>zee</form>
      <lemma>zee</lemma>
      <pos>NOU-C(number=sg)</pos>
    </w>
    <w>
      <form>dreef</form>
      <lemma>drijven</lemma>
      <pos>VRB(finiteness=fin,tense=past)</pos>
    </w>
    <w>
      <form>van</form>
      <lemma>van</lemma>
      <pos>ADP(type=pre)</pos>
    </w>
    <w>
      <form>den</form>
      <lemma>de</lemma>
      <pos>PD(type=d-p,subtype=art,position=prenom)</pos>
    </w>
    <w>
      <form>eylande</form>
      <lemma>eiland</lemma>
      <pos>NOU-C(number=sg)</pos>
    </w>
  </l>
  <l n="108" tokens="Tscip daer oriande was in" lemmas="dat+schip daar Oriande zijn in">
    <w>
      <form>Tscip</form>
      <lemma>dat+schip</lemma>
      <pos>PD(type=d-p,subtype=art,position=prenom)+NOU-C(number=sg)</pos>
    </w>
    <w>
      <form>daer</form>
      <lemma>daar</lemma>
      <pos>ADV(type=reg)</pos>
    </w>
    <w>
      <form>oriande</form>
      <lemma>Oriande</lemma>
      <pos>NOU-P</pos>
    </w>
    <w>
      <form>was</form>
      <lemma>zijn</lemma>
      <pos>VRB(finiteness=fin,tense=past)</pos>
    </w>
    <w>
      <form>in</form>
      <lemma>in</lemma>
      <pos>ADP(type=pre)</pos>
    </w>
  </l>
  <l n="109" tokens="Die hadde enen drouuen sin" lemmas="die hebben een droef zin">
    <w>
      <form>Die</form>
      <lemma>die</lemma>
      <pos>PD(type=d-p,position=free)</pos>
    </w>
    <w>
      <form>hadde</form>
      <lemma>hebben</lemma>
      <pos>VRB(finiteness=fin,tense=past)</pos>
    </w>
    <w>
      <form>enen</form>
      <lemma>een</lemma>
      <pos>PD(type=indef,subtype=art,position=prenom)</pos>
    </w>
    <w>
      <form>drouuen</form>
      <lemma>droef</lemma>
      <pos>AA(degree=pos,position=prenom)</pos>
    </w>
    <w>
      <form>sin</form>
      <lemma>zin</lemma>
      <pos>NOU-C(number=sg)</pos>
    </w>
  </l>
  <l n="110" tokens="Om den speelman nigrieel" lemmas="om de speelman Nigrieel">
    <w>
      <form>Om</form>
      <lemma>om</lemma>
      <pos>ADP(type=pre)</pos>
    </w>
    <w>
      <form>den</form>
      <lemma>de</lemma>
      <pos>PD(type=d-p,subtype=art,position=prenom)</pos>
    </w>
    <w>
      <form>speelman</form>
      <lemma>speelman</lemma>
      <pos>NOU-C(number=sg)</pos>
    </w>
    <w>
      <form>nigrieel</form>
      <lemma>Nigrieel</lemma>
      <pos>NOU-P</pos>
    </w>
  </l>
  <l n="111" tokens="So gaet hi kikelen ende duwen" lemmas="zo gaan hij kikkelen en duwen">
    <w>
      <form>So</form>
      <lemma>zo</lemma>
      <pos>ADV(type=reg)</pos>
    </w>
    <w>
      <form>gaet</form>
      <lemma>gaan</lemma>
      <pos>VRB(finiteness=fin,tense=pres)</pos>
    </w>
    <w>
      <form>hi</form>
      <lemma>hij</lemma>
      <pos>PD(type=pers,position=free)</pos>
    </w>
    <w>
      <form>kikelen</form>
      <lemma>kikkelen</lemma>
      <pos>VRB(finiteness=inf)</pos>
    </w>
    <w>
      <form>ende</form>
      <lemma>en</lemma>
      <pos>CONJ(type=coor)</pos>
    </w>
    <w>
      <form>duwen</form>
      <lemma>duwen</lemma>
      <pos>VRB(finiteness=inf)</pos>
    </w>
  </l>
  <l n="112" tokens="Om ons sijn doen es al ghescict" lemmas="om ons zijn doen zijn al geschikt">
    <w>
      <form>Om</form>
      <lemma>om</lemma>
      <pos>ADP(type=pre)</pos>
    </w>
    <w>
      <form>ons</form>
      <lemma>ons</lemma>
      <pos>PD(type=pers,position=free)</pos>
    </w>
    <w>
      <form>sijn</form>
      <lemma>zijn</lemma>
      <pos>PD(type=poss,position=prenom)</pos>
    </w>
    <w>
      <form>doen</form>
      <lemma>doen</lemma>
      <pos>NOU-C(number=sg)</pos>
    </w>
    <w>
      <form>es</form>
      <lemma>zijn</lemma>
      <pos>VRB(finiteness=fin,tense=pres)</pos>
    </w>
    <w>
      <form>al</form>
      <lemma>al</lemma>
      <pos>PD(type=indef,position=free)</pos>
    </w>
    <w>
      <form>ghescict</form>
      <lemma>geschikt</lemma>
      <pos>AA(degree=pos,position=free)</pos>
    </w>
  </l>
  <l n="113" tokens="O vrouwe die noit reet in sambuwen" lemmas="o vrouwe die nooit rijten in Sambuwe">
    <w>
      <form>O</form>
      <lemma>o</lemma>
      <pos>INT</pos>
    </w>
    <w>
      <form>vrouwe</form>
      <lemma>vrouwe</lemma>
      <pos>NOU-C(number=sg)</pos>
    </w>
    <w>
      <form>die</form>
      <lemma>die</lemma>
      <pos>PD(type=d-p,position=free)</pos>
    </w>
    <w>
      <form>noit</form>
      <lemma>nooit</lemma>
      <pos>ADV(type=reg)</pos>
    </w>
    <w>
      <form>reet</form>
      <lemma>rijten</lemma>
      <pos>VRB(finiteness=fin,tense=pres)</pos>
    </w>
    <w>
      <form>in</form>
      <lemma>in</lemma>
      <pos>ADP(type=pre)</pos>
    </w>
    <w>
      <form>sambuwen</form>
      <lemma>Sambuwe</lemma>
      <pos>NOU-P</pos>
    </w>
  </l>
  <l n="114" tokens="Van sathanase den fellen ruwen" lemmas="van Satanas de fel ruwen">
    <w>
      <form>Van</form>
      <lemma>van</lemma>
      <pos>ADP(type=pre)</pos>
    </w>
    <w>
      <form>sathanase</form>
      <lemma>Satanas</lemma>
      <pos>NOU-P</pos>
    </w>
    <w>
      <form>den</form>
      <lemma>de</lemma>
      <pos>PD(type=d-p,subtype=art,position=prenom)</pos>
    </w>
    <w>
      <form>fellen</form>
      <lemma>fel</lemma>
      <pos>AA(degree=pos,position=prenom)</pos>
    </w>
    <w>
      <form>ruwen</form>
      <lemma>ruwen</lemma>
      <pos>NOU-C(number=sg)</pos>
    </w>
  </l>
  <l n="115" tokens="Die met quaetheden es dorstict" lemmas="die met kwaadheid zijn dorstict">
    <w>
      <form>Die</form>
      <lemma>die</lemma>
      <pos>PD(type=d-p,position=free)</pos>
    </w>
    <w>
      <form>met</form>
      <lemma>met</lemma>
      <pos>ADP(type=pre)</pos>
    </w>
    <w>
      <form>quaetheden</form>
      <lemma>kwaadheid</lemma>
      <pos>NOU-C(number=pl)</pos>
    </w>
    <w>
      <form>es</form>
      <lemma>zijn</lemma>
      <pos>VRB(finiteness=fin,tense=pres)</pos>
    </w>
    <w>
      <form>dorstict</form>
      <lemma>dorstict</lemma>
      <pos>AA(degree=pos,position=free)</pos>
    </w>
  </l>
  <l n="116" tokens="Ghi moet ons verden van sinen tortuwen" lemmas="gij moeten ons vreden van zijn tortuwe">
    <w>
      <form>Ghi</form>
      <lemma>gij</lemma>
      <pos>PD(type=pers,position=free)</pos>
    </w>
    <w>
      <form>moet</form>
      <lemma>moeten</lemma>
      <pos>VRB(finiteness=fin,tense=pres)</pos>
    </w>
    <w>
      <form>ons</form>
      <lemma>ons</lemma>
      <pos>PD(type=pers,position=free)</pos>
    </w>
    <w>
      <form>verden</form>
      <lemma>vreden</lemma>
      <pos>VRB(finiteness=inf)</pos>
    </w>
    <w>
      <form>van</form>
      <lemma>van</lemma>
      <pos>ADP(type=pre)</pos>
    </w>
    <w>
      <form>sinen</form>
      <lemma>zijn</lemma>
      <pos>PD(type=poss,position=prenom)</pos>
    </w>
    <w>
      <form>tortuwen</form>
      <lemma>tortuwe</lemma>
      <pos>NOU-C(number=pl)</pos>
    </w>
  </l>
  <l n="117" tokens="Maer hier bouen metten uwen" lemmas="maar hier boven met+de uwe">
    <w>
      <form>Maer</form>
      <lemma>maar</lemma>
      <pos>CONJ(type=coor)</pos>
    </w>
    <w>
      <form>hier</form>
      <lemma>hier</lemma>
      <pos>ADV(type=pron)</pos>
    </w>
    <w>
      <form>bouen</form>
      <lemma>boven</lemma>
      <pos>ADV(type=pron)</pos>
    </w>
    <w>
      <form>metten</form>
      <lemma>met+de</lemma>
      <pos>ADP(type=pre)+PD(type=d-p,subtype=art,position=prenom)</pos>
    </w>
    <w>
      <form>uwen</form>
      <lemma>uwe</lemma>
      <pos>NOU-C(number=pl)</pos>
    </w>
  </l>
  <l n="118" tokens="Moeten comen die hebben predict" lemmas="moeten komen die hebben prediken">
    <w>
      <form>Moeten</form>
      <lemma>moeten</lemma>
      <pos>VRB(finiteness=inf)</pos>
    </w>
    <w>
      <form>comen</form>
      <lemma>komen</lemma>
      <pos>VRB(finiteness=inf)</pos>
    </w>
    <w>
      <form>die</form>
      <lemma>die</lemma>
      <pos>PD(type=d-p,position=free)</pos>
    </w>
    <w>
      <form>hebben</form>
      <lemma>hebben</lemma>
      <pos>VRB(finiteness=fin,tense=pres)</pos>
    </w>
    <w>
      <form>predict</form>
      <lemma>prediken</lemma>
      <pos>VRB(finiteness=pastpart)</pos>
    </w>
  </l>
  <l n="119" tokens="Gods gheboornesse ombeulict" lemmas="God geboornis omvlicen">
    <w>
      <form>Gods</form>
      <lemma>God</lemma>
      <pos>NOU-P</pos>
    </w>
    <w>
      <form>gheboornesse</form>
      <lemma>geboornis</lemma>
      <pos>NOU-C(number=sg)</pos>
    </w>
    <w>
      <form>ombeulict</form>
      <lemma>omvlicen</lemma>
      <pos>VRB(finiteness=pastpart)</pos>
    </w>
  </l>
  <l n="120" tokens="Dus voer die vrouwe op ende neder" lemmas="dus voor die vrouwe op en neder">
    <w>
      <form>Dus</form>
      <lemma>dus</lemma>
      <pos>ADV(type=reg)</pos>
    </w>
    <w>
      <form>voer</form>
      <lemma>voor</lemma>
      <pos>ADP(type=pre)</pos>
    </w>
    <w>
      <form>die</form>
      <lemma>die</lemma>
      <pos>PD(type=d-p,subtype=art,position=prenom)</pos>
    </w>
    <w>
      <form>vrouwe</form>
      <lemma>vrouwe</lemma>
      <pos>NOU-C(number=sg)</pos>
    </w>
    <w>
      <form>op</form>
      <lemma>op</lemma>
      <pos>ADV(type=reg)</pos>
    </w>
    <w>
      <form>ende</form>
      <lemma>en</lemma>
      <pos>CONJ(type=coor)</pos>
    </w>
    <w>
      <form>neder</form>
      <lemma>neder</lemma>
      <pos>ADV(type=reg)</pos>
    </w>
  </l>
  <l n="121" tokens="Jn de zee voert ende weder" lemmas="in de zee voort en weder">
    <w>
      <form>Jn</form>
      <lemma>in</lemma>
      <pos>ADP(type=pre)</pos>
    </w>
    <w>
      <form>de</form>
      <lemma>de</lemma>
      <pos>PD(type=d-p,subtype=art,position=prenom)</pos>
    </w>
    <w>
      <form>zee</form>
      <lemma>zee</lemma>
      <pos>NOU-C(number=sg)</pos>
    </w>
    <w>
      <form>voert</form>
      <lemma>voort</lemma>
      <pos>ADV(type=reg)</pos>
    </w>
    <w>
      <form>ende</form>
      <lemma>en</lemma>
      <pos>CONJ(type=coor)</pos>
    </w>
    <w>
      <form>weder</form>
      <lemma>weder</lemma>
      <pos>ADV(type=reg)</pos>
    </w>
  </l>
  <l n="122" tokens="Daer soe uele wonders vant" lemmas="daar zo eel wonder vinden">
    <w>
      <form>Daer</form>
      <lemma>daar</lemma>
      <pos>ADV(type=reg)</pos>
    </w>
    <w>
      <form>soe</form>
      <lemma>zo</lemma>
      <pos>ADV(type=reg)</pos>
    </w>
    <w>
      <form>uele</form>
      <lemma>eel</lemma>
      <pos>PD(type=indef,subtype=oth,position=prenom)</pos>
    </w>
    <w>
      <form>wonders</form>
      <lemma>wonder</lemma>
      <pos>NOU-C(number=sg)</pos>
    </w>
    <w>
      <form>vant</form>
      <lemma>vinden</lemma>
      <pos>VRB(finiteness=fin,tense=past)</pos>
    </w>
  </l>
  <l n="123" tokens="So langhe voer die vrouwe faeliant" lemmas="zo lang voor die vrouwe valiant">
    <w>
      <form>So</form>
      <lemma>zo</lemma>
      <pos>ADV(type=reg)</pos>
    </w>
    <w>
      <form>langhe</form>
      <lemma>lang</lemma>
      <pos>ADV(type=reg)</pos>
    </w>
    <w>
      <form>voer</form>
      <lemma>voor</lemma>
      <pos>ADP(type=pre)</pos>
    </w>
    <w>
      <form>die</form>
      <lemma>die</lemma>
      <pos>PD(type=d-p,subtype=art,position=prenom)</pos>
    </w>
    <w>
      <form>vrouwe</form>
      <lemma>vrouwe</lemma>
      <pos>NOU-C(number=sg)</pos>
    </w>
    <w>
      <form>faeliant</form>
      <lemma>valiant</lemma>
      <pos>AA(degree=pos,position=postnom)</pos>
    </w>
  </l>
  <l n="124" tokens="Dat soe ghemoete enen man" lemmas="dat zo gemoeten een man">
    <w>
      <form>Dat</form>
      <lemma>dat</lemma>
      <pos>CONJ(type=sub)</pos>
    </w>
    <w>
      <form>soe</form>
      <lemma>zo</lemma>
      <pos>ADV(type=reg)</pos>
    </w>
    <w>
      <form>ghemoete</form>
      <lemma>gemoeten</lemma>
      <pos>VRB(finiteness=fin,tense=past)</pos>
    </w>
    <w>
      <form>enen</form>
      <lemma>een</lemma>
      <pos>PD(type=indef,subtype=art,position=prenom)</pos>
    </w>
    <w>
      <form>man</form>
      <lemma>man</lemma>
      <pos>NOU-C(number=sg)</pos>
    </w>
  </l>
  <l n="125" tokens="Tieghen haer comen die sere stan" lemmas="tegen zij komen die zeer stenen">
    <w>
      <form>Tieghen</form>
      <lemma>tegen</lemma>
      <pos>ADP(type=pre)</pos>
    </w>
    <w>
      <form>haer</form>
      <lemma>zij</lemma>
      <pos>PD(type=pers,position=free)</pos>
    </w>
    <w>
      <form>comen</form>
      <lemma>komen</lemma>
      <pos>VRB(finiteness=inf)</pos>
    </w>
    <w>
      <form>die</form>
      <lemma>die</lemma>
      <pos>PD(type=d-p,position=free)</pos>
    </w>
    <w>
      <form>sere</form>
      <lemma>zeer</lemma>
      <pos>ADV(type=reg)</pos>
    </w>
    <w>
      <form>stan</form>
      <lemma>stenen</lemma>
      <pos>VRB(finiteness=fin,tense=past)</pos>
    </w>
  </l>
  <l n="126" tokens="Vlietende op ene planke" lemmas="vlieten op een plank">
    <w>
      <form>Vlietende</form>
      <lemma>vlieten</lemma>
      <pos>VRB(finiteness=prespart)</pos>
    </w>
    <w>
      <form>op</form>
      <lemma>op</lemma>
      <pos>ADP(type=pre)</pos>
    </w>
    <w>
      <form>ene</form>
      <lemma>een</lemma>
      <pos>PD(type=indef,subtype=art,position=prenom)</pos>
    </w>
    <w>
      <form>planke</form>
      <lemma>plank</lemma>
      <pos>NOU-C(number=sg)</pos>
    </w>
  </l>
  <l n="127" tokens="Hi beefde sere metten lanken" lemmas="hij beven zeer met+de lank">
    <w>
      <form>Hi</form>
      <lemma>hij</lemma>
      <pos>PD(type=pers,position=free)</pos>
    </w>
    <w>
      <form>beefde</form>
      <lemma>beven</lemma>
      <pos>VRB(finiteness=fin,tense=past)</pos>
    </w>
    <w>
      <form>sere</form>
      <lemma>zeer</lemma>
      <pos>ADV(type=reg)</pos>
    </w>
    <w>
      <form>metten</form>
      <lemma>met+de</lemma>
      <pos>ADP(type=pre)+PD(type=d-p,subtype=art,position=prenom)</pos>
    </w>
    <w>
      <form>lanken</form>
      <lemma>lank</lemma>
      <pos>NOU-C(number=pl)</pos>
    </w>
  </l>
  <l n="128" tokens="Bedi sine cledren waren of ghewasschen" lemmas="bedie zijn kleed zijn of wassen">
    <w>
      <form>Bedi</form>
      <lemma>bedie</lemma>
      <pos>CONJ(type=sub)</pos>
    </w>
    <w>
      <form>sine</form>
      <lemma>zijn</lemma>
      <pos>PD(type=poss,position=prenom)</pos>
    </w>
    <w>
      <form>cledren</form>
      <lemma>kleed</lemma>
      <pos>NOU-C(number=pl)</pos>
    </w>
    <w>
      <form>waren</form>
      <lemma>zijn</lemma>
      <pos>VRB(finiteness=fin,tense=past)</pos>
    </w>
    <w>
      <form>of</form>
      <lemma>of</lemma>
      <pos>CONJ(type=coor)</pos>
    </w>
    <w>
      <form>ghewasschen</form>
      <lemma>wassen</lemma>
      <pos>VRB(finiteness=pastpart)</pos>
    </w>
  </l>
  <l n="129" tokens="Metten watre ghelijc den asschen" lemmas="met+de water gelijk de as">
    <w>
      <form>Metten</form>
      <lemma>met+de</lemma>
      <pos>ADP(type=pre)+PD(type=d-p,subtype=art,position=prenom)</pos>
    </w>
    <w>
      <form>watre</form>
      <lemma>water</lemma>
      <pos>NOU-C(number=sg)</pos>
    </w>
    <w>
      <form>ghelijc</form>
      <lemma>gelijk</lemma>
      <pos>CONJ(type=sub)</pos>
    </w>
    <w>
      <form>den</form>
      <lemma>de</lemma>
      <pos>PD(type=d-p,subtype=art,position=prenom)</pos>
    </w>
    <w>
      <form>asschen</form>
      <lemma>as</lemma>
      <pos>NOU-C(number=pl)</pos>
    </w>
  </l>
  <l n="130" tokens="Sat hi bleec ende onghedaen" lemmas="zitten hij bleek en ongedaan">
    <w>
      <form>Sat</form>
      <lemma>zitten</lemma>
      <pos>VRB(finiteness=fin,tense=past)</pos>
    </w>
    <w>
      <form>hi</form>
      <lemma>hij</lemma>
      <pos>PD(type=pers,position=free)</pos>
    </w>
    <w>
      <form>bleec</form>
      <lemma>bleek</lemma>
      <pos>AA(degree=pos,position=free)</pos>
    </w>
    <w>
      <form>ende</form>
      <lemma>en</lemma>
      <pos>CONJ(type=coor)</pos>
    </w>
    <w>
      <form>onghedaen</form>
      <lemma>ongedaan</lemma>
      <pos>AA(degree=pos,position=free)</pos>
    </w>
  </l>
  <l n="131" tokens="Hi riep god ghi moet nu saen" lemmas="hij roepen God gij moeten nu zaan">
    <w>
      <form>Hi</form>
      <lemma>hij</lemma>
      <pos>PD(type=pers,position=free)</pos>
    </w>
    <w>
      <form>riep</form>
      <lemma>roepen</lemma>
      <pos>VRB(finiteness=fin,tense=past)</pos>
    </w>
    <w>
      <form>god</form>
      <lemma>God</lemma>
      <pos>NOU-P</pos>
    </w>
    <w>
      <form>ghi</form>
      <lemma>gij</lemma>
      <pos>PD(type=pers,position=free)</pos>
    </w>
    <w>
      <form>moet</form>
      <lemma>moeten</lemma>
      <pos>VRB(finiteness=fin,tense=pres)</pos>
    </w>
    <w>
      <form>nu</form>
      <lemma>nu</lemma>
      <pos>ADV(type=reg)</pos>
    </w>
    <w>
      <form>saen</form>
      <lemma>zaan</lemma>
      <pos>ADV(type=reg)</pos>
    </w>
  </l>
  <l n="132" tokens="Betren mijn swaer doghen" lemmas="beteren mijn zwaar dogen">
    <w>
      <form>Betren</form>
      <lemma>beteren</lemma>
      <pos>VRB(finiteness=inf)</pos>
    </w>
    <w>
      <form>mijn</form>
      <lemma>mijn</lemma>
      <pos>PD(type=poss,position=prenom)</pos>
    </w>
    <w>
      <form>swaer</form>
      <lemma>zwaar</lemma>
      <pos>AA(degree=pos,position=prenom)</pos>
    </w>
    <w>
      <form>doghen</form>
      <lemma>dogen</lemma>
      <pos>NOU-C(number=pl)</pos>
    </w>
  </l>
  <l n="133" tokens="Die tranen braken hem vten oghen" lemmas="die traan breken hij uit+de oog">
    <w>
      <form>Die</form>
      <lemma>die</lemma>
      <pos>PD(type=d-p,subtype=art,position=prenom)</pos>
    </w>
    <w>
      <form>tranen</form>
      <lemma>traan</lemma>
      <pos>NOU-C(number=pl)</pos>
    </w>
    <w>
      <form>braken</form>
      <lemma>breken</lemma>
      <pos>VRB(finiteness=fin,tense=past)</pos>
    </w>
    <w>
      <form>hem</form>
      <lemma>hij</lemma>
      <pos>PD(type=pers,position=free)</pos>
    </w>
    <w>
      <form>vten</form>
      <lemma>uit+de</lemma>
      <pos>ADP(type=pre)+PD(type=d-p,subtype=art,position=prenom)</pos>
    </w>
    <w>
      <form>oghen</form>
      <lemma>oog</lemma>
      <pos>NOU-C(number=pl)</pos>
    </w>
  </l>
  <l n="134" tokens="Sine droufheit was menichfout" lemmas="zijn droefheid zijn menigvoud">
    <w>
      <form>Sine</form>
      <lemma>zijn</lemma>
      <pos>PD(type=poss,position=prenom)</pos>
    </w>
    <w>
      <form>droufheit</form>
      <lemma>droefheid</lemma>
      <pos>NOU-C(number=sg)</pos>
    </w>
    <w>
      <form>was</form>
      <lemma>zijn</lemma>
      <pos>VRB(finiteness=fin,tense=past)</pos>
    </w>
    <w>
      <form>menichfout</form>
      <lemma>menigvoud</lemma>
      <pos>AA(degree=pos,position=free)</pos>
    </w>
  </l>
  <l n="135" tokens="Hi hadde hongher ende cout" lemmas="hij hebben honger en koud">
    <w>
      <form>Hi</form>
      <lemma>hij</lemma>
      <pos>PD(type=pers,position=free)</pos>
    </w>
    <w>
      <form>hadde</form>
      <lemma>hebben</lemma>
      <pos>VRB(finiteness=fin,tense=past)</pos>
    </w>
    <w>
      <form>hongher</form>
      <lemma>honger</lemma>
      <pos>NOU-C(number=sg)</pos>
    </w>
    <w>
      <form>ende</form>
      <lemma>en</lemma>
      <pos>CONJ(type=coor)</pos>
    </w>
    <w>
      <form>cout</form>
      <lemma>koud</lemma>
      <pos>NOU-C(number=sg)</pos>
    </w>
  </l>
  <l n="136" tokens="Also hi vloot moeder naect" lemmas="alzo hij vlieten moeder naakt">
    <w>
      <form>Also</form>
      <lemma>alzo</lemma>
      <pos>CONJ(type=sub)</pos>
    </w>
    <w>
      <form>hi</form>
      <lemma>hij</lemma>
      <pos>PD(type=pers,position=free)</pos>
    </w>
    <w>
      <form>vloot</form>
      <lemma>vlieten</lemma>
      <pos>VRB(finiteness=fin,tense=past)</pos>
    </w>
    <w>
      <form>moeder</form>
      <lemma>moeder</lemma>
      <pos>NOU-C(number=sg)</pos>
    </w>
    <w>
      <form>naect</form>
      <lemma>naakt</lemma>
      <pos>AA(degree=pos,position=free)</pos>
    </w>
  </l>
  <l n="137" tokens="Oriande was wel gheraect" lemmas="Oriande zijn wel raken">
    <w>
      <form>Oriande</form>
      <lemma>Oriande</lemma>
      <pos>NOU-P</pos>
    </w>
    <w>
      <form>was</form>
      <lemma>zijn</lemma>
      <pos>VRB(finiteness=fin,tense=past)</pos>
    </w>
    <w>
      <form>wel</form>
      <lemma>wel</lemma>
      <pos>ADV(type=reg)</pos>
    </w>
    <w>
      <form>gheraect</form>
      <lemma>raken</lemma>
      <pos>VRB(finiteness=pastpart)</pos>
    </w>
  </l>
  <l n="138" tokens="Soe hiet balkare alsoe eerst mochte" lemmas="zo heten Balkara alzo eerst mogen">
    <w>
      <form>Soe</form>
      <lemma>zo</lemma>
      <pos>ADV(type=reg)</pos>
    </w>
    <w>
      <form>hiet</form>
      <lemma>heten</lemma>
      <pos>VRB(finiteness=fin,tense=past)</pos>
    </w>
    <w>
      <form>balkare</form>
      <lemma>Balkara</lemma>
      <pos>NOU-P</pos>
    </w>
    <w>
      <form>alsoe</form>
      <lemma>alzo</lemma>
      <pos>ADV(type=reg)</pos>
    </w>
    <w>
      <form>eerst</form>
      <lemma>eerst</lemma>
      <pos>ADV(type=reg)</pos>
    </w>
    <w>
      <form>mochte</form>
      <lemma>mogen</lemma>
      <pos>VRB(finiteness=fin,tense=past)</pos>
    </w>
  </l>
  <l n="139" tokens="Dat hi den man in haer scip brochte" lemmas="dat hij de man in haar schip brengen">
    <w>
      <form>Dat</form>
      <lemma>dat</lemma>
      <pos>CONJ(type=sub)</pos>
    </w>
    <w>
      <form>hi</form>
      <lemma>hij</lemma>
      <pos>PD(type=pers,position=free)</pos>
    </w>
    <w>
      <form>den</form>
      <lemma>de</lemma>
      <pos>PD(type=d-p,subtype=art,position=prenom)</pos>
    </w>
    <w>
      <form>man</form>
      <lemma>man</lemma>
      <pos>NOU-C(number=sg)</pos>
    </w>
    <w>
      <form>in</form>
      <lemma>in</lemma>
      <pos>ADP(type=pre)</pos>
    </w>
    <w>
      <form>haer</form>
      <lemma>haar</lemma>
      <pos>PD(type=poss,position=prenom)</pos>
    </w>
    <w>
      <form>scip</form>
      <lemma>schip</lemma>
      <pos>NOU-C(number=sg)</pos>
    </w>
    <w>
      <form>brochte</form>
      <lemma>brengen</lemma>
      <pos>VRB(finiteness=fin,tense=past)</pos>
    </w>
  </l>
</text>
